Workbook

Sheet INICIO
B1: v9.0 · 1 de septiembre de 2026 · modelo de cliente de 22 factores
B2: HERRAMIENTA DE EVALUACIÓN DE RIESGO EBR · ACTIVIDADES VULNERABLES (LFPIORPI)
B3: Determina tu riesgo inherente y residual conforme a las Reglas (Cap. II Quáter y III Bis/III Ter), la Guía CNBV y GAFILAT.
B4: NOTA: trae un EJEMPLO completo precargado (una inmobiliaria, fracción V). Todo lo que está en texto azul es del ejemplo: sustitúyelo por lo tuyo.
B5: Paso 1 de 10 · Configura antes en PARÁMETROS · Sigue: A9 secciones 1 y 2 (ENR y conciliación), y luego A1
B6: CÓMO USAR
B7: 1. Abre primero PARÁMETROS: actualiza el valor de la UMA y declara tu nivel de tolerancia al riesgo. Se hace una vez al año.
B8: 2. Aquí en INICIO elige tu Actividad Vulnerable —se precargan tus umbrales— y captura los datos de tu entidad y las tres cifras de doce meses (Art. 10 Septies 2, fr. II).
B9: 3. Ve a «A9» secciones 1 y 2 ANTES de capturar nada: la Evaluación Nacional de Riesgos que tomaste en cuenta, y la conciliación de tus tres cifras contra tu mecanismo automatizado.
B10: 4. En «A1 EXPOSICION» reparte 100% entre Alto/Medio/Bajo en cada indicador y asigna los dos pesos —el del indicador y el del elemento— con su justificación escrita. En «A2» describe qué pasaría si el riesgo se materializa.
B11: 5. Revisa el inherente en «A3». En «A4 CONTROLES MINIMOS» califica las 14 obligaciones del Manual (Art. 37 Bis) y anota numeral y evidencia: sin los dos, la obligación cuenta cero. Los controles extra van en «A4 BIS».
B12: 6. Lee el residual en «A5» y el resumen en «A6». Cierra en «A8» (tolerancia, fecha de revisión y plan de acción) y en «A9» secciones 3 a 7 (aprobación, plazos y conservación).
... B14: LEYENDA
B15: Amarillo = tú capturas | C15: Verde = viene de otra hoja | D15: Negro = se calcula solo
B16: Texto azul = dato de ejemplo: sustitúyelo | C16: Gris = referencia fija: no se edita | D16: Texto rojo = aviso · Relleno azul = resultado clave
B17: PASO 1 · SELECCIONA TU ACTIVIDAD VULNERABLE
B18: Actividad Vulnerable: | C18: V - Construcción/comercialización inmuebles
B19: Fracción Art. 17: | C19: =IFERROR(INDEX(CATALOGO!$C$6:$C$35,MATCH($C$18,CATALOGO!$E$6:$E$35,0)),"")
B20: Umbral de identificación (UMA): | C20: =IFERROR(INDEX(CATALOGO!$F$6:$F$35,MATCH($C$18,CATALOGO!$E$6:$E$35,0)),"") | D20: Umbral de aviso (UMA): | E20: =IFERROR(INDEX(CATALOGO!$G$6:$G$35,MATCH($C$18,CATALOGO!$E$6:$E$35,0)),"")
B21: Umbral de identificación (MXN): | C21: =IFERROR(INDEX(CATALOGO!$H$6:$H$35,MATCH($C$18,CATALOGO!$E$6:$E$35,0)),"") | D21: Umbral de aviso (MXN): | E21: =IFERROR(INDEX(CATALOGO!$I$6:$I$35,MATCH($C$18,CATALOGO!$E$6:$E$35,0)),"")
B23: PASO 2 · DATOS DE LA ENTIDAD
B24: Denominación o razón social: | C24: Inmobiliaria Ejemplo, S.A. de C.V.
B25: Nombre corto o comercial: | C25: Inmobiliaria Ejemplo
B26: Representante / Encargado de Cumplimiento: | C26: María Ejemplo Ruiz — Representante Encargada de Cumplimiento
B27: Fecha de la evaluación: | C27: 46204
B28: Periodo analizado (inicio): | C28: 45839
B29: Periodo analizado (fin, mín. 12 meses): | C29: 46203
B31: PASO 3 · DATOS DE 12 MESES (base de la evaluación, Art. 10 Septies 2)
B32: Número total de Clientes/Usuarias: | C32: 86
B33: Número total de actos u operaciones: | C33: 112
B34: Monto total operado (MXN): | C34: 428600000
B36: Revisa y actualiza al menos cada 12 meses o al actualizarse la ENR. Conserva la documentación 10 años.
B38: ESTADO DE AVANCE — REVÍSALO ANTES DE IMPRIMIR, FIRMAR O ENTREGAR
B39: Verificación | E39: Dato | F39: Estatus
B40: Indicadores cuyo reparto Alto/Medio/Bajo no suma 100% | E40: =SUMPRODUCT(--('A1 EXPOSICION'!$G$7:$G$31="Sí"),--(ABS('A1 EXPOSICION'!$N$7:$N$31-1)>0.001)) | F40: =IF(E40=0,"OK","Corregir")
B41: Suma de los pesos de los cuatro elementos (debe ser 100%) | E41: ='A1 EXPOSICION'!$D$40 | F41: =IF(ABS(E41-1)<=0.001,"OK","Corregir")
B42: Indicadores excluidos sin justificación escrita | E42: ='A1 EXPOSICION'!$E$45 | F42: =IF(E42=0,"OK","Corregir")
B43: Obligaciones del catálogo sin calificar | E43: ='A4 CONTROLES MINIMOS'!$F$36 | F43: =IF(E43=0,"OK","Corregir")
B44: Obligaciones del catálogo en «No cumple» | E44: ='A4 CONTROLES MINIMOS'!$F$33 | F44: =IF(E44=0,"OK","Corregir")
B45: Exclusiones del catálogo sin constancia en el Manual | E45: ='A4 CONTROLES MINIMOS'!$F$34 | F45: =IF(E45=0,"OK","Corregir")
B46: Datos obligatorios pendientes en la constancia A9 | E46: ='A9 CONSTANCIA Y FUENTES'!$D$6 | F46: =IF(E46=0,"OK","Corregir")
B48: =IF(AND(E40=0,ABS(E41-1)<=0.001,E42=0,E43=0,E44=0,E45=0,E46=0),"Evaluación completa: puede imprimirse, aprobarse y conservarse diez años.","Hay verificaciones en «Corregir». La evaluación calcula, pero todavía no es defendible ante un requerimiento.")

Sheet A1 EXPOSICION
B2: A1 · EXPOSICIÓN — Captura tu concentración de negocio (12 meses)
B3: Por cada indicador reparte el 100% entre Alto/Medio/Bajo. Calificación = qué tan riesgoso; Concentración = qué tan expuesto; Riesgo = Calif × Conc. Un indicador en «No» sale del numerador y del denominador.
B4: Paso 3 de 10 · Viene de: A9 §1 y §2 · Sigue: A2 CONSECUENCIAS
B5: OJO · La unidad del reparto cambia según el indicador: en unos el 100 % se reparte sobre el NÚMERO DE CLIENTES o de operaciones, y en otros sobre los MONTOS OPERADOS (por ejemplo tipo de moneda, monto frente a umbrales o instrumento monetario). Lee la columna «Guía» de cada renglón antes de capturar, y anota en «Justificación» sobre qué lo repartiste. | G5: GRIS = obligatorio (139 Quáter / 400 Bis): no admite «No». AMARILLO = tú decides si aplica.
B6: Elem. | C6: # | D6: Indicador | E6: Atiende | F6: Fuente | G6: Aplica | H6: Guía ALTO | I6: Guía MEDIO | J6: Guía BAJO | K6: % Alto | L6: % Medio | M6: % Bajo | N6: Suma | O6: Peso (relativo dentro del elemento) | P6: Calif. | Q6: Conc. | R6: Riesgo | S6: Justificación (del No aplica o del peso)
B7: 1 | C7: 1 | D7: Valor unitario de la operación | F7: B | G7: Sí | H7: =IFERROR(INDEX(BASE!$E:$E,MATCH(INICIO!$C$18&"-"&$C7,BASE!$A:$A,0)),"") | I7: =IFERROR(INDEX(BASE!$F:$F,MATCH(INICIO!$C$18&"-"&$C7,BASE!$A:$A,0)),"") | J7: =IFERROR(INDEX(BASE!$G:$G,MATCH(INICIO!$C$18&"-"&$C7,BASE!$A:$A,0)),"") | K7: 0.2 | L7: 0.35 | M7: 0.45 | N7: =K7+L7+M7 | O7: 0.3 | P7: =IF($G7="No",0,ROUND(5*K7+3*L7+1*M7,0)) | Q7: =IF($G7="No",0,ROUND(1+4*(K7+L7),0)) | R7: =P7*Q7 | S7: Es el elemento de mayor exposicion del giro: el ticket promedio del periodo supera por si solo el umbral de aviso, de modo que casi toda la operacion nace ya dentro del regimen.
B8: 1 | C8: 2 | D8: Liquidez: facilidad de convertir en dinero | F8: B | G8: Sí | H8: =IFERROR(INDEX(BASE!$E:$E,MATCH(INICIO!$C$18&"-"&$C8,BASE!$A:$A,0)),"") | I8: =IFERROR(INDEX(BASE!$F:$F,MATCH(INICIO!$C$18&"-"&$C8,BASE!$A:$A,0)),"") | J8: =IFERROR(INDEX(BASE!$G:$G,MATCH(INICIO!$C$18&"-"&$C8,BASE!$A:$A,0)),"") | K8: 0.15 | L8: 0.3 | M8: 0.55 | N8: =K8+L8+M8 | O8: 0.1 | P8: =IF($G8="No",0,ROUND(5*K8+3*L8+1*M8,0)) | Q8: =IF($G8="No",0,ROUND(1+4*(K8+L8),0)) | R8: =P8*Q8 | S8: El inmueble es el activo menos liquido del catalogo del Art. 17; la conversion exige escritura publica y registro, lo que reduce su atractivo para colocacion rapida.
B9: 1 | C9: 3 | D9: Anonimato: si el beneficiario queda a la vista | F9: B | G9: Sí | H9: =IFERROR(INDEX(BASE!$E:$E,MATCH(INICIO!$C$18&"-"&$C9,BASE!$A:$A,0)),"") | I9: =IFERROR(INDEX(BASE!$F:$F,MATCH(INICIO!$C$18&"-"&$C9,BASE!$A:$A,0)),"") | J9: =IFERROR(INDEX(BASE!$G:$G,MATCH(INICIO!$C$18&"-"&$C9,BASE!$A:$A,0)),"") | K9: 0.45 | L9: 0.3 | M9: 0.25 | N9: =K9+L9+M9 | O9: 0.25 | P9: =IF($G9="No",0,ROUND(5*K9+3*L9+1*M9,0)) | Q9: =IF($G9="No",0,ROUND(1+4*(K9+L9),0)) | R9: =P9*Q9 | S9: Peso alto: la interposicion de terceros y la compra a traves de personas morales de reciente constitucion es la tipologia inmobiliaria dominante en la ENR.
B10: 1 | C10: 4 | D10: Ocultamiento de valor en el precio | E10: 400 Bis | F10: B | G10: Sí | H10: =IFERROR(INDEX(BASE!$E:$E,MATCH(INICIO!$C$18&"-"&$C10,BASE!$A:$A,0)),"") | I10: =IFERROR(INDEX(BASE!$F:$F,MATCH(INICIO!$C$18&"-"&$C10,BASE!$A:$A,0)),"") | J10: =IFERROR(INDEX(BASE!$G:$G,MATCH(INICIO!$C$18&"-"&$C10,BASE!$A:$A,0)),"") | K10: 0.35 | L10: 0.35 | M10: 0.3 | N10: =K10+L10+M10 | O10: 0.25 | P10: =IF($G10="No",0,ROUND(5*K10+3*L10+1*M10,0)) | Q10: =IF($G10="No",0,ROUND(1+4*(K10+L10),0)) | R10: =P10*Q10 | S10: Peso alto por mandato del ultimo parrafo del Art. 10 Septies 1: es el indicador de 400 Bis del elemento, y la transferencia de valor via inmueble es el mecanismo tipico de integracion.
B11: 1 | C11: 5 | D11: Exposición a personas señaladas por terrorismo | E11: 139 Quáter | F11: B | G11: Sí | H11: =IFERROR(INDEX(BASE!$E:$E,MATCH(INICIO!$C$18&"-"&$C11,BASE!$A:$A,0)),"") | I11: =IFERROR(INDEX(BASE!$F:$F,MATCH(INICIO!$C$18&"-"&$C11,BASE!$A:$A,0)),"") | J11: =IFERROR(INDEX(BASE!$G:$G,MATCH(INICIO!$C$18&"-"&$C11,BASE!$A:$A,0)),"") | K11: 0.1 | L11: 0.2 | M11: 0.7 | N11: =K11+L11+M11 | O11: 0.1 | P11: =IF($G11="No",0,ROUND(5*K11+3*L11+1*M11,0)) | Q11: =IF($G11="No",0,ROUND(1+4*(K11+L11),0)) | R11: =P11*Q11 | S11: Se mantiene por obligacion normativa como indicador de 139 Quater del elemento, con peso bajo: no se detectaron contrapartes ni destinos vinculados a financiamiento al terrorismo en el periodo.
B12: 2 | C12: 6 | D12: Tipo de persona | F12: A | G12: Sí | H12: =IFERROR(INDEX(BASE!$E:$E,MATCH(INICIO!$C$18&"-"&$C12,BASE!$A:$A,0)),"") | I12: =IFERROR(INDEX(BASE!$F:$F,MATCH(INICIO!$C$18&"-"&$C12,BASE!$A:$A,0)),"") | J12: =IFERROR(INDEX(BASE!$G:$G,MATCH(INICIO!$C$18&"-"&$C12,BASE!$A:$A,0)),"") | K12: 0.3 | L12: 0.35 | M12: 0.35 | N12: =K12+L12+M12 | O12: 0.18 | P12: =IF($G12="No",0,ROUND(5*K12+3*L12+1*M12,0)) | Q12: =IF($G12="No",0,ROUND(1+4*(K12+L12),0)) | R12: =P12*Q12 | S12: La estructura del cliente es el primer discriminante del giro: persona moral con socios no identificables concentra la mayor parte de las alertas del periodo.
B13: 2 | C13: 7 | D13: Antigüedad del Cliente | F13: A | G13: Sí | H13: =IFERROR(INDEX(BASE!$E:$E,MATCH(INICIO!$C$18&"-"&$C13,BASE!$A:$A,0)),"") | I13: =IFERROR(INDEX(BASE!$F:$F,MATCH(INICIO!$C$18&"-"&$C13,BASE!$A:$A,0)),"") | J13: =IFERROR(INDEX(BASE!$G:$G,MATCH(INICIO!$C$18&"-"&$C13,BASE!$A:$A,0)),"") | K13: 0.15 | L13: 0.3 | M13: 0.55 | N13: =K13+L13+M13 | O13: 0.08 | P13: =IF($G13="No",0,ROUND(5*K13+3*L13+1*M13,0)) | Q13: =IF($G13="No",0,ROUND(1+4*(K13+L13),0)) | R13: =P13*Q13 | S13: Peso bajo: la antiguedad por si sola discrimina poco, pero se conserva porque la sociedad constituida en el mismo ejercicio de la compra es senal de alerta reconocida.
B14: 2 | C14: 8 | D14: Giro o actividad declarada | F14: A | G14: Sí | H14: =IFERROR(INDEX(BASE!$E:$E,MATCH(INICIO!$C$18&"-"&$C14,BASE!$A:$A,0)),"") | I14: =IFERROR(INDEX(BASE!$F:$F,MATCH(INICIO!$C$18&"-"&$C14,BASE!$A:$A,0)),"") | J14: =IFERROR(INDEX(BASE!$G:$G,MATCH(INICIO!$C$18&"-"&$C14,BASE!$A:$A,0)),"") | K14: 0.4 | L14: 0.3 | M14: 0.3 | N14: =K14+L14+M14 | O14: 0.15 | P14: =IF($G14="No",0,ROUND(5*K14+3*L14+1*M14,0)) | Q14: =IF($G14="No",0,ROUND(1+4*(K14+L14),0)) | R14: =P14*Q14 | S14: El giro del cliente explica la congruencia entre el precio del inmueble y su capacidad economica declarada; es la pregunta que abre cualquier revision.
B15: 2 | C15: 9 | D15: Nacionalidad | F15: A | G15: Sí | H15: =IFERROR(INDEX(BASE!$E:$E,MATCH(INICIO!$C$18&"-"&$C15,BASE!$A:$A,0)),"") | I15: =IFERROR(INDEX(BASE!$F:$F,MATCH(INICIO!$C$18&"-"&$C15,BASE!$A:$A,0)),"") | J15: =IFERROR(INDEX(BASE!$G:$G,MATCH(INICIO!$C$18&"-"&$C15,BASE!$A:$A,0)),"") | K15: 0.1 | L15: 0.25 | M15: 0.65 | N15: =K15+L15+M15 | O15: 0.07 | P15: =IF($G15="No",0,ROUND(5*K15+3*L15+1*M15,0)) | Q15: =IF($G15="No",0,ROUND(1+4*(K15+L15),0)) | R15: =P15*Q15 | S15: Peso bajo: la nacionalidad aisladamente no explica riesgo. Su efecto real se mide en el indicador de residencia y en el elemento 3.
B16: 2 | C16: 10 | D16: País y entidad de residencia | F16: A | G16: Sí | H16: =IFERROR(INDEX(BASE!$E:$E,MATCH(INICIO!$C$18&"-"&$C16,BASE!$A:$A,0)),"") | I16: =IFERROR(INDEX(BASE!$F:$F,MATCH(INICIO!$C$18&"-"&$C16,BASE!$A:$A,0)),"") | J16: =IFERROR(INDEX(BASE!$G:$G,MATCH(INICIO!$C$18&"-"&$C16,BASE!$A:$A,0)),"") | K16: 0.15 | L16: 0.25 | M16: 0.6 | N16: =K16+L16+M16 | O16: 0.1 | P16: =IF($G16="No",0,ROUND(5*K16+3*L16+1*M16,0)) | Q16: =IF($G16="No",0,ROUND(1+4*(K16+L16),0)) | R16: =P16*Q16 | S16: Peso medio bajo: la residencia fuera de la plaza donde esta el inmueble es senal util, pero se pondera junto con el indicador 17 para no contar dos veces lo mismo.
B17: 2 | C17: 11 | D17: Condición de Persona Políticamente Expuesta | E17: 400 Bis | F17: D | G17: Sí | H17: =IFERROR(INDEX(BASE!$E:$E,MATCH(INICIO!$C$18&"-"&$C17,BASE!$A:$A,0)),"") | I17: =IFERROR(INDEX(BASE!$F:$F,MATCH(INICIO!$C$18&"-"&$C17,BASE!$A:$A,0)),"") | J17: =IFERROR(INDEX(BASE!$G:$G,MATCH(INICIO!$C$18&"-"&$C17,BASE!$A:$A,0)),"") | K17: 0.2 | L17: 0.2 | M17: 0.6 | N17: =K17+L17+M17 | O17: 0.14 | P17: =IF($G17="No",0,ROUND(5*K17+3*L17+1*M17,0)) | Q17: =IF($G17="No",0,ROUND(1+4*(K17+L17),0)) | R17: =P17*Q17 | S17: Indicador de 400 Bis del elemento. Peso relevante: la condicion PEP dispara seguimiento reforzado por el Art. 23 Bis 3, y la PEP extranjera fuerza grado alto por el Art. 23 Bis 4.
B18: 2 | C18: 12 | D18: Resultado de la búsqueda en listas | E18: 139 Quáter | F18: D | G18: Sí | H18: =IFERROR(INDEX(BASE!$E:$E,MATCH(INICIO!$C$18&"-"&$C18,BASE!$A:$A,0)),"") | I18: =IFERROR(INDEX(BASE!$F:$F,MATCH(INICIO!$C$18&"-"&$C18,BASE!$A:$A,0)),"") | J18: =IFERROR(INDEX(BASE!$G:$G,MATCH(INICIO!$C$18&"-"&$C18,BASE!$A:$A,0)),"") | K18: 0.05 | L18: 0.15 | M18: 0.8 | N18: =K18+L18+M18 | O18: 0.1 | P18: =IF($G18="No",0,ROUND(5*K18+3*L18+1*M18,0)) | Q18: =IF($G18="No",0,ROUND(1+4*(K18+L18),0)) | R18: =P18*Q18 | S18: Indicador de 139 Quater del elemento. Peso contenido porque la validacion contra listas esta automatizada y se ejecuta al 100% de las operaciones.
B19: 2 | C19: 13 | D19: Profundidad de la cadena de control | E19: 400 Bis | F19: A | G19: Sí | H19: =IFERROR(INDEX(BASE!$E:$E,MATCH(INICIO!$C$18&"-"&$C19,BASE!$A:$A,0)),"") | I19: =IFERROR(INDEX(BASE!$F:$F,MATCH(INICIO!$C$18&"-"&$C19,BASE!$A:$A,0)),"") | J19: =IFERROR(INDEX(BASE!$G:$G,MATCH(INICIO!$C$18&"-"&$C19,BASE!$A:$A,0)),"") | K19: 0.35 | L19: 0.35 | M19: 0.3 | N19: =K19+L19+M19 | O19: 0.18 | P19: =IF($G19="No",0,ROUND(5*K19+3*L19+1*M19,0)) | Q19: =IF($G19="No",0,ROUND(1+4*(K19+L19),0)) | R19: =P19*Q19 | S19: Peso alto: desde el 30 de noviembre de 2026 desaparece la constancia declarativa en persona moral y fideicomiso, y hay que identificar al Beneficiario Controlador. La complejidad de la cadena es riesgo medible.
B20: 3 | C20: 14 | D20: País donde se realiza la operación | E20: 400 Bis | F20: C+D | G20: Sí | H20: =IFERROR(INDEX(BASE!$E:$E,MATCH(INICIO!$C$18&"-"&$C20,BASE!$A:$A,0)),"") | I20: =IFERROR(INDEX(BASE!$F:$F,MATCH(INICIO!$C$18&"-"&$C20,BASE!$A:$A,0)),"") | J20: =IFERROR(INDEX(BASE!$G:$G,MATCH(INICIO!$C$18&"-"&$C20,BASE!$A:$A,0)),"") | K20: 0.15 | L20: 0.25 | M20: 0.6 | N20: =K20+L20+M20 | O20: 0.3 | P20: =IF($G20="No",0,ROUND(5*K20+3*L20+1*M20,0)) | Q20: =IF($G20="No",0,ROUND(1+4*(K20+L20),0)) | R20: =P20*Q20 | S20: Indicador de 400 Bis del elemento y el de mayor peso: la jurisdiccion donde se ubica el inmueble determina el marco registral y la trazabilidad real de la operacion.
B21: 3 | C21: 15 | D21: Entidad o municipio de la operación | F21: C+D | G21: Sí | H21: =IFERROR(INDEX(BASE!$E:$E,MATCH(INICIO!$C$18&"-"&$C21,BASE!$A:$A,0)),"") | I21: =IFERROR(INDEX(BASE!$F:$F,MATCH(INICIO!$C$18&"-"&$C21,BASE!$A:$A,0)),"") | J21: =IFERROR(INDEX(BASE!$G:$G,MATCH(INICIO!$C$18&"-"&$C21,BASE!$A:$A,0)),"") | K21: 0.3 | L21: 0.35 | M21: 0.35 | N21: =K21+L21+M21 | O21: 0.3 | P21: =IF($G21="No",0,ROUND(5*K21+3*L21+1*M21,0)) | Q21: =IF($G21="No",0,ROUND(1+4*(K21+L21),0)) | R21: =P21*Q21 | S21: Peso equivalente al anterior: la plaza nacional concentra la exposicion. Dos de los desarrollos del periodo estan en municipios senalados en la ENR.
B22: 3 | C22: 16 | D22: Vínculo con jurisdicción sancionada o de acción requerida | E22: 139 Quáter | F22: C+D | G22: Sí | H22: =IFERROR(INDEX(BASE!$E:$E,MATCH(INICIO!$C$18&"-"&$C22,BASE!$A:$A,0)),"") | I22: =IFERROR(INDEX(BASE!$F:$F,MATCH(INICIO!$C$18&"-"&$C22,BASE!$A:$A,0)),"") | J22: =IFERROR(INDEX(BASE!$G:$G,MATCH(INICIO!$C$18&"-"&$C22,BASE!$A:$A,0)),"") | K22: 0.05 | L22: 0.15 | M22: 0.8 | N22: =K22+L22+M22 | O22: 0.15 | P22: =IF($G22="No",0,ROUND(5*K22+3*L22+1*M22,0)) | Q22: =IF($G22="No",0,ROUND(1+4*(K22+L22),0)) | R22: =P22*Q22 | S22: Indicador de 139 Quater del elemento, con peso bajo: la operacion del periodo fue integramente nacional, sin contrapartes en jurisdicciones sancionadas.
B23: 3 | C23: 17 | D23: Coincidencia entre domicilio y lugar de la operación | E23: 400 Bis | F23: A+C | G23: Sí | H23: =IFERROR(INDEX(BASE!$E:$E,MATCH(INICIO!$C$18&"-"&$C23,BASE!$A:$A,0)),"") | I23: =IFERROR(INDEX(BASE!$F:$F,MATCH(INICIO!$C$18&"-"&$C23,BASE!$A:$A,0)),"") | J23: =IFERROR(INDEX(BASE!$G:$G,MATCH(INICIO!$C$18&"-"&$C23,BASE!$A:$A,0)),"") | K23: 0.25 | L23: 0.3 | M23: 0.45 | N23: =K23+L23+M23 | O23: 0.25 | P23: =IF($G23="No",0,ROUND(5*K23+3*L23+1*M23,0)) | Q23: =IF($G23="No",0,ROUND(1+4*(K23+L23),0)) | R23: =P23*Q23 | S23: Peso alto: la incongruencia entre el domicilio del cliente y la ubicacion del inmueble es la alerta que mas veces se activo en el periodo evaluado.
B24: 4 | C24: 18 | D24: Instrumento con que se paga | F24: C | G24: Sí | H24: =IFERROR(INDEX(BASE!$E:$E,MATCH(INICIO!$C$18&"-"&$C24,BASE!$A:$A,0)),"") | I24: =IFERROR(INDEX(BASE!$F:$F,MATCH(INICIO!$C$18&"-"&$C24,BASE!$A:$A,0)),"") | J24: =IFERROR(INDEX(BASE!$G:$G,MATCH(INICIO!$C$18&"-"&$C24,BASE!$A:$A,0)),"") | K24: 0.5 | L24: 0.25 | M24: 0.25 | N24: =K24+L24+M24 | O24: 0.22 | P24: =IF($G24="No",0,ROUND(5*K24+3*L24+1*M24,0)) | Q24: =IF($G24="No",0,ROUND(1+4*(K24+L24),0)) | R24: =P24*Q24 | S24: El peso mas alto del elemento: el efectivo es el mecanismo de colocacion por excelencia y la mitad de las operaciones del periodo tuvo algun componente en efectivo.
B25: 4 | C25: 19 | D25: Moneda de la operación | F25: C | G25: Sí | H25: =IFERROR(INDEX(BASE!$E:$E,MATCH(INICIO!$C$18&"-"&$C25,BASE!$A:$A,0)),"") | I25: =IFERROR(INDEX(BASE!$F:$F,MATCH(INICIO!$C$18&"-"&$C25,BASE!$A:$A,0)),"") | J25: =IFERROR(INDEX(BASE!$G:$G,MATCH(INICIO!$C$18&"-"&$C25,BASE!$A:$A,0)),"") | K25: 0.1 | L25: 0.2 | M25: 0.7 | N25: =K25+L25+M25 | O25: 0.05 | P25: =IF($G25="No",0,ROUND(5*K25+3*L25+1*M25,0)) | Q25: =IF($G25="No",0,ROUND(1+4*(K25+L25),0)) | R25: =P25*Q25 | S25: Peso minimo: el 100% de las operaciones del periodo se pacto y liquido en pesos mexicanos.
B26: 4 | C26: 20 | D26: Monto frente al umbral de tu fracción | F26: C | G26: Sí | H26: =IFERROR(INDEX(BASE!$E:$E,MATCH(INICIO!$C$18&"-"&$C26,BASE!$A:$A,0)),"") | I26: =IFERROR(INDEX(BASE!$F:$F,MATCH(INICIO!$C$18&"-"&$C26,BASE!$A:$A,0)),"") | J26: =IFERROR(INDEX(BASE!$G:$G,MATCH(INICIO!$C$18&"-"&$C26,BASE!$A:$A,0)),"") | K26: 0.35 | L26: 0.3 | M26: 0.35 | N26: =K26+L26+M26 | O26: 0.13 | P26: =IF($G26="No",0,ROUND(5*K26+3*L26+1*M26,0)) | Q26: =IF($G26="No",0,ROUND(1+4*(K26+L26),0)) | R26: =P26*Q26 | S26: Peso medio: el monto frente al umbral define si la operacion entra al regimen, pero en este giro practicamente todas lo superan, de modo que discrimina poco entre clientes.
B27: 4 | C27: 21 | D27: Número y ritmo de operaciones en el periodo | F27: C | G27: Sí | H27: =IFERROR(INDEX(BASE!$E:$E,MATCH(INICIO!$C$18&"-"&$C27,BASE!$A:$A,0)),"") | I27: =IFERROR(INDEX(BASE!$F:$F,MATCH(INICIO!$C$18&"-"&$C27,BASE!$A:$A,0)),"") | J27: =IFERROR(INDEX(BASE!$G:$G,MATCH(INICIO!$C$18&"-"&$C27,BASE!$A:$A,0)),"") | K27: 0.3 | L27: 0.35 | M27: 0.35 | N27: =K27+L27+M27 | O27: 0.15 | P27: =IF($G27="No",0,ROUND(5*K27+3*L27+1*M27,0)) | Q27: =IF($G27="No",0,ROUND(1+4*(K27+L27),0)) | R27: =P27*Q27 | S27: Peso relevante: el pago en parcialidades es la practica normal del giro, lo que hace dificil distinguir la amortizacion legitima del fraccionamiento deliberado.
B28: 4 | C28: 22 | D28: Canal: certeza de identificación del Cliente | E28: 400 Bis | F28: B+C | G28: Sí | H28: =IFERROR(INDEX(BASE!$E:$E,MATCH(INICIO!$C$18&"-"&$C28,BASE!$A:$A,0)),"") | I28: =IFERROR(INDEX(BASE!$F:$F,MATCH(INICIO!$C$18&"-"&$C28,BASE!$A:$A,0)),"") | J28: =IFERROR(INDEX(BASE!$G:$G,MATCH(INICIO!$C$18&"-"&$C28,BASE!$A:$A,0)),"") | K28: 0.25 | L28: 0.35 | M28: 0.4 | N28: =K28+L28+M28 | O28: 0.1 | P28: =IF($G28="No",0,ROUND(5*K28+3*L28+1*M28,0)) | Q28: =IF($G28="No",0,ROUND(1+4*(K28+L28),0)) | R28: =P28*Q28 | S28: Indicador de 400 Bis del elemento. Peso contenido: la operacion es presencial y ante fedatario, lo que limita el riesgo de canal.
B29: 4 | C29: 23 | D29: Acreditación del origen de los recursos | F29: C+D | G29: Sí | H29: =IFERROR(INDEX(BASE!$E:$E,MATCH(INICIO!$C$18&"-"&$C29,BASE!$A:$A,0)),"") | I29: =IFERROR(INDEX(BASE!$F:$F,MATCH(INICIO!$C$18&"-"&$C29,BASE!$A:$A,0)),"") | J29: =IFERROR(INDEX(BASE!$G:$G,MATCH(INICIO!$C$18&"-"&$C29,BASE!$A:$A,0)),"") | K29: 0.45 | L29: 0.3 | M29: 0.25 | N29: =K29+L29+M29 | O29: 0.18 | P29: =IF($G29="No",0,ROUND(5*K29+3*L29+1*M29,0)) | Q29: =IF($G29="No",0,ROUND(1+4*(K29+L29),0)) | R29: =P29*Q29 | S29: Peso alto: el origen de los recursos es el dato que sostiene o derrumba toda la operacion, y es la primera pregunta de cualquier requerimiento.
B30: 4 | C30: 24 | D30: Acreditación del destino de los recursos o del bien | F30: C+D | G30: Sí | H30: =IFERROR(INDEX(BASE!$E:$E,MATCH(INICIO!$C$18&"-"&$C30,BASE!$A:$A,0)),"") | I30: =IFERROR(INDEX(BASE!$F:$F,MATCH(INICIO!$C$18&"-"&$C30,BASE!$A:$A,0)),"") | J30: =IFERROR(INDEX(BASE!$G:$G,MATCH(INICIO!$C$18&"-"&$C30,BASE!$A:$A,0)),"") | K30: 0.3 | L30: 0.3 | M30: 0.4 | N30: =K30+L30+M30 | O30: 0.09 | P30: =IF($G30="No",0,ROUND(5*K30+3*L30+1*M30,0)) | Q30: =IF($G30="No",0,ROUND(1+4*(K30+L30),0)) | R30: =P30*Q30 | S30: Peso menor que el origen: en compraventa de inmueble el destino es el propio bien, que queda registrado; el riesgo se concentra en la entrada de los recursos.
B31: 4 | C31: 25 | D31: Combinación de canal e instrumento idónea para el financiamiento al terrorismo | E31: 139 Quáter | F31: B+C | G31: Sí | H31: =IFERROR(INDEX(BASE!$E:$E,MATCH(INICIO!$C$18&"-"&$C31,BASE!$A:$A,0)),"") | I31: =IFERROR(INDEX(BASE!$F:$F,MATCH(INICIO!$C$18&"-"&$C31,BASE!$A:$A,0)),"") | J31: =IFERROR(INDEX(BASE!$G:$G,MATCH(INICIO!$C$18&"-"&$C31,BASE!$A:$A,0)),"") | K31: 0.2 | L31: 0.3 | M31: 0.5 | N31: =K31+L31+M31 | O31: 0.08 | P31: =IF($G31="No",0,ROUND(5*K31+3*L31+1*M31,0)) | Q31: =IF($G31="No",0,ROUND(1+4*(K31+L31),0)) | R31: =P31*Q31 | S31: Indicador de 139 Quater del elemento. Peso bajo: no se identificaron canales ni instrumentos de los descritos en la ENR para financiamiento al terrorismo.
B33: RESUMEN POR ELEMENTO
B34: Elemento | D34: Peso | E34: Calif. | F34: Conc. | G34: Riesgo | H34: Nivel | I34: N/A | J34: Aviso | K34: Justificación del peso asignado (Art. 10 Septies 1, fr. II)
B35: 1. Actos u operaciones | D35: 0.2 | E35: =IFERROR(SUMPRODUCT($P$7:$P$11,$O$7:$O$11,--($G$7:$G$11="Sí"))/SUMPRODUCT($O$7:$O$11,--($G$7:$G$11="Sí")),0) | F35: =IFERROR(SUMPRODUCT($Q$7:$Q$11,$O$7:$O$11,--($G$7:$G$11="Sí"))/SUMPRODUCT($O$7:$O$11,--($G$7:$G$11="Sí")),0) | G35: =E35*F35 | H35: =IFERROR(INDEX(PARAMETROS!$E$15:$E$19,MATCH(G35,PARAMETROS!$B$15:$B$19,1)),"") | I35: =COUNTIF($G$7:$G$11,"No") | J35: =IF(I35>5/3,"Revisar: más de un tercio del elemento está en No aplica","") | K35: La entidad realiza un solo tipo de acto —compraventa de inmueble destinado a casa habitación y local comercial— de alto valor unitario y baja liquidez. Se le asigna 20% porque el acto en sí está bien acotado y registrado ante fedatario: la exposición no está en qué se vende, sino en con quién y cómo se paga.
B36: 2. Clientes / Usuarios | D36: 0.3 | E36: =IFERROR(SUMPRODUCT($P$12:$P$19,$O$12:$O$19,--($G$12:$G$19="Sí"))/SUMPRODUCT($O$12:$O$19,--($G$12:$G$19="Sí")),0) | F36: =IFERROR(SUMPRODUCT($Q$12:$Q$19,$O$12:$O$19,--($G$12:$G$19="Sí"))/SUMPRODUCT($O$12:$O$19,--($G$12:$G$19="Sí")),0) | G36: =E36*F36 | H36: =IFERROR(INDEX(PARAMETROS!$E$15:$E$19,MATCH(G36,PARAMETROS!$B$15:$B$19,1)),"") | I36: =COUNTIF($G$12:$G$19,"No") | J36: =IF(I36>8/3,"Revisar: más de un tercio del elemento está en No aplica","") | K36: Es donde se concentra la exposición real. De los 86 Clientes del periodo, 31 son personas morales y 9 de ellas se constituyeron en los doce meses previos a la operación. La interposición de terceros y la opacidad de la cadena de propiedad son la tipología inmobiliaria dominante en la Evaluación Nacional de Riesgos. Se le asigna 30%.
B37: 3. Países y áreas geográficas | D37: 0.15 | E37: =IFERROR(SUMPRODUCT($P$20:$P$23,$O$20:$O$23,--($G$20:$G$23="Sí"))/SUMPRODUCT($O$20:$O$23,--($G$20:$G$23="Sí")),0) | F37: =IFERROR(SUMPRODUCT($Q$20:$Q$23,$O$20:$O$23,--($G$20:$G$23="Sí"))/SUMPRODUCT($O$20:$O$23,--($G$20:$G$23="Sí")),0) | G37: =E37*F37 | H37: =IFERROR(INDEX(PARAMETROS!$E$15:$E$19,MATCH(G37,PARAMETROS!$B$15:$B$19,1)),"") | I37: =COUNTIF($G$20:$G$23,"No") | J37: =IF(I37>4/3,"Revisar: más de un tercio del elemento está en No aplica","") | K37: La operación es local: los cuatro desarrollos están en el área metropolitana y no hubo contrapartes ni recursos de jurisdicciones extranjeras en el periodo. Se le asigna 15%, el peso más bajo, y no cero: dos de los desarrollos están en municipios señalados en la ENR, y eso se mide en el indicador 15.
B38: 4. Transacciones y canales | D38: 0.35 | E38: =IFERROR(SUMPRODUCT($P$24:$P$31,$O$24:$O$31,--($G$24:$G$31="Sí"))/SUMPRODUCT($O$24:$O$31,--($G$24:$G$31="Sí")),0) | F38: =IFERROR(SUMPRODUCT($Q$24:$Q$31,$O$24:$O$31,--($G$24:$G$31="Sí"))/SUMPRODUCT($O$24:$O$31,--($G$24:$G$31="Sí")),0) | G38: =E38*F38 | H38: =IFERROR(INDEX(PARAMETROS!$E$15:$E$19,MATCH(G38,PARAMETROS!$B$15:$B$19,1)),"") | I38: =COUNTIF($G$24:$G$31,"No") | J38: =IF(I38>8/3,"Revisar: más de un tercio del elemento está en No aplica","") | K38: El mayor peso, 35%. Es donde se materializa el riesgo: 56 de las 112 operaciones tuvieron algún componente en efectivo, 41 se liquidaron en parcialidades y en 7 casos el pago provino de un tercero distinto del comprador. Los tres hechos están documentados en el reporte de acumulación del sistema.
B40: RIESGO DE LA ENTIDAD | D40: =SUM(D35:D38) | E40: =IFERROR(SUMPRODUCT(E35:E38,D35:D38)/SUM(D35:D38),0) | F40: =IFERROR(SUMPRODUCT(F35:F38,D35:D38)/SUM(D35:D38),0) | G40: =E40*F40 | H40: =IFERROR(INDEX(PARAMETROS!$E$15:$E$19,MATCH(G40,PARAMETROS!$B$15:$B$19,1)),"") | I40: =COUNTIF($G$7:$G$31,"No") | J40: =IF(SUMPRODUCT(--($G$7:$G$31="No"),--($S$7:$S$31=""))>0,"Hay exclusiones sin justificación escrita: no son defendibles ante un requerimiento","") | K40: =IF(ABS(SUM($D$35:$D$38)-1)>0.001,"Los pesos de los cuatro elementos suman "&TEXT(SUM($D$35:$D$38),"0%")&" y deben sumar 100%. Corrige la columna Peso.","Los pesos de los elementos suman 100%.")
K41: El peso de cada indicador (columna Peso) es relativo dentro de su elemento: el promedio se normaliza solo. El peso de los cuatro elementos sí debe sumar 100%.
B42: Trazabilidad (Art. 10 Septies 1, fr. I y último párrafo): indicadores evaluados y excluidos
B43: Indicadores evaluados: | E43: =COUNTIF($G$7:$G$31,"Sí")
B44: Indicadores excluidos (No aplica): | E44: =COUNTIF($G$7:$G$31,"No")
B45: Exclusiones sin justificación escrita: | E45: =SUMPRODUCT(--($G$7:$G$31="No"),--($S$7:$S$31=""))
B46: Los indicadores de 139 Quáter y de 400 Bis con celda gris no admiten «No aplica»: excluirlos incumpliría el último párrafo del Art. 10 Septies 1.

Sheet A2 CONSECUENCIAS
B2: A2 · CONSECUENCIAS SI EL RIESGO SE MATERIALIZA (análisis cualitativo)
B3: Esta hoja NO alimenta el cálculo y no cambia ningún número. En una sola descripción, explica qué pasaría si el riesgo LD/FT se materializa en tu entidad. Sirve para justificar el nivel de tolerancia declarado y para sustentar la evaluación ante un requerimiento.
B4: Paso 4 de 10 · Viene de: A1 · Sigue: A3 INHERENTE (solo lectura)
B6: ¿Qué pasaría si el riesgo LD/FT se materializa en tu entidad? | G6: Severidad (ref.)
B7: Si una operación con recursos de procedencia ilícita se materializara en la entidad, el impacto sería simultáneo en cuatro planos. LEGAL: la multa por Aviso omitido es de 10,000 a 65,000 UMA, o del 10 al 100 % del valor del acto cuando sea cuantificable, la que resulte mayor (Art. 53 fr. VI con Art. 54 fr. III de la Ley) —entre $1,173,100 y $7,625,150 al valor vigente de la UMA, y en una operación de este tamaño manda el porcentaje— y la conducta puede escalar a responsabilidad penal por el Art. 400 Bis del Código Penal Federal para quien intervino a sabiendas. REPUTACIONAL: el negocio depende de la recomendación entre compradores y de la relación con tres desarrolladoras; una nota pública o un requerimiento conocido bastaría para frenar la preventa del desarrollo en curso. DE CONTAGIO: las instituciones financieras con las que se dispersan los recursos aplican sus propias medidas del Art. 115 de la LIC y pueden restringir o cancelar las cuentas de la entidad, lo que detendría la operación aunque no hubiera sanción. OPERATIVO: atender un requerimiento con expedientes incompletos consumiría a la Encargada de Cumplimiento y al área jurídica durante semanas, con el costo de oportunidad correspondiente. | G7: Grave
B9: Guía: cubre en la misma redacción las cuatro caras del impacto — legal (multas y sanciones), reputacional (imagen y pérdida de clientes), de contagio (relación con terceros ilícitos) y operativa (interrupción y costos). No hace falta separarlas por elemento de riesgo.

Sheet A3 INHERENTE
B2: A3 · RIESGO INHERENTE = Calificación × Concentración (antes de controles)
B3: Resultado en tres niveles: por elemento, por indicador y de la entidad.
B4: Paso 5 de 10 · Se calcula solo · Sigue: A4 CONTROLES MINIMOS
B5: RIESGO INHERENTE POR ELEMENTO
B6: Elemento | C6: Calif. | D6: Conc. | E6: Riesgo | F6: Nivel
B7: 1. Actos u operaciones | C7: ='A1 EXPOSICION'!E35 | D7: ='A1 EXPOSICION'!F35 | E7: ='A1 EXPOSICION'!G35 | F7: =IFERROR(INDEX(PARAMETROS!$E$15:$E$19,MATCH(E7,PARAMETROS!$B$15:$B$19,1)),"")
B8: 2. Clientes / Usuarios | C8: ='A1 EXPOSICION'!E36 | D8: ='A1 EXPOSICION'!F36 | E8: ='A1 EXPOSICION'!G36 | F8: =IFERROR(INDEX(PARAMETROS!$E$15:$E$19,MATCH(E8,PARAMETROS!$B$15:$B$19,1)),"")
B9: 3. Países y áreas geográficas | C9: ='A1 EXPOSICION'!E37 | D9: ='A1 EXPOSICION'!F37 | E9: ='A1 EXPOSICION'!G37 | F9: =IFERROR(INDEX(PARAMETROS!$E$15:$E$19,MATCH(E9,PARAMETROS!$B$15:$B$19,1)),"")
B10: 4. Transacciones y canales | C10: ='A1 EXPOSICION'!E38 | D10: ='A1 EXPOSICION'!F38 | E10: ='A1 EXPOSICION'!G38 | F10: =IFERROR(INDEX(PARAMETROS!$E$15:$E$19,MATCH(E10,PARAMETROS!$B$15:$B$19,1)),"")
B12: RIESGO INHERENTE DE LA ENTIDAD | C12: ='A1 EXPOSICION'!E40 | D12: ='A1 EXPOSICION'!F40 | E12: ='A1 EXPOSICION'!G40 | F12: =IFERROR(INDEX(PARAMETROS!$E$15:$E$19,MATCH(E12,PARAMETROS!$B$15:$B$19,1)),"")
B14: RIESGO INHERENTE POR INDICADOR
B15: # | C15: Indicador | D15: Calif. | E15: Conc. | F15: Riesgo | G15: Nivel
B16: 1 | C16: ='A1 EXPOSICION'!D7 | D16: =IF('A1 EXPOSICION'!$G7="No","N/A",'A1 EXPOSICION'!P7) | E16: =IF('A1 EXPOSICION'!$G7="No","N/A",'A1 EXPOSICION'!Q7) | F16: =IF('A1 EXPOSICION'!$G7="No","N/A",'A1 EXPOSICION'!R7) | G16: =IF('A1 EXPOSICION'!$G7="No","No aplica",IFERROR(INDEX(PARAMETROS!$E$15:$E$19,MATCH(F16,PARAMETROS!$B$15:$B$19,1)),""))
B17: 2 | C17: ='A1 EXPOSICION'!D8 | D17: =IF('A1 EXPOSICION'!$G8="No","N/A",'A1 EXPOSICION'!P8) | E17: =IF('A1 EXPOSICION'!$G8="No","N/A",'A1 EXPOSICION'!Q8) | F17: =IF('A1 EXPOSICION'!$G8="No","N/A",'A1 EXPOSICION'!R8) | G17: =IF('A1 EXPOSICION'!$G8="No","No aplica",IFERROR(INDEX(PARAMETROS!$E$15:$E$19,MATCH(F17,PARAMETROS!$B$15:$B$19,1)),""))
B18: 3 | C18: ='A1 EXPOSICION'!D9 | D18: =IF('A1 EXPOSICION'!$G9="No","N/A",'A1 EXPOSICION'!P9) | E18: =IF('A1 EXPOSICION'!$G9="No","N/A",'A1 EXPOSICION'!Q9) | F18: =IF('A1 EXPOSICION'!$G9="No","N/A",'A1 EXPOSICION'!R9) | G18: =IF('A1 EXPOSICION'!$G9="No","No aplica",IFERROR(INDEX(PARAMETROS!$E$15:$E$19,MATCH(F18,PARAMETROS!$B$15:$B$19,1)),""))
B19: 4 | C19: ='A1 EXPOSICION'!D10 | D19: =IF('A1 EXPOSICION'!$G10="No","N/A",'A1 EXPOSICION'!P10) | E19: =IF('A1 EXPOSICION'!$G10="No","N/A",'A1 EXPOSICION'!Q10) | F19: =IF('A1 EXPOSICION'!$G10="No","N/A",'A1 EXPOSICION'!R10) | G19: =IF('A1 EXPOSICION'!$G10="No","No aplica",IFERROR(INDEX(PARAMETROS!$E$15:$E$19,MATCH(F19,PARAMETROS!$B$15:$B$19,1)),""))
B20: 5 | C20: ='A1 EXPOSICION'!D11 | D20: =IF('A1 EXPOSICION'!$G11="No","N/A",'A1 EXPOSICION'!P11) | E20: =IF('A1 EXPOSICION'!$G11="No","N/A",'A1 EXPOSICION'!Q11) | F20: =IF('A1 EXPOSICION'!$G11="No","N/A",'A1 EXPOSICION'!R11) | G20: =IF('A1 EXPOSICION'!$G11="No","No aplica",IFERROR(INDEX(PARAMETROS!$E$15:$E$19,MATCH(F20,PARAMETROS!$B$15:$B$19,1)),""))
B21: 6 | C21: ='A1 EXPOSICION'!D12 | D21: =IF('A1 EXPOSICION'!$G12="No","N/A",'A1 EXPOSICION'!P12) | E21: =IF('A1 EXPOSICION'!$G12="No","N/A",'A1 EXPOSICION'!Q12) | F21: =IF('A1 EXPOSICION'!$G12="No","N/A",'A1 EXPOSICION'!R12) | G21: =IF('A1 EXPOSICION'!$G12="No","No aplica",IFERROR(INDEX(PARAMETROS!$E$15:$E$19,MATCH(F21,PARAMETROS!$B$15:$B$19,1)),""))
B22: 7 | C22: ='A1 EXPOSICION'!D13 | D22: =IF('A1 EXPOSICION'!$G13="No","N/A",'A1 EXPOSICION'!P13) | E22: =IF('A1 EXPOSICION'!$G13="No","N/A",'A1 EXPOSICION'!Q13) | F22: =IF('A1 EXPOSICION'!$G13="No","N/A",'A1 EXPOSICION'!R13) | G22: =IF('A1 EXPOSICION'!$G13="No","No aplica",IFERROR(INDEX(PARAMETROS!$E$15:$E$19,MATCH(F22,PARAMETROS!$B$15:$B$19,1)),""))
B23: 8 | C23: ='A1 EXPOSICION'!D14 | D23: =IF('A1 EXPOSICION'!$G14="No","N/A",'A1 EXPOSICION'!P14) | E23: =IF('A1 EXPOSICION'!$G14="No","N/A",'A1 EXPOSICION'!Q14) | F23: =IF('A1 EXPOSICION'!$G14="No","N/A",'A1 EXPOSICION'!R14) | G23: =IF('A1 EXPOSICION'!$G14="No","No aplica",IFERROR(INDEX(PARAMETROS!$E$15:$E$19,MATCH(F23,PARAMETROS!$B$15:$B$19,1)),""))
B24: 9 | C24: ='A1 EXPOSICION'!D15 | D24: =IF('A1 EXPOSICION'!$G15="No","N/A",'A1 EXPOSICION'!P15) | E24: =IF('A1 EXPOSICION'!$G15="No","N/A",'A1 EXPOSICION'!Q15) | F24: =IF('A1 EXPOSICION'!$G15="No","N/A",'A1 EXPOSICION'!R15) | G24: =IF('A1 EXPOSICION'!$G15="No","No aplica",IFERROR(INDEX(PARAMETROS!$E$15:$E$19,MATCH(F24,PARAMETROS!$B$15:$B$19,1)),""))
B25: 10 | C25: ='A1 EXPOSICION'!D16 | D25: =IF('A1 EXPOSICION'!$G16="No","N/A",'A1 EXPOSICION'!P16) | E25: =IF('A1 EXPOSICION'!$G16="No","N/A",'A1 EXPOSICION'!Q16) | F25: =IF('A1 EXPOSICION'!$G16="No","N/A",'A1 EXPOSICION'!R16) | G25: =IF('A1 EXPOSICION'!$G16="No","No aplica",IFERROR(INDEX(PARAMETROS!$E$15:$E$19,MATCH(F25,PARAMETROS!$B$15:$B$19,1)),""))
B26: 11 | C26: ='A1 EXPOSICION'!D17 | D26: =IF('A1 EXPOSICION'!$G17="No","N/A",'A1 EXPOSICION'!P17) | E26: =IF('A1 EXPOSICION'!$G17="No","N/A",'A1 EXPOSICION'!Q17) | F26: =IF('A1 EXPOSICION'!$G17="No","N/A",'A1 EXPOSICION'!R17) | G26: =IF('A1 EXPOSICION'!$G17="No","No aplica",IFERROR(INDEX(PARAMETROS!$E$15:$E$19,MATCH(F26,PARAMETROS!$B$15:$B$19,1)),""))
B27: 12 | C27: ='A1 EXPOSICION'!D18 | D27: =IF('A1 EXPOSICION'!$G18="No","N/A",'A1 EXPOSICION'!P18) | E27: =IF('A1 EXPOSICION'!$G18="No","N/A",'A1 EXPOSICION'!Q18) | F27: =IF('A1 EXPOSICION'!$G18="No","N/A",'A1 EXPOSICION'!R18) | G27: =IF('A1 EXPOSICION'!$G18="No","No aplica",IFERROR(INDEX(PARAMETROS!$E$15:$E$19,MATCH(F27,PARAMETROS!$B$15:$B$19,1)),""))
... B40: 25 | C40: ='A1 EXPOSICION'!D31 | D40: =IF('A1 EXPOSICION'!$G31="No","N/A",'A1 EXPOSICION'!P31) | E40: =IF('A1 EXPOSICION'!$G31="No","N/A",'A1 EXPOSICION'!Q31) | F40: =IF('A1 EXPOSICION'!$G31="No","N/A",'A1 EXPOSICION'!R31) | G40: =IF('A1 EXPOSICION'!$G31="No","No aplica",IFERROR(INDEX(PARAMETROS!$E$15:$E$19,MATCH(F40,PARAMETROS!$B$15:$B$19,1)),""))
B41: Un indicador marcado «No aplica» en A1 se muestra aquí como «No aplica», no como riesgo cero: no se evaluó, no es que haya salido bajo. Sale del numerador y del denominador del elemento.
B43: MAPA DE CALOR — Calificación (col) × Concentración (fila)
B44: Conc\Calif | C44: 1 | D44: 2 | E44: 3 | F44: 4 | G44: 5
B45: 5 | C45: 5 | D45: 10 | E45: 15 | F45: 20 | G45: 25
B46: 4 | C46: 4 | D46: 8 | E46: 12 | F46: 16 | G46: 20
B47: 3 | C47: 3 | D47: 6 | E47: 9 | F47: 12 | G47: 15
B48: 2 | C48: 2 | D48: 4 | E48: 6 | F48: 8 | G48: 10
B49: 1 | C49: 1 | D49: 2 | E49: 3 | F49: 4 | G49: 5
B51: Tu entidad (nivel inherente): | D51: ='A3 INHERENTE'!$F$12

Sheet A4 CONTROLES MINIMOS
B2: A4 · CATÁLOGO DE CONTROLES MÍNIMOS — las 14 obligaciones del Manual (Art. 37 Bis)
B3: Éste es el denominador de la mitigación. La efectividad NO se promedia sobre los controles que registres: se mide contra las 14 obligaciones del catálogo. Una obligación no registrada computa 0%; solo sale del cálculo si es «No aplica» conforme al Art. 37 Bis 2 y así consta en tu Manual.
B4: Paso 6 de 10 · Viene de: A3 INHERENTE · Sigue: A5 RESIDUAL · Controles por encima del mínimo: A4 BIS
B6: Fr. | C6: Contenido mínimo del Manual (Art. 37 Bis) | D6: Fundamento verificado | E6: Qué se espera (referencia) | F6: ¿Admite «No aplica»? | G6: Resultado (Art. 48) | H6: % | I6: Numeral del Manual que lo prevé | J6: Evidencia de aplicación efectiva y dónde se resguarda | K6: Justificación del «No aplica» (numeral del Manual, Art. 37 Bis 2) | L6: Aviso
B7: I | C7: Criterios para la identificación y conocimiento de Clientes o Usuarias | D7: Arts. 12, 17 y 17 Bis; Cap. III Ter | E7: Procedimiento escrito para integrar el expediente según el Grado de Riesgo, con los datos y documentos de los Anexos aplicables a tu fracción, verificación de identidad y cuestionario de conocimiento del Cliente. | F7: No | G7: Cumple | H7: =IF($G7="","",IF($G7="No aplica","",IF(OR($I7="",$J7=""),0,IFERROR(INDEX(PARAMETROS!$I$15:$I$18,MATCH($G7,PARAMETROS!$H$15:$H$18,0)),0)))) | I7: Manual, numeral 4.1 | J7: Expedientes íntegros con acuse de verificación de identificación oficial; muestreo trimestral firmado. | L7: =IF($G7="","Falta calificar esta obligación del Manual (Art. 37 Bis).",IF($G7="No aplica",IF($K7="","Exclusión sin constancia en el Manual: el Art. 37 Bis 2 exige hacerla constar por escrito.",""),IF($G7="No cumple","No cumple: puede actualizar una sanción (Art. 48 fr. IV). Llévalo al plan de acción de A8.",IF(OR($I7="",$J7=""),"Sin numeral del Manual o sin evidencia de aplicación efectiva: la obligación computa 0% (Art. 10 Septies 1, fr. III).",""))))
B8: II | C8: Mecanismos de clasificación de Riesgo | D8: Art. 23 Bis | E8: Modelo escrito que califique a cada Cliente en al menos tres grados, congruente con esta metodología, con reevaluación al menos cada seis meses (hoja B CLIENTE). | F8: No | G8: Cumple mayoritariamente | H8: =IF($G8="","",IF($G8="No aplica","",IF(OR($I8="",$J8=""),0,IFERROR(INDEX(PARAMETROS!$I$15:$I$18,MATCH($G8,PARAMETROS!$H$15:$H$18,0)),0)))) | I8: Manual, numeral 4.3 | J8: Cédulas de calificación de los 86 Clientes; falta evidenciar la reevaluación semestral de dos de ellos. | L8: =IF($G8="","Falta calificar esta obligación del Manual (Art. 37 Bis).",IF($G8="No aplica",IF($K8="","Exclusión sin constancia en el Manual: el Art. 37 Bis 2 exige hacerla constar por escrito.",""),IF($G8="No cumple","No cumple: puede actualizar una sanción (Art. 48 fr. IV). Llévalo al plan de acción de A8.",IF(OR($I8="",$J8=""),"Sin numeral del Manual o sin evidencia de aplicación efectiva: la obligación computa 0% (Art. 10 Septies 1, fr. III).",""))))
B9: III | C9: Medidas de debida diligencia aplicables conforme al Grado de Riesgo | D9: Arts. 17 y 17 Bis; Arts. 23 Ter 1 a 5 | E9: Regla explícita de qué expediente corresponde a cada grado: simplificado, completo del Art. 12, o reforzado con cuestionario y Firma Electrónica. | F9: No | G9: Cumple mayoritariamente | H9: =IF($G9="","",IF($G9="No aplica","",IF(OR($I9="",$J9=""),0,IFERROR(INDEX(PARAMETROS!$I$15:$I$18,MATCH($G9,PARAMETROS!$H$15:$H$18,0)),0)))) | I9: Manual, numeral 4.4 | J9: Matriz de correspondencia grado–expediente aplicada; dos expedientes reforzados sin acuse de Firma Electrónica. | L9: =IF($G9="","Falta calificar esta obligación del Manual (Art. 37 Bis).",IF($G9="No aplica",IF($K9="","Exclusión sin constancia en el Manual: el Art. 37 Bis 2 exige hacerla constar por escrito.",""),IF($G9="No cumple","No cumple: puede actualizar una sanción (Art. 48 fr. IV). Llévalo al plan de acción de A8.",IF(OR($I9="",$J9=""),"Sin numeral del Manual o sin evidencia de aplicación efectiva: la obligación computa 0% (Art. 10 Septies 1, fr. III).",""))))
B10: IV | C10: Identificación y seguimiento reforzado de Personas Políticamente Expuestas | D10: Arts. 23 Bis 3 y 23 Bis 4 | E10: Procedimiento de detección de PEP nacionales y extranjeras y de sus allegados, factores de Riesgo adicionales, y aprobación de un directivo para PEP extranjera de riesgo alto. | F10: No | G10: Cumple parcialmente | H10: =IF($G10="","",IF($G10="No aplica","",IF(OR($I10="",$J10=""),0,IFERROR(INDEX(PARAMETROS!$I$15:$I$18,MATCH($G10,PARAMETROS!$H$15:$H$18,0)),0)))) | I10: Manual, numeral 4.6 | J10: Se declara la búsqueda de PEP pero no se conserva la constancia por operación. | L10: =IF($G10="","Falta calificar esta obligación del Manual (Art. 37 Bis).",IF($G10="No aplica",IF($K10="","Exclusión sin constancia en el Manual: el Art. 37 Bis 2 exige hacerla constar por escrito.",""),IF($G10="No cumple","No cumple: puede actualizar una sanción (Art. 48 fr. IV). Llévalo al plan de acción de A8.",IF(OR($I10="",$J10=""),"Sin numeral del Manual o sin evidencia de aplicación efectiva: la obligación computa 0% (Art. 10 Septies 1, fr. III).",""))))
B11: V | C11: Detección de actos u operaciones que se apartan del Perfil transaccional | D11: Art. 41 fr. II | E11: Perfil transaccional documentado por Cliente y alertas por desviación, con bitácora de la alerta, su análisis y su conclusión. | F11: Condicionado | G11: Cumple parcialmente | H11: =IF($G11="","",IF($G11="No aplica","",IF(OR($I11="",$J11=""),0,IFERROR(INDEX(PARAMETROS!$I$15:$I$18,MATCH($G11,PARAMETROS!$H$15:$H$18,0)),0)))) | I11: Manual, numeral 6.4 | J11: Perfil transaccional documentado; las alertas se revisan sin bitácora de conclusión. | L11: =IF($G11="","Falta calificar esta obligación del Manual (Art. 37 Bis).",IF($G11="No aplica",IF($K11="","Exclusión sin constancia en el Manual: el Art. 37 Bis 2 exige hacerla constar por escrito.",""),IF($G11="No cumple","No cumple: puede actualizar una sanción (Art. 48 fr. IV). Llévalo al plan de acción de A8.",IF(OR($I11="",$J11=""),"Sin numeral del Manual o sin evidencia de aplicación efectiva: la obligación computa 0% (Art. 10 Septies 1, fr. III).",""))))
B12: VI | C12: Procedimientos para la presentación de Avisos e Informes | D12: Cap. V de las Reglas; Art. 23 de la Ley | E12: Flujo interno con responsable y plazos: Aviso ordinario a más tardar el día 17 del mes inmediato siguiente, y protocolo de 24 horas. | F12: No | G12: Cumple | H12: =IF($G12="","",IF($G12="No aplica","",IF(OR($I12="",$J12=""),0,IFERROR(INDEX(PARAMETROS!$I$15:$I$18,MATCH($G12,PARAMETROS!$H$15:$H$18,0)),0)))) | I12: Manual, numeral 5.2 | J12: Acuses del portal por los 14 Avisos del periodo, conciliados con el registro de operaciones. | L12: =IF($G12="","Falta calificar esta obligación del Manual (Art. 37 Bis).",IF($G12="No aplica",IF($K12="","Exclusión sin constancia en el Manual: el Art. 37 Bis 2 exige hacerla constar por escrito.",""),IF($G12="No cumple","No cumple: puede actualizar una sanción (Art. 48 fr. IV). Llévalo al plan de acción de A8.",IF(OR($I12="",$J12=""),"Sin numeral del Manual o sin evidencia de aplicación efectiva: la obligación computa 0% (Art. 10 Septies 1, fr. III).",""))))
B13: VII | C13: Mecanismos de conservación de información y documentación | D13: Art. 10 Septies 3, 3er párr.; Art. 41 fr. I y IV | E13: Política de resguardo por diez años, lugar y medio de conservación, y medidas de seguridad contra pérdida, alteración u ocultamiento. | F13: No | G13: Cumple | H13: =IF($G13="","",IF($G13="No aplica","",IF(OR($I13="",$J13=""),0,IFERROR(INDEX(PARAMETROS!$I$15:$I$18,MATCH($G13,PARAMETROS!$H$15:$H$18,0)),0)))) | I13: Manual, numeral 8.1 | J13: Política de resguardo firmada, respaldo cifrado y control de acceso al repositorio. | L13: =IF($G13="","Falta calificar esta obligación del Manual (Art. 37 Bis).",IF($G13="No aplica",IF($K13="","Exclusión sin constancia en el Manual: el Art. 37 Bis 2 exige hacerla constar por escrito.",""),IF($G13="No cumple","No cumple: puede actualizar una sanción (Art. 48 fr. IV). Llévalo al plan de acción de A8.",IF(OR($I13="",$J13=""),"Sin numeral del Manual o sin evidencia de aplicación efectiva: la obligación computa 0% (Art. 10 Septies 1, fr. III).",""))))
B14: VIII | C14: Seguimiento y acumulación de actos u operaciones frente a los umbrales | D14: Art. 17, penúltimo párr. de la Ley; Art. 41 fr. II | E14: Mecanismo que agrupe las operaciones del mismo Cliente y dispare el Aviso cuando la suma acumulada alcance el umbral de tu fracción. | F14: Condicionado | G14: Cumple mayoritariamente | H14: =IF($G14="","",IF($G14="No aplica","",IF(OR($I14="",$J14=""),0,IFERROR(INDEX(PARAMETROS!$I$15:$I$18,MATCH($G14,PARAMETROS!$H$15:$H$18,0)),0)))) | I14: Manual, numeral 5.4 | J14: Reporte de acumulación del sistema; falta prueba de recorrido de un caso completo. | L14: =IF($G14="","Falta calificar esta obligación del Manual (Art. 37 Bis).",IF($G14="No aplica",IF($K14="","Exclusión sin constancia en el Manual: el Art. 37 Bis 2 exige hacerla constar por escrito.",""),IF($G14="No cumple","No cumple: puede actualizar una sanción (Art. 48 fr. IV). Llévalo al plan de acción de A8.",IF(OR($I14="",$J14=""),"Sin numeral del Manual o sin evidencia de aplicación efectiva: la obligación computa 0% (Art. 10 Septies 1, fr. III).",""))))
B15: IX | C15: Identificación de personas publicadas en listas de autoridades nacionales u organismos internacionales | D15: Arts. 38 y 41 fr. V | E15: Búsqueda documentada del Cliente, su Beneficiario Controlador y sus apoderados contra las listas aplicables, con constancia por operación y protocolo ante coincidencia. | F15: No | G15: Cumple | H15: =IF($G15="","",IF($G15="No aplica","",IF(OR($I15="",$J15=""),0,IFERROR(INDEX(PARAMETROS!$I$15:$I$18,MATCH($G15,PARAMETROS!$H$15:$H$18,0)),0)))) | I15: Manual, numeral 6.2 | J15: Bitácora de validación contra listas con acuse por operación en el expediente electrónico. | L15: =IF($G15="","Falta calificar esta obligación del Manual (Art. 37 Bis).",IF($G15="No aplica",IF($K15="","Exclusión sin constancia en el Manual: el Art. 37 Bis 2 exige hacerla constar por escrito.",""),IF($G15="No cumple","No cumple: puede actualizar una sanción (Art. 48 fr. IV). Llévalo al plan de acción de A8.",IF(OR($I15="",$J15=""),"Sin numeral del Manual o sin evidencia de aplicación efectiva: la obligación computa 0% (Art. 10 Septies 1, fr. III).",""))))
B16: X | C16: Funciones y responsabilidades de la persona Representante Encargada de Cumplimiento | D16: Art. 20 de la Ley | E16: Designación vigente y acreditada ante el SAT, con funciones, nivel de autoridad y suplencia definidos por escrito. | F16: Condicionado | G16: Cumple | H16: =IF($G16="","",IF($G16="No aplica","",IF(OR($I16="",$J16=""),0,IFERROR(INDEX(PARAMETROS!$I$15:$I$18,MATCH($G16,PARAMETROS!$H$15:$H$18,0)),0)))) | I16: Manual, numeral 3.1 | J16: Constancia de alta de la Representante Encargada de Cumplimiento y descripción de funciones firmada. | L16: =IF($G16="","Falta calificar esta obligación del Manual (Art. 37 Bis).",IF($G16="No aplica",IF($K16="","Exclusión sin constancia en el Manual: el Art. 37 Bis 2 exige hacerla constar por escrito.",""),IF($G16="No cumple","No cumple: puede actualizar una sanción (Art. 48 fr. IV). Llévalo al plan de acción de A8.",IF(OR($I16="",$J16=""),"Sin numeral del Manual o sin evidencia de aplicación efectiva: la obligación computa 0% (Art. 10 Septies 1, fr. III).",""))))
B17: XI | C17: Programas de capacitación | D17: Cap. XII, Art. 39 Bis | E17: Programa anual con contenido, destinatarios (órgano de administración, directivos, personal de atención, de envío de Avisos y de auditoría) y constancias de acreditación. | F17: No | G17: Cumple mayoritariamente | H17: =IF($G17="","",IF($G17="No aplica","",IF(OR($I17="",$J17=""),0,IFERROR(INDEX(PARAMETROS!$I$15:$I$18,MATCH($G17,PARAMETROS!$H$15:$H$18,0)),0)))) | I17: Manual, numeral 9.1 | J17: Constancias de capacitación 2026 del 82% del personal objetivo. | L17: =IF($G17="","Falta calificar esta obligación del Manual (Art. 37 Bis).",IF($G17="No aplica",IF($K17="","Exclusión sin constancia en el Manual: el Art. 37 Bis 2 exige hacerla constar por escrito.",""),IF($G17="No cumple","No cumple: puede actualizar una sanción (Art. 48 fr. IV). Llévalo al plan de acción de A8.",IF(OR($I17="",$J17=""),"Sin numeral del Manual o sin evidencia de aplicación efectiva: la obligación computa 0% (Art. 10 Septies 1, fr. III).",""))))
B18: XII | C18: Mecanismos de control interno, supervisión y auditoría | D18: Cap. XIV, Arts. 42 a 51 | E18: Programa de revisión anual y designación de quien emite el dictamen: puede ser el área interna si tu riesgo es bajo o medio (Art. 44); auditor externo certificado por la UIF si es alto, o si así lo eliges (Art. 45). Ver A6. | F18: No | G18: Cumple parcialmente | H18: =IF($G18="","",IF($G18="No aplica","",IF(OR($I18="",$J18=""),0,IFERROR(INDEX(PARAMETROS!$I$15:$I$18,MATCH($G18,PARAMETROS!$H$15:$H$18,0)),0)))) | I18: Manual, numeral 10.1 | J18: Programa de auditoría aprobado; primer dictamen aún no exigible (primer periodo: 2028). | L18: =IF($G18="","Falta calificar esta obligación del Manual (Art. 37 Bis).",IF($G18="No aplica",IF($K18="","Exclusión sin constancia en el Manual: el Art. 37 Bis 2 exige hacerla constar por escrito.",""),IF($G18="No cumple","No cumple: puede actualizar una sanción (Art. 48 fr. IV). Llévalo al plan de acción de A8.",IF(OR($I18="",$J18=""),"Sin numeral del Manual o sin evidencia de aplicación efectiva: la obligación computa 0% (Art. 10 Septies 1, fr. III).",""))))
... B20: XIV | C20: Procedimientos para la actualización del propio Manual de Políticas Internas | D20: Art. 37 Bis 3 | E20: Procedimiento y periodicidad de actualización, responsable, control de versiones y atención a los ajustes que señale el SAT. | F20: No | G20: Cumple mayoritariamente | H20: =IF($G20="","",IF($G20="No aplica","",IF(OR($I20="",$J20=""),0,IFERROR(INDEX(PARAMETROS!$I$15:$I$18,MATCH($G20,PARAMETROS!$H$15:$H$18,0)),0)))) | I20: Manual, numeral 12.1 | J20: Control de versiones del Manual; falta fijar la periodicidad mínima de revisión. | L20: =IF($G20="","Falta calificar esta obligación del Manual (Art. 37 Bis).",IF($G20="No aplica",IF($K20="","Exclusión sin constancia en el Manual: el Art. 37 Bis 2 exige hacerla constar por escrito.",""),IF($G20="No cumple","No cumple: puede actualizar una sanción (Art. 48 fr. IV). Llévalo al plan de acción de A8.",IF(OR($I20="",$J20=""),"Sin numeral del Manual o sin evidencia de aplicación efectiva: la obligación computa 0% (Art. 10 Septies 1, fr. III).",""))))
B23: RESULTADO DEL CATÁLOGO — ESTA ES LA MITIGACIÓN DE TODA LA MATRIZ
B24: Obligaciones del catálogo (Art. 37 Bis): | F24: =COUNTA($B$7:$B$20)
B25: Excluidas por «No aplica» (Art. 37 Bis 2): | F25: =COUNTIF($G$7:$G$20,"No aplica")
B26: Obligaciones exigibles — denominador: | F26: =$F$24-$F$25
B27: Suma de los porcentajes obtenidos: | F27: =SUM($H$7:$H$20)
B28: EFECTIVIDAD DE LOS MITIGANTES: | F28: =IFERROR($F$27/$F$26,0)
B29: Tope máximo de reducción (PARÁMETROS C30): | F29: =PARAMETROS!$C$30
B30: REDUCCIÓN QUE SE APLICARÁ AL RIESGO INHERENTE: | F30: =$F$28*$F$29
B32: ALERTAS DEL CATÁLOGO
B33: Obligaciones en «No cumple»: | F33: =COUNTIF($G$7:$G$20,"No cumple")
B34: Exclusiones sin constancia en el Manual: | F34: =SUMPRODUCT(--($G$7:$G$20="No aplica"),--($K$7:$K$20=""))
B35: Obligaciones sin numeral del Manual o sin evidencia: | F35: =SUMPRODUCT(--($G$7:$G$20<>""),--($G$7:$G$20<>"No aplica"),--((($I$7:$I$20="")+($J$7:$J$20=""))>0))
B36: Obligaciones sin calificar: | F36: =COUNTBLANK($G$7:$G$20)
B38: =IF($F$33>0,"Hay "&$F$33&" obligación(es) en «No cumple». El Art. 48 fr. IV las define como incumplimiento que puede actualizar una sanción: no basta con que bajen el promedio, deben ir al plan de acción de A8.",IF($F$36>0,"Faltan "&$F$36&" obligación(es) por calificar. Mientras no las califiques computan 0% y tu residual sale más alto de lo real.","Catálogo completo: las 14 obligaciones están calificadas y ninguna está en «No cumple»."))
B40: Cómo se calcula: Efectividad = suma de los porcentajes ÷ obligaciones exigibles. El denominador es fijo (14) y solo baja cuando una obligación es «No aplica». Por eso registrar menos controles ya NO mejora el resultado: lo empeora.
B41: El Art. 37 Bis 2 no enlista fracciones: exenta cualquier contenido del Manual referido a actos u operaciones que se determine no realizar, con constancia en el propio Manual. Que en esta matriz sólo se habilite «No aplica» en las fracciones V, VIII y X es criterio de la herramienta, y de forma condicionada: V para quien opera exclusivamente con Clientes ocasionales sin Relación de Negocios; VIII para las fracciones cuyo umbral no admite acumulación; X para la persona física que realiza la Actividad Vulnerable sin estructura, porque el Art. 20 de la Ley ata la designación a las personas morales. Las otras once no admiten exclusión.
B42: El Art. 48 fr. V exige que el auditor verifique que la exclusión no actualice un incumplimiento y que sea consistente con el análisis de Riesgos. Por eso la justificación pide el numeral del Manual donde consta la exención, no un texto libre.
B43: Una obligación cubierta en el papel pero sin evidencia de aplicación efectiva computa 0%: el Art. 10 Septies 1, fr. III habla de los mitigantes «así como su efectiva aplicación». Control diseñado, control implementado y control operando son tres estados distintos y se prueban distinto.
B44: Pendiente declarado: la columna «Qué se espera» es todavía guía común a las 30 fracciones. El anexo sectorial —qué se espera en cada obligación según tu Actividad Vulnerable— es el siguiente entregable y no altera el denominador ni el cálculo.

Sheet A4 BIS ADICIONALES
B2: A4 BIS · CONTROLES ADICIONALES (por encima del mínimo) — INFORMATIVO
B3: Registra aquí los controles que tienes por encima de las 14 obligaciones del catálogo. Esta hoja NO cambia el resultado: la mitigación se calcula en A4 CONTROLES MINIMOS. Sirve para documentar tu programa completo ante un requerimiento sin alterar el número.
B4: Complemento del paso 6 · No entra en el cálculo · Sigue: A5 RESIDUAL
B6: # | C6: Descripción del control | D6: Elemento que mitiga (informativo) | E6: Naturaleza | F6: Automatización | G6: Frecuencia | H6: Efectividad | I6: Efectividad % | J6: Numeral del Manual que lo prevé | K6: Evidencia de aplicación efectiva y dónde se resguarda | L6: Aviso
B7: 1 | C7: El sistema valida a cada Cliente, a su Beneficiario Controlador y a los apoderados contra la lista de personas bloqueadas del Art. 38 y las listas internacionales, en cada operación y no sólo al alta. | D7: 2 | E7: Preventivo | F7: Automático | G7: Permanente | H7: Cumple | I7: =IF($H7="","",IF(OR($J7="",$K7=""),0,IFERROR(INDEX(PARAMETROS!$I$15:$I$18,MATCH($H7,PARAMETROS!$H$15:$H$18,0)),0))) | J7: Manual, numeral 6.2 | K7: Bitácora de validación con acuse por operación; 112 corridas conciliadas contra el número de operaciones del periodo. | L7: =IF($H7="","",IF(OR($J7="",$K7=""),"Sin numeral del Manual o sin evidencia: el mitigante no acredita aplicación efectiva (Art. 10 Septies 1, fr. III).",""))
B8: 2 | C8: Política de aceptación de efectivo con umbral interno de 150,000 pesos por operación, por debajo del umbral de aviso, con validación del origen y autorización escrita de la Encargada de Cumplimiento por encima de ese monto. | D8: 4 | E8: Preventivo | F8: Semiautomático | G8: Permanente | H8: Cumple mayoritariamente | I8: =IF($H8="","",IF(OR($J8="",$K8=""),0,IFERROR(INDEX(PARAMETROS!$I$15:$I$18,MATCH($H8,PARAMETROS!$H$15:$H$18,0)),0))) | J8: Manual, numeral 7.1 | K8: Reporte mensual de excepciones firmado; faltan las autorizaciones de dos operaciones de mayo de 2026. | L8: =IF($H8="","",IF(OR($J8="",$K8=""),"Sin numeral del Manual o sin evidencia: el mitigante no acredita aplicación efectiva (Art. 10 Septies 1, fr. III).",""))
B9: 3 | C9: Verificación de la constitución y del objeto social de toda persona moral compradora en el registro electrónico de la Secretaría de Economía, antes de la firma. | D9: 2 | E9: Preventivo | F9: Manual | G9: Permanente | H9: Cumple | I9: =IF($H9="","",IF(OR($J9="",$K9=""),0,IFERROR(INDEX(PARAMETROS!$I$15:$I$18,MATCH($H9,PARAMETROS!$H$15:$H$18,0)),0))) | J9: Manual, numeral 4.2 | K9: Impresión del folio electrónico mercantil integrada a los 31 expedientes de persona moral del periodo. | L9: =IF($H9="","",IF(OR($J9="",$K9=""),"Sin numeral del Manual o sin evidencia: el mitigante no acredita aplicación efectiva (Art. 10 Septies 1, fr. III).",""))
B10: 4 | C10: Regla de cuatro ojos: ninguna operación que supere el umbral de aviso se firma sin visto bueno documentado de la Encargada de Cumplimiento, además del ejecutivo de venta. | D10: 1 | E10: Preventivo | F10: Manual | G10: Permanente | H10: Cumple | I10: =IF($H10="","",IF(OR($J10="",$K10=""),0,IFERROR(INDEX(PARAMETROS!$I$15:$I$18,MATCH($H10,PARAMETROS!$H$15:$H$18,0)),0))) | J10: Manual, numeral 5.1 | K10: Cédula de doble firma en las 47 operaciones del periodo que superaron el umbral. | L10: =IF($H10="","",IF(OR($J10="",$K10=""),"Sin numeral del Manual o sin evidencia: el mitigante no acredita aplicación efectiva (Art. 10 Septies 1, fr. III).",""))
B11: 5 | C11: Alerta automática cuando el pago proviene de un tercero distinto del comprador o de una cuenta no declarada en el expediente. | D11: 4 | E11: Detectivo | F11: Automático | G11: Permanente | H11: Cumple mayoritariamente | I11: =IF($H11="","",IF(OR($J11="",$K11=""),0,IFERROR(INDEX(PARAMETROS!$I$15:$I$18,MATCH($H11,PARAMETROS!$H$15:$H$18,0)),0))) | J11: Manual, numeral 6.4 | K11: Se dispararon 7 alertas en el periodo; 5 tienen dictamen documentado y 2 siguen en análisis. | L11: =IF($H11="","",IF(OR($J11="",$K11=""),"Sin numeral del Manual o sin evidencia: el mitigante no acredita aplicación efectiva (Art. 10 Septies 1, fr. III).",""))
B12: 6 | C12: Capacitación específica de fuerza de ventas sobre señales de alerta en preventa, adicional al programa anual obligatorio. | D12: 2 | E12: Preventivo | F12: Manual | G12: Periódico | H12: Cumple mayoritariamente | I12: =IF($H12="","",IF(OR($J12="",$K12=""),0,IFERROR(INDEX(PARAMETROS!$I$15:$I$18,MATCH($H12,PARAMETROS!$H$15:$H$18,0)),0))) | J12: Manual, numeral 9.2 | K12: Lista de asistencia de la sesión de marzo de 2026; cubrió a 9 de los 11 ejecutivos. | L12: =IF($H12="","",IF(OR($J12="",$K12=""),"Sin numeral del Manual o sin evidencia: el mitigante no acredita aplicación efectiva (Art. 10 Septies 1, fr. III).",""))
B13: 7 | I13: =IF($H13="","",IF(OR($J13="",$K13=""),0,IFERROR(INDEX(PARAMETROS!$I$15:$I$18,MATCH($H13,PARAMETROS!$H$15:$H$18,0)),0))) | L13: =IF($H13="","",IF(OR($J13="",$K13=""),"Sin numeral del Manual o sin evidencia: el mitigante no acredita aplicación efectiva (Art. 10 Septies 1, fr. III).",""))
B14: 8 | I14: =IF($H14="","",IF(OR($J14="",$K14=""),0,IFERROR(INDEX(PARAMETROS!$I$15:$I$18,MATCH($H14,PARAMETROS!$H$15:$H$18,0)),0))) | L14: =IF($H14="","",IF(OR($J14="",$K14=""),"Sin numeral del Manual o sin evidencia: el mitigante no acredita aplicación efectiva (Art. 10 Septies 1, fr. III).",""))
B15: 9 | I15: =IF($H15="","",IF(OR($J15="",$K15=""),0,IFERROR(INDEX(PARAMETROS!$I$15:$I$18,MATCH($H15,PARAMETROS!$H$15:$H$18,0)),0))) | L15: =IF($H15="","",IF(OR($J15="",$K15=""),"Sin numeral del Manual o sin evidencia: el mitigante no acredita aplicación efectiva (Art. 10 Septies 1, fr. III).",""))
B16: 10 | I16: =IF($H16="","",IF(OR($J16="",$K16=""),0,IFERROR(INDEX(PARAMETROS!$I$15:$I$18,MATCH($H16,PARAMETROS!$H$15:$H$18,0)),0))) | L16: =IF($H16="","",IF(OR($J16="",$K16=""),"Sin numeral del Manual o sin evidencia: el mitigante no acredita aplicación efectiva (Art. 10 Septies 1, fr. III).",""))
B17: 11 | I17: =IF($H17="","",IF(OR($J17="",$K17=""),0,IFERROR(INDEX(PARAMETROS!$I$15:$I$18,MATCH($H17,PARAMETROS!$H$15:$H$18,0)),0))) | L17: =IF($H17="","",IF(OR($J17="",$K17=""),"Sin numeral del Manual o sin evidencia: el mitigante no acredita aplicación efectiva (Art. 10 Septies 1, fr. III).",""))
B18: 12 | I18: =IF($H18="","",IF(OR($J18="",$K18=""),0,IFERROR(INDEX(PARAMETROS!$I$15:$I$18,MATCH($H18,PARAMETROS!$H$15:$H$18,0)),0))) | L18: =IF($H18="","",IF(OR($J18="",$K18=""),"Sin numeral del Manual o sin evidencia: el mitigante no acredita aplicación efectiva (Art. 10 Septies 1, fr. III).",""))
B19: 13 | I19: =IF($H19="","",IF(OR($J19="",$K19=""),0,IFERROR(INDEX(PARAMETROS!$I$15:$I$18,MATCH($H19,PARAMETROS!$H$15:$H$18,0)),0))) | L19: =IF($H19="","",IF(OR($J19="",$K19=""),"Sin numeral del Manual o sin evidencia: el mitigante no acredita aplicación efectiva (Art. 10 Septies 1, fr. III).",""))
B20: 14 | I20: =IF($H20="","",IF(OR($J20="",$K20=""),0,IFERROR(INDEX(PARAMETROS!$I$15:$I$18,MATCH($H20,PARAMETROS!$H$15:$H$18,0)),0))) | L20: =IF($H20="","",IF(OR($J20="",$K20=""),"Sin numeral del Manual o sin evidencia: el mitigante no acredita aplicación efectiva (Art. 10 Septies 1, fr. III).",""))
B21: 15 | I21: =IF($H21="","",IF(OR($J21="",$K21=""),0,IFERROR(INDEX(PARAMETROS!$I$15:$I$18,MATCH($H21,PARAMETROS!$H$15:$H$18,0)),0))) | L21: =IF($H21="","",IF(OR($J21="",$K21=""),"Sin numeral del Manual o sin evidencia: el mitigante no acredita aplicación efectiva (Art. 10 Septies 1, fr. III).",""))
B23: ESTOS CONTROLES NO ENTRAN EN EL CÁLCULO
B24: La mitigación se mide contra el catálogo de contenidos mínimos del Manual (Art. 37 Bis), en la hoja A4 CONTROLES MINIMOS. Un control adicional excelente no sube el resultado, y uno adicional deficiente tampoco lo baja: lo que califica es la cobertura de las obligaciones. Documentarlos aquí sí fortalece el expediente.
B30: Controles adicionales registrados: | D30: =COUNTA($C$7:$C$21)
B31: Adicionales sin numeral del Manual o sin evidencia: | D31: =SUMPRODUCT(--($H$7:$H$21<>""),--((($J$7:$J$21="")+($K$7:$K$21=""))>0))
B32: Aunque no cuenten para el número, un control que declaras sin numeral ni evidencia es un flanco: el auditor puede preguntar por él. Regístralo completo o no lo registres.

Sheet A5 RESIDUAL
B2: A5 · RIESGO RESIDUAL = Riesgo inherente × (1 − Reducción aplicada)
B3: La mitigación se mide una sola vez, a nivel de la entidad, y se aplica igual a los tres niveles: indicador, elemento y entidad. Si el residual supera tu tolerancia, exige plan de acción (hoja A8).
B4: Paso 7 de 10 · Se calcula solo · Sigue: A6 TABLERO
B5: MITIGACIÓN APLICADA — SE CALCULA UNA SOLA VEZ, A NIVEL ENTIDAD
B6: Efectividad de los mitigantes contra el catálogo de 14 obligaciones (hoja A4 CONTROLES MINIMOS): | F6: ='A4 CONTROLES MINIMOS'!$F$28
B7: Tope máximo de reducción (PARÁMETROS, celda C30): | F7: =PARAMETROS!$C$30
B8: Reducción aplicada = Efectividad × Tope: | F8: =$F$6*$F$7
B9: La efectividad se mide contra un denominador fijo: las 14 obligaciones del Art. 37 Bis, menos las excluidas por «No aplica». Una obligación sin registrar computa 0%, y una registrada sin numeral del Manual o sin evidencia de aplicación efectiva también (Art. 10 Septies 1, fr. III). Registrar menos no mejora el resultado.
B11: 1 · RIESGO RESIDUAL DE LA ENTIDAD
B12: # | C12: Ámbito evaluado | D12: Riesgo inh. | E12: Reducción | F12: Riesgo resid. | G12: Nivel | H12: Tratamiento
C13: ENTIDAD · resultado ponderado de los 4 elementos | D13: ='A3 INHERENTE'!E12 | E13: =$F$8 | F13: =D13*(1-E13) | G13: =IF(D13=0,"SIN EVALUAR",IFERROR(INDEX(PARAMETROS!$E$15:$E$19,MATCH(F13,PARAMETROS!$B$15:$B$19,1)),"")) | H13: =IF(G13="","",IFERROR(IF(MATCH(G13,PARAMETROS!$E$15:$E$19,0)>MATCH(PARAMETROS!$C$25,PARAMETROS!$E$15:$E$19,0),"Plan de acción / mitigar","Aceptable / monitorear"),"Declara el nivel de tolerancia en PARÁMETROS C25"))
B15: 2 · RIESGO RESIDUAL POR ELEMENTO (Art. 10 Septies 1, fr. I)
B16: # | C16: Ámbito evaluado | D16: Riesgo inh. | E16: Reducción | F16: Riesgo resid. | G16: Nivel | H16: Tratamiento
B17: 1 | C17: 1. Actos u operaciones | D17: ='A3 INHERENTE'!E7 | E17: =$F$8 | F17: =D17*(1-E17) | G17: =IF(D17=0,"SIN EVALUAR",IFERROR(INDEX(PARAMETROS!$E$15:$E$19,MATCH(F17,PARAMETROS!$B$15:$B$19,1)),"")) | H17: =IF(G17="","",IFERROR(IF(MATCH(G17,PARAMETROS!$E$15:$E$19,0)>MATCH(PARAMETROS!$C$25,PARAMETROS!$E$15:$E$19,0),"Plan de acción / mitigar","Aceptable / monitorear"),"Declara el nivel de tolerancia en PARÁMETROS C25"))
B18: 2 | C18: 2. Clientes / Usuarios | D18: ='A3 INHERENTE'!E8 | E18: =$F$8 | F18: =D18*(1-E18) | G18: =IF(D18=0,"SIN EVALUAR",IFERROR(INDEX(PARAMETROS!$E$15:$E$19,MATCH(F18,PARAMETROS!$B$15:$B$19,1)),"")) | H18: =IF(G18="","",IFERROR(IF(MATCH(G18,PARAMETROS!$E$15:$E$19,0)>MATCH(PARAMETROS!$C$25,PARAMETROS!$E$15:$E$19,0),"Plan de acción / mitigar","Aceptable / monitorear"),"Declara el nivel de tolerancia en PARÁMETROS C25"))
B19: 3 | C19: 3. Países y áreas geográficas | D19: ='A3 INHERENTE'!E9 | E19: =$F$8 | F19: =D19*(1-E19) | G19: =IF(D19=0,"SIN EVALUAR",IFERROR(INDEX(PARAMETROS!$E$15:$E$19,MATCH(F19,PARAMETROS!$B$15:$B$19,1)),"")) | H19: =IF(G19="","",IFERROR(IF(MATCH(G19,PARAMETROS!$E$15:$E$19,0)>MATCH(PARAMETROS!$C$25,PARAMETROS!$E$15:$E$19,0),"Plan de acción / mitigar","Aceptable / monitorear"),"Declara el nivel de tolerancia en PARÁMETROS C25"))
B20: 4 | C20: 4. Transacciones y canales | D20: ='A3 INHERENTE'!E10 | E20: =$F$8 | F20: =D20*(1-E20) | G20: =IF(D20=0,"SIN EVALUAR",IFERROR(INDEX(PARAMETROS!$E$15:$E$19,MATCH(F20,PARAMETROS!$B$15:$B$19,1)),"")) | H20: =IF(G20="","",IFERROR(IF(MATCH(G20,PARAMETROS!$E$15:$E$19,0)>MATCH(PARAMETROS!$C$25,PARAMETROS!$E$15:$E$19,0),"Plan de acción / mitigar","Aceptable / monitorear"),"Declara el nivel de tolerancia en PARÁMETROS C25"))
B22: 3 · RIESGO RESIDUAL POR INDICADOR (Art. 10 Septies 1, fr. II)
B23: # | C23: Ámbito evaluado | D23: Riesgo inh. | E23: Reducción | F23: Riesgo resid. | G23: Nivel | H23: Tratamiento | I23: Orden
B24: ='A3 INHERENTE'!B16 | C24: ='A3 INHERENTE'!C16 | D24: ='A3 INHERENTE'!F16 | E24: =IF($D24="N/A","",$F$8) | F24: =IF($D24="N/A","N/A",D24*(1-E24)) | G24: =IF($D24="N/A","No aplica",IF($D24=0,"SIN EVALUAR",IFERROR(INDEX(PARAMETROS!$E$15:$E$19,MATCH(F24,PARAMETROS!$B$15:$B$19,1)),""))) | H24: =IF(OR($D24="N/A",$G24=""),"",IFERROR(IF(MATCH($G24,PARAMETROS!$E$15:$E$19,0)>MATCH(PARAMETROS!$C$25,PARAMETROS!$E$15:$E$19,0),"Plan de acción / mitigar","Aceptable / monitorear"),"Declara el nivel de tolerancia en PARÁMETROS C25")) | I24: =IF($D24="N/A",-1,F24+(49-ROW())/100000)
B25: ='A3 INHERENTE'!B17 | C25: ='A3 INHERENTE'!C17 | D25: ='A3 INHERENTE'!F17 | E25: =IF($D25="N/A","",$F$8) | F25: =IF($D25="N/A","N/A",D25*(1-E25)) | G25: =IF($D25="N/A","No aplica",IF($D25=0,"SIN EVALUAR",IFERROR(INDEX(PARAMETROS!$E$15:$E$19,MATCH(F25,PARAMETROS!$B$15:$B$19,1)),""))) | H25: =IF(OR($D25="N/A",$G25=""),"",IFERROR(IF(MATCH($G25,PARAMETROS!$E$15:$E$19,0)>MATCH(PARAMETROS!$C$25,PARAMETROS!$E$15:$E$19,0),"Plan de acción / mitigar","Aceptable / monitorear"),"Declara el nivel de tolerancia en PARÁMETROS C25")) | I25: =IF($D25="N/A",-1,F25+(49-ROW())/100000)
B26: ='A3 INHERENTE'!B18 | C26: ='A3 INHERENTE'!C18 | D26: ='A3 INHERENTE'!F18 | E26: =IF($D26="N/A","",$F$8) | F26: =IF($D26="N/A","N/A",D26*(1-E26)) | G26: =IF($D26="N/A","No aplica",IF($D26=0,"SIN EVALUAR",IFERROR(INDEX(PARAMETROS!$E$15:$E$19,MATCH(F26,PARAMETROS!$B$15:$B$19,1)),""))) | H26: =IF(OR($D26="N/A",$G26=""),"",IFERROR(IF(MATCH($G26,PARAMETROS!$E$15:$E$19,0)>MATCH(PARAMETROS!$C$25,PARAMETROS!$E$15:$E$19,0),"Plan de acción / mitigar","Aceptable / monitorear"),"Declara el nivel de tolerancia en PARÁMETROS C25")) | I26: =IF($D26="N/A",-1,F26+(49-ROW())/100000)
B27: ='A3 INHERENTE'!B19 | C27: ='A3 INHERENTE'!C19 | D27: ='A3 INHERENTE'!F19 | E27: =IF($D27="N/A","",$F$8) | F27: =IF($D27="N/A","N/A",D27*(1-E27)) | G27: =IF($D27="N/A","No aplica",IF($D27=0,"SIN EVALUAR",IFERROR(INDEX(PARAMETROS!$E$15:$E$19,MATCH(F27,PARAMETROS!$B$15:$B$19,1)),""))) | H27: =IF(OR($D27="N/A",$G27=""),"",IFERROR(IF(MATCH($G27,PARAMETROS!$E$15:$E$19,0)>MATCH(PARAMETROS!$C$25,PARAMETROS!$E$15:$E$19,0),"Plan de acción / mitigar","Aceptable / monitorear"),"Declara el nivel de tolerancia en PARÁMETROS C25")) | I27: =IF($D27="N/A",-1,F27+(49-ROW())/100000)
B28: ='A3 INHERENTE'!B20 | C28: ='A3 INHERENTE'!C20 | D28: ='A3 INHERENTE'!F20 | E28: =IF($D28="N/A","",$F$8) | F28: =IF($D28="N/A","N/A",D28*(1-E28)) | G28: =IF($D28="N/A","No aplica",IF($D28=0,"SIN EVALUAR",IFERROR(INDEX(PARAMETROS!$E$15:$E$19,MATCH(F28,PARAMETROS!$B$15:$B$19,1)),""))) | H28: =IF(OR($D28="N/A",$G28=""),"",IFERROR(IF(MATCH($G28,PARAMETROS!$E$15:$E$19,0)>MATCH(PARAMETROS!$C$25,PARAMETROS!$E$15:$E$19,0),"Plan de acción / mitigar","Aceptable / monitorear"),"Declara el nivel de tolerancia en PARÁMETROS C25")) | I28: =IF($D28="N/A",-1,F28+(49-ROW())/100000)
B29: ='A3 INHERENTE'!B21 | C29: ='A3 INHERENTE'!C21 | D29: ='A3 INHERENTE'!F21 | E29: =IF($D29="N/A","",$F$8) | F29: =IF($D29="N/A","N/A",D29*(1-E29)) | G29: =IF($D29="N/A","No aplica",IF($D29=0,"SIN EVALUAR",IFERROR(INDEX(PARAMETROS!$E$15:$E$19,MATCH(F29,PARAMETROS!$B$15:$B$19,1)),""))) | H29: =IF(OR($D29="N/A",$G29=""),"",IFERROR(IF(MATCH($G29,PARAMETROS!$E$15:$E$19,0)>MATCH(PARAMETROS!$C$25,PARAMETROS!$E$15:$E$19,0),"Plan de acción / mitigar","Aceptable / monitorear"),"Declara el nivel de tolerancia en PARÁMETROS C25")) | I29: =IF($D29="N/A",-1,F29+(49-ROW())/100000)
B30: ='A3 INHERENTE'!B22 | C30: ='A3 INHERENTE'!C22 | D30: ='A3 INHERENTE'!F22 | E30: =IF($D30="N/A","",$F$8) | F30: =IF($D30="N/A","N/A",D30*(1-E30)) | G30: =IF($D30="N/A","No aplica",IF($D30=0,"SIN EVALUAR",IFERROR(INDEX(PARAMETROS!$E$15:$E$19,MATCH(F30,PARAMETROS!$B$15:$B$19,1)),""))) | H30: =IF(OR($D30="N/A",$G30=""),"",IFERROR(IF(MATCH($G30,PARAMETROS!$E$15:$E$19,0)>MATCH(PARAMETROS!$C$25,PARAMETROS!$E$15:$E$19,0),"Plan de acción / mitigar","Aceptable / monitorear"),"Declara el nivel de tolerancia en PARÁMETROS C25")) | I30: =IF($D30="N/A",-1,F30+(49-ROW())/100000)
B31: ='A3 INHERENTE'!B23 | C31: ='A3 INHERENTE'!C23 | D31: ='A3 INHERENTE'!F23 | E31: =IF($D31="N/A","",$F$8) | F31: =IF($D31="N/A","N/A",D31*(1-E31)) | G31: =IF($D31="N/A","No aplica",IF($D31=0,"SIN EVALUAR",IFERROR(INDEX(PARAMETROS!$E$15:$E$19,MATCH(F31,PARAMETROS!$B$15:$B$19,1)),""))) | H31: =IF(OR($D31="N/A",$G31=""),"",IFERROR(IF(MATCH($G31,PARAMETROS!$E$15:$E$19,0)>MATCH(PARAMETROS!$C$25,PARAMETROS!$E$15:$E$19,0),"Plan de acción / mitigar","Aceptable / monitorear"),"Declara el nivel de tolerancia en PARÁMETROS C25")) | I31: =IF($D31="N/A",-1,F31+(49-ROW())/100000)
B32: ='A3 INHERENTE'!B24 | C32: ='A3 INHERENTE'!C24 | D32: ='A3 INHERENTE'!F24 | E32: =IF($D32="N/A","",$F$8) | F32: =IF($D32="N/A","N/A",D32*(1-E32)) | G32: =IF($D32="N/A","No aplica",IF($D32=0,"SIN EVALUAR",IFERROR(INDEX(PARAMETROS!$E$15:$E$19,MATCH(F32,PARAMETROS!$B$15:$B$19,1)),""))) | H32: =IF(OR($D32="N/A",$G32=""),"",IFERROR(IF(MATCH($G32,PARAMETROS!$E$15:$E$19,0)>MATCH(PARAMETROS!$C$25,PARAMETROS!$E$15:$E$19,0),"Plan de acción / mitigar","Aceptable / monitorear"),"Declara el nivel de tolerancia en PARÁMETROS C25")) | I32: =IF($D32="N/A",-1,F32+(49-ROW())/100000)
B33: ='A3 INHERENTE'!B25 | C33: ='A3 INHERENTE'!C25 | D33: ='A3 INHERENTE'!F25 | E33: =IF($D33="N/A","",$F$8) | F33: =IF($D33="N/A","N/A",D33*(1-E33)) | G33: =IF($D33="N/A","No aplica",IF($D33=0,"SIN EVALUAR",IFERROR(INDEX(PARAMETROS!$E$15:$E$19,MATCH(F33,PARAMETROS!$B$15:$B$19,1)),""))) | H33: =IF(OR($D33="N/A",$G33=""),"",IFERROR(IF(MATCH($G33,PARAMETROS!$E$15:$E$19,0)>MATCH(PARAMETROS!$C$25,PARAMETROS!$E$15:$E$19,0),"Plan de acción / mitigar","Aceptable / monitorear"),"Declara el nivel de tolerancia en PARÁMETROS C25")) | I33: =IF($D33="N/A",-1,F33+(49-ROW())/100000)
B34: ='A3 INHERENTE'!B26 | C34: ='A3 INHERENTE'!C26 | D34: ='A3 INHERENTE'!F26 | E34: =IF($D34="N/A","",$F$8) | F34: =IF($D34="N/A","N/A",D34*(1-E34)) | G34: =IF($D34="N/A","No aplica",IF($D34=0,"SIN EVALUAR",IFERROR(INDEX(PARAMETROS!$E$15:$E$19,MATCH(F34,PARAMETROS!$B$15:$B$19,1)),""))) | H34: =IF(OR($D34="N/A",$G34=""),"",IFERROR(IF(MATCH($G34,PARAMETROS!$E$15:$E$19,0)>MATCH(PARAMETROS!$C$25,PARAMETROS!$E$15:$E$19,0),"Plan de acción / mitigar","Aceptable / monitorear"),"Declara el nivel de tolerancia en PARÁMETROS C25")) | I34: =IF($D34="N/A",-1,F34+(49-ROW())/100000)
B35: ='A3 INHERENTE'!B27 | C35: ='A3 INHERENTE'!C27 | D35: ='A3 INHERENTE'!F27 | E35: =IF($D35="N/A","",$F$8) | F35: =IF($D35="N/A","N/A",D35*(1-E35)) | G35: =IF($D35="N/A","No aplica",IF($D35=0,"SIN EVALUAR",IFERROR(INDEX(PARAMETROS!$E$15:$E$19,MATCH(F35,PARAMETROS!$B$15:$B$19,1)),""))) | H35: =IF(OR($D35="N/A",$G35=""),"",IFERROR(IF(MATCH($G35,PARAMETROS!$E$15:$E$19,0)>MATCH(PARAMETROS!$C$25,PARAMETROS!$E$15:$E$19,0),"Plan de acción / mitigar","Aceptable / monitorear"),"Declara el nivel de tolerancia en PARÁMETROS C25")) | I35: =IF($D35="N/A",-1,F35+(49-ROW())/100000)
... B48: ='A3 INHERENTE'!B40 | C48: ='A3 INHERENTE'!C40 | D48: ='A3 INHERENTE'!F40 | E48: =IF($D48="N/A","",$F$8) | F48: =IF($D48="N/A","N/A",D48*(1-E48)) | G48: =IF($D48="N/A","No aplica",IF($D48=0,"SIN EVALUAR",IFERROR(INDEX(PARAMETROS!$E$15:$E$19,MATCH(F48,PARAMETROS!$B$15:$B$19,1)),""))) | H48: =IF(OR($D48="N/A",$G48=""),"",IFERROR(IF(MATCH($G48,PARAMETROS!$E$15:$E$19,0)>MATCH(PARAMETROS!$C$25,PARAMETROS!$E$15:$E$19,0),"Plan de acción / mitigar","Aceptable / monitorear"),"Declara el nivel de tolerancia en PARÁMETROS C25")) | I48: =IF($D48="N/A",-1,F48+(49-ROW())/100000)
B50: La columna «Orden» solo sirve para ordenar el top 5 del tablero sin empates. No es un dato de la metodología.
B51: Los tres niveles usan la misma reducción porque los mitigantes se evaluaron a nivel de la entidad. Si en el futuro se documenta la efectividad por elemento o por indicador, basta sustituir la referencia de la columna «Reducción» en el bloque correspondiente.

Sheet A6 TABLERO
B2: A6 · TABLERO — Resumen ejecutivo
B3: Paso 8 de 10 · Se calcula solo · Sigue: A8 TOLERANCIA
B4: Actividad Vulnerable: | C4: =INICIO!C18
B5: Entidad: | C5: =IF(INICIO!$C$24="","(captura la razón social en INICIO)",INICIO!$C$24)
B6: Fecha de evaluación: | C6: =IF(INICIO!$C$27="","(captura la fecha en INICIO)",INICIO!$C$27)
B8: RIESGO INHERENTE DE LA ENTIDAD | E8: RIESGO RESIDUAL DE LA ENTIDAD
B9: ='A3 INHERENTE'!F12 | E9: ='A5 RESIDUAL'!$G$13
B13: DETALLE POR ELEMENTO
B14: Elemento | C14: Inherente | D14: Residual | E14: Tratamiento
B15: 1. Actos u operaciones | C15: ='A3 INHERENTE'!F7 | D15: ='A5 RESIDUAL'!G17 | E15: ='A5 RESIDUAL'!H17
B16: 2. Clientes / Usuarios | C16: ='A3 INHERENTE'!F8 | D16: ='A5 RESIDUAL'!G18 | E16: ='A5 RESIDUAL'!H18
B17: 3. Países y áreas geográficas | C17: ='A3 INHERENTE'!F9 | D17: ='A5 RESIDUAL'!G19 | E17: ='A5 RESIDUAL'!H19
B18: 4. Transacciones y canales | C18: ='A3 INHERENTE'!F10 | D18: ='A5 RESIDUAL'!G20 | E18: ='A5 RESIDUAL'!H20
B20: Vigencia: revisar y actualizar al menos cada 12 meses o al actualizarse la ENR (Art. 10 Septies 3). Conservar 10 años.
B22: CONSECUENCIAS DEL RESULTADO
B23: Régimen de auditoría (Cap. XIV RCG) | C23: =IF(OR('A5 RESIDUAL'!$G$13="ALTO",'A5 RESIDUAL'!$G$13="MEDIO ALTO"),("Riesgo alto: el dictamen debe emitirlo una persona auditora externa independiente con certificación vigente de la UIF (Art. 45, inciso b, con el Art. 34 Bis). CRITERIO: los Arts. 44 y 45 sólo emplean tres términos, bajo, medio y alto. La banda MEDIO "&"ALTO es de este modelo, no de la norma, y aquí se reporta como alto. Es criterio conservador y debe quedar escrito en tu metodología."),("Riesgo bajo o medio: el dictamen puede emitirlo tu área de auditoría interna o de control interno (Art. 44), integrada por personal independiente de la Representante Encargada de Cumplimiento. Y ojo: el Art. 45 permite optar por auditor externo aunqu"&"e tu riesgo sea bajo o medio, cuando así lo elija quien realiza la Actividad Vulnerable."))
B24: Medidas simplificadas (Art. 15 del Reglamento + Art. 17 de las Reglas) | C24: =IF('A5 RESIDUAL'!$G$13="BAJO",("Tu entidad cumple la condición del Art. 15 del Reglamento: bajo riesgo conforme a la evaluación del Art. 18 fr. VII de la Ley. Pero ésa es sólo UNA de las dos condiciones. El Art. 17 de las Reglas exige además que el Cliente esté clasificado como de "&"bajo Riesgo conforme al Capítulo III Bis. Las dos deben cumplirse: ver hoja B CLIENTE."),"Tu nivel no cumple la condición del Art. 15 del Reglamento, de modo que no proceden las medidas simplificadas con ningún Cliente. El expediente de cada Cliente se define por su Grado de Riesgo en la hoja B CLIENTE (Arts. 12, 17 y 17 Bis de las Reglas).")
B25: Tolerancia (PARÁMETROS, celda C25) | C25: =IFERROR(IF(MATCH('A5 RESIDUAL'!$G$13,PARAMETROS!$E$15:$E$19,0)>MATCH(PARAMETROS!$C$25,PARAMETROS!$E$15:$E$19,0),"FUERA de la tolerancia declarada. Se requiere plan de acción con responsable y fecha (ver hoja A8).","DENTRO de la tolerancia declarada. Mantener monitoreo y evidencia."),"Falta declarar el nivel de tolerancia en PARÁMETROS, celda C25.")
B26: Vigencia (Art. 10 Septies 2 y 10 Septies 3) | C26: =IF(INICIO!$C$27="","Captura la fecha de la evaluación en INICIO para calcular la fecha límite de revisión.","Revisión obligatoria a más tardar en "&CHOOSE(MONTH(EDATE(INICIO!$C$27,12)),"enero","febrero","marzo","abril","mayo","junio","julio","agosto","septiembre","octubre","noviembre","diciembre")&" de "&YEAR(EDATE(INICIO!$C$27,12))&". La metodología debe constar por escrito y conservarse 10 años.")
B28: LOS 5 INDICADORES CON MAYOR RIESGO RESIDUAL
B29: Indicador | C29: Riesgo resid. | D29: Nivel
B30: =IFERROR("#"&INDEX('A5 RESIDUAL'!$B$24:$B$48,MATCH(LARGE('A5 RESIDUAL'!$I$24:$I$48,1),'A5 RESIDUAL'!$I$24:$I$48,0))&" · "&INDEX('A5 RESIDUAL'!$C$24:$C$48,MATCH(LARGE('A5 RESIDUAL'!$I$24:$I$48,1),'A5 RESIDUAL'!$I$24:$I$48,0)),"") | C30: =IFERROR(INDEX('A5 RESIDUAL'!$F$24:$F$48,MATCH(LARGE('A5 RESIDUAL'!$I$24:$I$48,1),'A5 RESIDUAL'!$I$24:$I$48,0)),"") | D30: =IFERROR(INDEX('A5 RESIDUAL'!$G$24:$G$48,MATCH(LARGE('A5 RESIDUAL'!$I$24:$I$48,1),'A5 RESIDUAL'!$I$24:$I$48,0)),"")
B31: =IFERROR("#"&INDEX('A5 RESIDUAL'!$B$24:$B$48,MATCH(LARGE('A5 RESIDUAL'!$I$24:$I$48,2),'A5 RESIDUAL'!$I$24:$I$48,0))&" · "&INDEX('A5 RESIDUAL'!$C$24:$C$48,MATCH(LARGE('A5 RESIDUAL'!$I$24:$I$48,2),'A5 RESIDUAL'!$I$24:$I$48,0)),"") | C31: =IFERROR(INDEX('A5 RESIDUAL'!$F$24:$F$48,MATCH(LARGE('A5 RESIDUAL'!$I$24:$I$48,2),'A5 RESIDUAL'!$I$24:$I$48,0)),"") | D31: =IFERROR(INDEX('A5 RESIDUAL'!$G$24:$G$48,MATCH(LARGE('A5 RESIDUAL'!$I$24:$I$48,2),'A5 RESIDUAL'!$I$24:$I$48,0)),"")
B32: =IFERROR("#"&INDEX('A5 RESIDUAL'!$B$24:$B$48,MATCH(LARGE('A5 RESIDUAL'!$I$24:$I$48,3),'A5 RESIDUAL'!$I$24:$I$48,0))&" · "&INDEX('A5 RESIDUAL'!$C$24:$C$48,MATCH(LARGE('A5 RESIDUAL'!$I$24:$I$48,3),'A5 RESIDUAL'!$I$24:$I$48,0)),"") | C32: =IFERROR(INDEX('A5 RESIDUAL'!$F$24:$F$48,MATCH(LARGE('A5 RESIDUAL'!$I$24:$I$48,3),'A5 RESIDUAL'!$I$24:$I$48,0)),"") | D32: =IFERROR(INDEX('A5 RESIDUAL'!$G$24:$G$48,MATCH(LARGE('A5 RESIDUAL'!$I$24:$I$48,3),'A5 RESIDUAL'!$I$24:$I$48,0)),"")
B33: =IFERROR("#"&INDEX('A5 RESIDUAL'!$B$24:$B$48,MATCH(LARGE('A5 RESIDUAL'!$I$24:$I$48,4),'A5 RESIDUAL'!$I$24:$I$48,0))&" · "&INDEX('A5 RESIDUAL'!$C$24:$C$48,MATCH(LARGE('A5 RESIDUAL'!$I$24:$I$48,4),'A5 RESIDUAL'!$I$24:$I$48,0)),"") | C33: =IFERROR(INDEX('A5 RESIDUAL'!$F$24:$F$48,MATCH(LARGE('A5 RESIDUAL'!$I$24:$I$48,4),'A5 RESIDUAL'!$I$24:$I$48,0)),"") | D33: =IFERROR(INDEX('A5 RESIDUAL'!$G$24:$G$48,MATCH(LARGE('A5 RESIDUAL'!$I$24:$I$48,4),'A5 RESIDUAL'!$I$24:$I$48,0)),"")
B34: =IFERROR("#"&INDEX('A5 RESIDUAL'!$B$24:$B$48,MATCH(LARGE('A5 RESIDUAL'!$I$24:$I$48,5),'A5 RESIDUAL'!$I$24:$I$48,0))&" · "&INDEX('A5 RESIDUAL'!$C$24:$C$48,MATCH(LARGE('A5 RESIDUAL'!$I$24:$I$48,5),'A5 RESIDUAL'!$I$24:$I$48,0)),"") | C34: =IFERROR(INDEX('A5 RESIDUAL'!$F$24:$F$48,MATCH(LARGE('A5 RESIDUAL'!$I$24:$I$48,5),'A5 RESIDUAL'!$I$24:$I$48,0)),"") | D34: =IFERROR(INDEX('A5 RESIDUAL'!$G$24:$G$48,MATCH(LARGE('A5 RESIDUAL'!$I$24:$I$48,5),'A5 RESIDUAL'!$I$24:$I$48,0)),"")
B35: Estos son los indicadores por los que empieza el plan de acción de la hoja A8: son los que más aportan al resultado y los primeros que la autoridad va a preguntar.
B37: COBERTURA DEL CATÁLOGO DE CONTROLES MÍNIMOS (Art. 37 Bis)
B38: Efectividad de los mitigantes (obligaciones cubiertas): | C38: ='A4 CONTROLES MINIMOS'!$F$28
B39: Reducción aplicada al riesgo inherente: | C39: ='A4 CONTROLES MINIMOS'!$F$30
B40: Obligaciones en «No cumple»: | C40: ='A4 CONTROLES MINIMOS'!$F$33
B41: Obligaciones sin calificar: | C41: ='A4 CONTROLES MINIMOS'!$F$36
B42: =IF('A4 CONTROLES MINIMOS'!$F$33>0,"Hay obligaciones del Manual en «No cumple». Antes de discutir el nivel de riesgo, atiende eso: el Art. 48 fr. IV lo define como incumplimiento que puede actualizar una sanción.",IF('A4 CONTROLES MINIMOS'!$F$36>0,"Faltan obligaciones por calificar en el catálogo: mientras tanto computan 0% y el residual sale más alto de lo real.","Catálogo completo y sin incumplimientos declarados."))

Sheet A7 NUEVOS PRODUCTOS
B2: A7 · EVALUACIÓN PREVIA DE NUEVOS PRODUCTOS, SERVICIOS Y CANALES
B3: Art. 10 Septies, tercer párrafo: antes de lanzar un nuevo medio, canal, modalidad, producto, servicio o tipo de Cliente, evalúa el riesgo. Una ficha por lanzamiento. Esta hoja no altera el resultado de A1; es evidencia y decisión previa.
B4: Fuera de secuencia: se llena ANTES de cada lanzamiento (Art. 10 Septies, 3er párrafo)
B6: # | C6: Nuevo producto, servicio, canal o tipo de Cliente | D6: Fecha prevista de lanzamiento | E6: Riesgo elem. 1 | F6: Riesgo elem. 2 | G6: Riesgo elem. 3 | H6: Riesgo elem. 4 | I6: Riesgo previo | J6: Nivel | K6: Controles previos comprometidos | L6: Decisión
B7: 1 | C7: Cobro con transferencia SPEI desde cuenta de tercero no declarado en el expediente, solicitado por dos desarrolladoras para agilizar el enganche. | D7: 46266 | E7: Medio | F7: Alto | G7: Bajo | H7: Alto | I7: =IFERROR(ROUND((IF(E7="Alto",5,IF(E7="Medio",3,IF(E7="Bajo",1,"")))+IF(F7="Alto",5,IF(F7="Medio",3,IF(F7="Bajo",1,"")))+IF(G7="Alto",5,IF(G7="Medio",3,IF(G7="Bajo",1,"")))+IF(H7="Alto",5,IF(H7="Medio",3,IF(H7="Bajo",1,""))))/4,2),"") | J7: =IF(I7="","",IF(I7>=4,"ALTO",IF(I7>=2.34,"MEDIO","BAJO"))) | K7: Prohibir el pago de tercero salvo parentesco acreditado; alta obligatoria de la cuenta ordenante en el expediente antes de recibir el recurso; alerta automática por cuenta no declarada. | L7: Se lanza con controles adicionales
B8: 2 | C8: Esquema de preventa con apartado de 50,000 pesos reembolsable, dirigido a compradores que aún no acreditan la fuente de los recursos. | D8: 46310 | E8: Medio | F8: Medio | G8: Bajo | H8: Medio | I8: =IFERROR(ROUND((IF(E8="Alto",5,IF(E8="Medio",3,IF(E8="Bajo",1,"")))+IF(F8="Alto",5,IF(F8="Medio",3,IF(F8="Bajo",1,"")))+IF(G8="Alto",5,IF(G8="Medio",3,IF(G8="Bajo",1,"")))+IF(H8="Alto",5,IF(H8="Medio",3,IF(H8="Bajo",1,""))))/4,2),"") | J8: =IF(I8="","",IF(I8>=4,"ALTO",IF(I8>=2.34,"MEDIO","BAJO"))) | K8: Identificación completa desde el apartado y no hasta la escrituración; el reembolso se paga sólo a la misma cuenta de origen; acumulación del apartado al precio para efectos del umbral. | L8: Se lanza con controles adicionales
B9: 3 | C9: Recepción de criptoactivos como parte del pago, propuesta por un intermediario externo. | D9: 46327 | E9: Alto | F9: Alto | G9: Alto | H9: Alto | I9: =IFERROR(ROUND((IF(E9="Alto",5,IF(E9="Medio",3,IF(E9="Bajo",1,"")))+IF(F9="Alto",5,IF(F9="Medio",3,IF(F9="Bajo",1,"")))+IF(G9="Alto",5,IF(G9="Medio",3,IF(G9="Bajo",1,"")))+IF(H9="Alto",5,IF(H9="Medio",3,IF(H9="Bajo",1,""))))/4,2),"") | J9: =IF(I9="","",IF(I9>=4,"ALTO",IF(I9>=2.34,"MEDIO","BAJO"))) | K9: No se identificó forma de acreditar el origen de los recursos ni de cumplir la fracción XVI del Art. 17 sin registrarse como sujeto obligado por esa actividad. | L9: No se lanza
B10: 4 | I10: =IFERROR(ROUND((IF(E10="Alto",5,IF(E10="Medio",3,IF(E10="Bajo",1,"")))+IF(F10="Alto",5,IF(F10="Medio",3,IF(F10="Bajo",1,"")))+IF(G10="Alto",5,IF(G10="Medio",3,IF(G10="Bajo",1,"")))+IF(H10="Alto",5,IF(H10="Medio",3,IF(H10="Bajo",1,""))))/4,2),"") | J10: =IF(I10="","",IF(I10>=4,"ALTO",IF(I10>=2.34,"MEDIO","BAJO")))
B11: 5 | I11: =IFERROR(ROUND((IF(E11="Alto",5,IF(E11="Medio",3,IF(E11="Bajo",1,"")))+IF(F11="Alto",5,IF(F11="Medio",3,IF(F11="Bajo",1,"")))+IF(G11="Alto",5,IF(G11="Medio",3,IF(G11="Bajo",1,"")))+IF(H11="Alto",5,IF(H11="Medio",3,IF(H11="Bajo",1,""))))/4,2),"") | J11: =IF(I11="","",IF(I11>=4,"ALTO",IF(I11>=2.34,"MEDIO","BAJO")))
B12: 6 | I12: =IFERROR(ROUND((IF(E12="Alto",5,IF(E12="Medio",3,IF(E12="Bajo",1,"")))+IF(F12="Alto",5,IF(F12="Medio",3,IF(F12="Bajo",1,"")))+IF(G12="Alto",5,IF(G12="Medio",3,IF(G12="Bajo",1,"")))+IF(H12="Alto",5,IF(H12="Medio",3,IF(H12="Bajo",1,""))))/4,2),"") | J12: =IF(I12="","",IF(I12>=4,"ALTO",IF(I12>=2.34,"MEDIO","BAJO")))
B13: 7 | I13: =IFERROR(ROUND((IF(E13="Alto",5,IF(E13="Medio",3,IF(E13="Bajo",1,"")))+IF(F13="Alto",5,IF(F13="Medio",3,IF(F13="Bajo",1,"")))+IF(G13="Alto",5,IF(G13="Medio",3,IF(G13="Bajo",1,"")))+IF(H13="Alto",5,IF(H13="Medio",3,IF(H13="Bajo",1,""))))/4,2),"") | J13: =IF(I13="","",IF(I13>=4,"ALTO",IF(I13>=2.34,"MEDIO","BAJO")))
B14: 8 | I14: =IFERROR(ROUND((IF(E14="Alto",5,IF(E14="Medio",3,IF(E14="Bajo",1,"")))+IF(F14="Alto",5,IF(F14="Medio",3,IF(F14="Bajo",1,"")))+IF(G14="Alto",5,IF(G14="Medio",3,IF(G14="Bajo",1,"")))+IF(H14="Alto",5,IF(H14="Medio",3,IF(H14="Bajo",1,""))))/4,2),"") | J14: =IF(I14="","",IF(I14>=4,"ALTO",IF(I14>=2.34,"MEDIO","BAJO")))
B15: 9 | I15: =IFERROR(ROUND((IF(E15="Alto",5,IF(E15="Medio",3,IF(E15="Bajo",1,"")))+IF(F15="Alto",5,IF(F15="Medio",3,IF(F15="Bajo",1,"")))+IF(G15="Alto",5,IF(G15="Medio",3,IF(G15="Bajo",1,"")))+IF(H15="Alto",5,IF(H15="Medio",3,IF(H15="Bajo",1,""))))/4,2),"") | J15: =IF(I15="","",IF(I15>=4,"ALTO",IF(I15>=2.34,"MEDIO","BAJO")))
B16: 10 | I16: =IFERROR(ROUND((IF(E16="Alto",5,IF(E16="Medio",3,IF(E16="Bajo",1,"")))+IF(F16="Alto",5,IF(F16="Medio",3,IF(F16="Bajo",1,"")))+IF(G16="Alto",5,IF(G16="Medio",3,IF(G16="Bajo",1,"")))+IF(H16="Alto",5,IF(H16="Medio",3,IF(H16="Bajo",1,""))))/4,2),"") | J16: =IF(I16="","",IF(I16>=4,"ALTO",IF(I16>=2.34,"MEDIO","BAJO")))
B17: 11 | I17: =IFERROR(ROUND((IF(E17="Alto",5,IF(E17="Medio",3,IF(E17="Bajo",1,"")))+IF(F17="Alto",5,IF(F17="Medio",3,IF(F17="Bajo",1,"")))+IF(G17="Alto",5,IF(G17="Medio",3,IF(G17="Bajo",1,"")))+IF(H17="Alto",5,IF(H17="Medio",3,IF(H17="Bajo",1,""))))/4,2),"") | J17: =IF(I17="","",IF(I17>=4,"ALTO",IF(I17>=2.34,"MEDIO","BAJO")))
B18: 12 | I18: =IFERROR(ROUND((IF(E18="Alto",5,IF(E18="Medio",3,IF(E18="Bajo",1,"")))+IF(F18="Alto",5,IF(F18="Medio",3,IF(F18="Bajo",1,"")))+IF(G18="Alto",5,IF(G18="Medio",3,IF(G18="Bajo",1,"")))+IF(H18="Alto",5,IF(H18="Medio",3,IF(H18="Bajo",1,""))))/4,2),"") | J18: =IF(I18="","",IF(I18>=4,"ALTO",IF(I18>=2.34,"MEDIO","BAJO")))
B21: La ficha debe llenarse ANTES del lanzamiento y conservarse 10 años. Si la decisión es «Se lanza» o «Se lanza con controles adicionales», el producto o canal debe incorporarse a la siguiente actualización de A1 y a la matriz de controles A4.

Sheet A8 TOLERANCIA
B2: A8 · TOLERANCIA AL RIESGO, VIGENCIA Y PLAN DE ACCIÓN
B3: Art. 10 Septies 2 y 10 Septies 3: periodo evaluado de al menos 12 meses, tolerancia declarada, modificación en un plazo no mayor a 12 meses indicando al menos el año y el mes, y revisión anual por escrito.
B4: Paso 9 de 10 · Viene de: A6 · Sigue: A9 CONSTANCIA Y FUENTES
B5: DECLARACIÓN DE TOLERANCIA Y PERIODO EVALUADO
B6: Nivel de tolerancia declarado (PARÁMETROS C25): | D6: =PARAMETROS!C25
B7: Periodo evaluado — inicio (INICIO C28): | D7: =IF(INICIO!$C$28="","",INICIO!$C$28)
B8: Periodo evaluado — fin (INICIO C29): | D8: =IF(INICIO!$C$29="","",INICIO!$C$29)
B9: Meses del periodo (ambos extremos incluidos): | D9: =IFERROR(DATEDIF($D$7,$D$8+1,"m"),"")
B10: ¿Cumple el mínimo de 12 meses (Art. 10 Septies 2)? | D10: =IF($D$9="","",IF($D$9>=12,"Sí","No: el periodo evaluado es menor a 12 meses"))
B11: Fecha de la evaluación (INICIO C27): | D11: =IF(INICIO!$C$27="","",INICIO!$C$27)
B12: Fecha límite de la próxima revisión: | D12: =IF(INICIO!$C$27="","",CHOOSE(MONTH(EDATE(INICIO!$C$27,12)),"enero","febrero","marzo","abril","mayo","junio","julio","agosto","septiembre","octubre","noviembre","diciembre")&" de "&YEAR(EDATE(INICIO!$C$27,12)))
B14: VEREDICTO: ¿EL RESULTADO ESTÁ DENTRO DE LA TOLERANCIA?
B15: Riesgo residual de la entidad: | D15: ='A5 RESIDUAL'!$G$13
B16: Tolerancia declarada: | D16: =PARAMETROS!$C$25
B17: Veredicto: | D17: =IF('A5 RESIDUAL'!$G$13="","",IFERROR(IF(MATCH('A5 RESIDUAL'!$G$13,PARAMETROS!$E$15:$E$19,0)>MATCH(PARAMETROS!$C$25,PARAMETROS!$E$15:$E$19,0),"FUERA DE TOLERANCIA","DENTRO DE TOLERANCIA"),"Falta declarar la tolerancia en PARÁMETROS C25"))
B18: Consecuencia: | D18: =IF($D$17="","",IF($D$17="FUERA DE TOLERANCIA","Obligatorio documentar plan de acción con responsable y fecha comprometida, y ejecutar la modificación en un plazo no mayor a 12 meses (Art. 10 Septies 2, fr. IV).",IF($D$17="DENTRO DE TOLERANCIA","Se conserva el esquema de control vigente, con monitoreo y evidencia. Igual debe revisarse al menos cada 12 meses.","Sin tolerancia declarada no hay veredicto posible: captúrala en PARÁMETROS, celda C25.")))
B20: PLAN DE ACCIÓN (obligatorio si el resultado queda fuera de tolerancia)
B21: # | C21: Hallazgo / riesgo fuera de tolerancia | E21: Acción comprometida | F21: Responsable | G21: Año y mes comprometidos | H21: Estatus | I21: Evidencia
B22: 1 | C22: El indicador 18, instrumento monetario, es el de mayor riesgo residual de toda la matriz (9.74, MEDIO): 56 de 112 operaciones del periodo tuvieron algún componente en efectivo. | E22: Bajar el umbral interno de aceptación de efectivo de 150,000 a 80,000 pesos por operación y desplazar el cobro a transferencia mediante acuerdo con las tres desarrolladoras. | F22: Representante Encargada de Cumplimiento | G22: marzo de 2027 | H22: En proceso | I22: Adenda al Manual numeral 7.1 y convenios firmados con las desarrolladoras.
B23: 2 | C23: La fracción IV del catálogo quedó en «Cumple parcialmente»: se declara la búsqueda de Personas Políticamente Expuestas pero no se conserva constancia de la consulta. | E23: Incorporar la impresión fechada de la consulta PEP al expediente de cada Cliente y correr la consulta retroactiva de los 86 Clientes del periodo. | F23: Área de expedientes | G23: enero de 2027 | H23: En proceso | I23: Constancia de consulta en expediente y reporte de la corrida retroactiva.
B24: 3 | C24: La fracción V quedó en «Cumple parcialmente»: las alertas del perfil transaccional se revisan pero sin bitácora de atención. Dos de las siete alertas del periodo siguen sin dictamen. | E24: Implantar bitácora de atención de alertas con responsable, fecha, dictamen y evidencia, y cerrar las dos alertas pendientes. | F24: Representante Encargada de Cumplimiento | G24: noviembre de 2026 | H24: En proceso | I24: Bitácora del sistema con dictamen firmado por alerta.
B25: 4 | C25: La fracción XII quedó en «Cumple parcialmente»: hay programa de auditoría aprobado pero falta designar y preparar al área que emitirá el dictamen. | E25: Preparar el área de auditoría y designar a quien emitirá el dictamen. Con riesgo bajo o medio puede practicarla el área de auditoría interna (Art. 44); con riesgo alto, o si así se elige, va persona auditora externa independiente (Art. 45). El primer periodo de revisión corre del 1 de enero al 31 de diciembre de 2028 (Transitorio Octavo) y el dictamen se entrega a más tardar el último día hábil de marzo de 2029 (Art. 50). | F25: Órgano de administración | G25: diciembre de 2026 | H25: No iniciada | I25: Programa anual de auditoría y acta de designación de quien emitirá el dictamen; el dictamen del ejercicio 2028 se entrega en marzo de 2029.
B26: 5 | C26: El indicador 13, Beneficiario Controlador, pesa 0.18 dentro del elemento 2 y el régimen cambia: a partir del 30 de noviembre de 2026 desaparece la constancia declarativa en persona moral y fideicomiso, y hay que identificarlo. | E26: Sustituir la constancia declarativa por identificación efectiva en los 31 expedientes de persona moral y adecuar el formato del expediente antes de la fecha de entrada en vigor. | F26: Área de expedientes | G26: noviembre de 2026 | H26: En proceso | I26: Expedientes con Beneficiario Controlador identificado y formato nuevo liberado.
B27: 6
B28: 7
B29: 8
B30: 9
B31: 10
B33: El Art. 10 Septies 2, último párrafo, pide indicar al menos el año y mes EN QUE SE OBTUVIERON LOS RESULTADOS de la implementación: ése ancla el plazo de doce meses. La fecha comprometida de la acción es buena práctica de esta matriz. Un plan sin fecha no acredita mitigación: acredita intención.

Sheet A9 CONSTANCIA Y FUENTES
B2: A9 · CONSTANCIA DE LA EVALUACIÓN, FUENTES Y CONSERVACIÓN
B3: Aquí se documenta lo que la matriz no calcula pero la autoridad sí exige: la ENR tomada en cuenta, la conciliación con tus mecanismos automatizados, los datos proyectados, la aprobación y las versiones.
B4: Pasos 2 y 10 · Secciones 1 y 2 se llenan ANTES de A1 · Secciones 3 a 7 al cierre
B5: ESTADO DE LLENADO DE LA CONSTANCIA
B6: Datos obligatorios que faltan: | D6: =COUNTBLANK(D10:D14)+COUNTBLANK(E19:E21)+COUNTBLANK(D22:D23)+COUNTBLANK(D28)+COUNTBLANK(D34:D39)+COUNTBLANK(F46)+COUNTBLANK(D54:D56)
D7: =IF($D$6=0,"Completa: la constancia puede imprimirse, firmarse y conservarse como evidencia de la evaluación.","Faltan "&$D$6&" dato(s) obligatorio(s): la evaluación todavía no está documentada por completo.")
B9: 1 · EVALUACIÓN NACIONAL DE RIESGOS (Art. 10 Septies, segundo párrafo)
B10: Versión o año de la ENR tomada en cuenta: | D10: ENR 2023 (versión pública)
B11: Fecha en que se consultó: | D11: 46188
B12: Amenazas, sectores y tipologías de la ENR que aplican a esta actividad: | D12: De la ENR aplican a esta actividad: el uso del sector inmobiliario para colocar efectivo de procedencia ilícita; la interposición de personas morales de reciente constitución y de terceros para ocultar al comprador real; el pago fraccionado por debajo de umbrales; y la subvaluación o sobrevaluación del inmueble respecto del valor de mercado.
B13: Cómo se reflejó la ENR en esta evaluación: | D13: Cada amenaza se ancló a un indicador. La colocación de efectivo elevó el perfil Alto del indicador 18 a 50% y sostiene su peso de 0.22. La interposición de personas morales sostiene el peso de 0.18 de los indicadores 6 y 13, y el 45% de perfil Alto del indicador 3. El fraccionamiento sostiene el 30% de perfil Alto del indicador 21. La subvaluación se atiende en el indicador 20 y en el control adicional de doble firma. Las cuatro quedaron además en el plan de acción de A8.
B14: ¿La ENR se actualizó después de esta evaluación? | D14: No
D15: =IF($D$14="Sí","⚠ La actualización de la Evaluación Nacional de Riesgos obliga a revisar esta evaluación (Art. 10 Septies 3), sin esperar a que se cumplan los doce meses.","")
B17: 2 · DATOS DE DOCE MESES Y CONCILIACIÓN CON EL MECANISMO AUTOMATIZADO (Art. 10 Septies 2, fr. I y II)
B18: Dato mínimo de doce meses | D18: Usado en esta evaluación | E18: Según el mecanismo automatizado | F18: Diferencia | G18: Estatus
B19: Número de Clientes o Usuarios | D19: =INICIO!$C$32 | E19: 86 | F19: =IF(OR($D19="",$E19=""),"",$E19-$D19) | G19: =IF($F19="","",IF($F19=0,"Conciliado","Diferencia"))
B20: Número de operaciones (actos u operaciones) | D20: =INICIO!$C$33 | E20: 112 | F20: =IF(OR($D20="",$E20=""),"",$E20-$D20) | G20: =IF($F20="","",IF($F20=0,"Conciliado","Diferencia"))
B21: Monto operado en el periodo | D21: =INICIO!$C$34 | E21: 428600000 | F21: =IF(OR($D21="",$E21=""),"",$E21-$D21) | G21: =IF($F21="","",IF($F21=0,"Conciliado","Diferencia"))
B22: Sistema o mecanismo automatizado del que se obtuvieron las cifras: | D22: Sistema de registro de operaciones y generación de Avisos «Ejemplo ERP Inmobiliario», módulo de cumplimiento y reportes, versión 4.2.
B23: Fecha de la conciliación: | D23: 46203
B24: Explicación de las diferencias (si las hay): | D24: Sin diferencias: las tres cifras de la evaluación coinciden con las del mecanismo automatizado al corte del 30 de junio de 2026. Se verificó además que las 14 operaciones que generaron Aviso en el periodo estén conciliadas contra los acuses del portal.
D25: =IF(SUMPRODUCT(--($F$19:$F$21<>""),--($F$19:$F$21<>0))>0,"Hay diferencias con el mecanismo automatizado. El Art. 10 Septies 2, fr. I exige que la evaluación no sea inconsistente con lo que registran tus mecanismos: corrige la cifra o explica la diferencia en el renglón anterior.","Sin diferencias: la evaluación es consistente con lo registrado en el mecanismo automatizado.")
B27: 3 · DATOS PROYECTADOS (Art. 10 Septies 2, párrafo siguiente a la fr. II)
B28: ¿La entidad operó durante todo el periodo evaluado? | D28: Sí
B29: Si no operó todo el periodo: base y metodología de la proyección | D29: No aplica: la entidad operó los doce meses completos del periodo evaluado, del 1 de julio de 2025 al 30 de junio de 2026, y la evaluación se hizo íntegramente con datos reales. No se utilizaron datos proyectados.
B30: Fecha en que deben sustituirse los proyectados por datos reales: | D30: =IF(INICIO!$C$27="","(captura la fecha de la evaluación en INICIO)",CHOOSE(MONTH(EDATE(INICIO!$C$27,12)),"enero","febrero","marzo","abril","mayo","junio","julio","agosto","septiembre","octubre","noviembre","diciembre")&" de "&YEAR(EDATE(INICIO!$C$27,12)))
D31: =IF($D$28="No","⚠ Estás trabajando con datos proyectados. Al cumplirse los doce meses debes actualizar la evaluación con datos reales (Art. 10 Septies 2).","")
B33: 4 · APROBACIÓN, CONSTANCIA Y CONSERVACIÓN (Art. 10 Septies 3, tercer párrafo)
B34: Elaboró la evaluación (nombre y cargo): | D34: María Ejemplo Ruiz — Representante Encargada de Cumplimiento
B35: Fecha de elaboración: | D35: 46204
B36: Aprobó la evaluación (nombre y cargo): | D36: Jorge Ejemplo Lara — Administrador Único
B37: Fecha de aprobación: | D37: 46218
B38: Medio en que consta la aprobación: | D38: Acta de sesión del órgano de administración
B39: Lugar de resguardo del expediente de la evaluación: | D39: Repositorio de cumplimiento en servidor propio con respaldo cifrado y control de accesos, más carpeta física en el domicilio fiscal. Responsable del resguardo: la Representante Encargada de Cumplimiento.
B40: Conservar al menos hasta: | D40: =IF($D$37="","(captura la fecha de aprobación)",CHOOSE(MONTH(EDATE($D$37,120)),"enero","febrero","marzo","abril","mayo","junio","julio","agosto","septiembre","octubre","noviembre","diciembre")&" de "&YEAR(EDATE($D$37,120)))
D41: =IF($D$37="","⚠ Sin fecha de aprobación no se acredita que la evaluación fue aprobada ni puede calcularse el plazo de conservación de diez años.","")
B43: 5 · LOS DOS PLAZOS DE DOCE MESES — NO SON EL MISMO
B44: Obligación | D44: Fundamento | E44: Vence | F44: Compromiso registrado (año y mes)
B45: Revisar y actualizar esta evaluación | D45: Art. 10 Septies 3, primer párrafo | E45: =IF(INICIO!$C$27="","",CHOOSE(MONTH(EDATE(INICIO!$C$27,12)),"enero","febrero","marzo","abril","mayo","junio","julio","agosto","septiembre","octubre","noviembre","diciembre")&" de "&YEAR(EDATE(INICIO!$C$27,12))) | F45: No aplica: el plazo lo fija la propia norma
B46: Modificar las políticas conforme a los resultados | D46: Art. 10 Septies 2, último párrafo | E46: =IF(INICIO!$C$27="","",CHOOSE(MONTH(EDATE(INICIO!$C$27,12)),"enero","febrero","marzo","abril","mayo","junio","julio","agosto","septiembre","octubre","noviembre","diciembre")&" de "&YEAR(EDATE(INICIO!$C$27,12))) | F46: julio de 2027
D47: =IF($F$46="","Falta registrar el año y el mes. Ojo: el Art. 10 Septies 2, último párrafo, pide el año y mes EN QUE SE OBTUVIERON LOS RESULTADOS de la implementación, que es el que ancla el plazo de doce meses.","Compromiso registrado. Los dos plazos corren en paralelo: revisar la evaluación y modificar las políticas son obligaciones distintas.")
B49: 6 · CONTROL DE VERSIONES DE LA EVALUACIÓN
B50: Versión | D50: Fecha | E50: Cambios principales | G50: Responsable
B51: v.1 | D51: 46218 | E51: Primera evaluación bajo el Cap. II Quáter de las Reglas de Carácter General. | G51: Encargado de Cumplimiento
B53: 7 · METODOLOGÍA INCORPORADA AL MANUAL (Art. 37, último párrafo)
B54: ¿El Manual incluye el diseño de esta metodología? | D54: Sí | E54: =IF(OR($D$54="No",$D$55="No"),"⚠ El Art. 37, último párrafo, exige que el Manual incluya el diseño de la metodología y los criterios de apertura, limitación o terminación congruentes con ella. Sin eso, la evaluación existe pero no está incorporada donde la norma la pide.","")
B55: ¿Incluye los criterios de apertura, limitación o terminación congruentes con ella? | D55: Sí
B56: Numeral del Manual donde consta: | D56: Manual, numeral 2.3
B57: Esta hoja es la constancia por escrito que exige el Art. 10 Septies 3: impresa y firmada, junto con A1 a A8, acredita que la evaluación existió, quién la aprobó y con qué fuentes se hizo. Conservarla diez años.

Sheet PRODUCTOS
B2: PRODUCTOS Y SERVICIOS · nivel de riesgo de lo que ofreces
B3: Un renglón por producto, servicio u operación que ofreces. Cada indicador se califica por columna y el nivel del producto es el promedio de sus indicadores.
B4: Alimenta el factor «Producto o servicio contratado» de la hoja B CLIENTE. Los seis indicadores son los del elemento 1 de la hoja A1: así el riesgo del producto se mide igual en los dos modelos.
B6: CATÁLOGO DE PRODUCTOS · califica cada indicador en Alto, Medio o Bajo
B7: Clave | C7: Producto, servicio u operación | D7: Valor del producto o servicio | E7: Liquidez o convertibilidad | F7: Anonimato que permite | G7: Facilidad de transferir u ocultar valor | H7: Exposición al financiamiento al terrorismo | I7: Uso de efectivo asociado | J7: Nivel | K7: Riesgo
B8: P-01 | C8: Compraventa de casa habitación de interés medio | D8: Medio | E8: Bajo | F8: Medio | G8: Medio | H8: Bajo | I8: Medio | J8: =(IF(D8="Alto",5,IF(D8="Medio",3,1))+IF(E8="Alto",5,IF(E8="Medio",3,1))+IF(F8="Alto",5,IF(F8="Medio",3,1))+IF(G8="Alto",5,IF(G8="Medio",3,1))+IF(H8="Alto",5,IF(H8="Medio",3,1))+IF(I8="Alto",5,IF(I8="Medio",3,1)))/6 | K8: =IF(J8>=3.67,"ALTO",IF(J8>=2.34,"MEDIO","BAJO"))
B9: P-02 | C9: Compraventa de casa habitación residencial | D9: Alto | E9: Bajo | F9: Medio | G9: Alto | H9: Bajo | I9: Alto | J9: =(IF(D9="Alto",5,IF(D9="Medio",3,1))+IF(E9="Alto",5,IF(E9="Medio",3,1))+IF(F9="Alto",5,IF(F9="Medio",3,1))+IF(G9="Alto",5,IF(G9="Medio",3,1))+IF(H9="Alto",5,IF(H9="Medio",3,1))+IF(I9="Alto",5,IF(I9="Medio",3,1)))/6 | K9: =IF(J9>=3.67,"ALTO",IF(J9>=2.34,"MEDIO","BAJO"))
B10: P-03 | C10: Compraventa de local comercial | D10: Alto | E10: Medio | F10: Medio | G10: Alto | H10: Medio | I10: Medio | J10: =(IF(D10="Alto",5,IF(D10="Medio",3,1))+IF(E10="Alto",5,IF(E10="Medio",3,1))+IF(F10="Alto",5,IF(F10="Medio",3,1))+IF(G10="Alto",5,IF(G10="Medio",3,1))+IF(H10="Alto",5,IF(H10="Medio",3,1))+IF(I10="Alto",5,IF(I10="Medio",3,1)))/6 | K10: =IF(J10>=3.67,"ALTO",IF(J10>=2.34,"MEDIO","BAJO"))
B11: P-04 | C11: Preventa con apartado reembolsable | D11: Medio | E11: Alto | F11: Alto | G11: Alto | H11: Bajo | I11: Alto | J11: =(IF(D11="Alto",5,IF(D11="Medio",3,1))+IF(E11="Alto",5,IF(E11="Medio",3,1))+IF(F11="Alto",5,IF(F11="Medio",3,1))+IF(G11="Alto",5,IF(G11="Medio",3,1))+IF(H11="Alto",5,IF(H11="Medio",3,1))+IF(I11="Alto",5,IF(I11="Medio",3,1)))/6 | K11: =IF(J11>=3.67,"ALTO",IF(J11>=2.34,"MEDIO","BAJO"))
B12: P-05 | C12: Renta con opción a compra | D12: Medio | E12: Medio | F12: Alto | G12: Medio | H12: Bajo | I12: Medio | J12: =(IF(D12="Alto",5,IF(D12="Medio",3,1))+IF(E12="Alto",5,IF(E12="Medio",3,1))+IF(F12="Alto",5,IF(F12="Medio",3,1))+IF(G12="Alto",5,IF(G12="Medio",3,1))+IF(H12="Alto",5,IF(H12="Medio",3,1))+IF(I12="Alto",5,IF(I12="Medio",3,1)))/6 | K12: =IF(J12>=3.67,"ALTO",IF(J12>=2.34,"MEDIO","BAJO"))
B13: P-06 | C13: Desarrollo por encargo (obra a la medida) | D13: Alto | E13: Bajo | F13: Alto | G13: Alto | H13: Medio | I13: Medio | J13: =(IF(D13="Alto",5,IF(D13="Medio",3,1))+IF(E13="Alto",5,IF(E13="Medio",3,1))+IF(F13="Alto",5,IF(F13="Medio",3,1))+IF(G13="Alto",5,IF(G13="Medio",3,1))+IF(H13="Alto",5,IF(H13="Medio",3,1))+IF(I13="Alto",5,IF(I13="Medio",3,1)))/6 | K13: =IF(J13>=3.67,"ALTO",IF(J13>=2.34,"MEDIO","BAJO"))
B15: Los seis indicadores corresponden al elemento 1 de la hoja A1 —actos u operaciones— y a los delitos de los artículos 139 Quáter y 400 Bis del Código Penal Federal. El anonimato no es un atributo del Cliente sino del producto: por eso se mide aquí y no en la hoja B CLIENTE.
C17: Fundamento de cada indicador
C18: Valor del producto o servicio | D18: RCG 10 Septies 1 fr. I a)
C19: Liquidez o convertibilidad | D19: RCG 10 Septies 1 fr. I a)
C20: Anonimato que permite | D20: CPF 400 Bis
C21: Facilidad de transferir u ocultar valor | D21: CPF 400 Bis
C22: Exposición al financiamiento al terrorismo | D22: CPF 139 Quáter
C23: Uso de efectivo asociado | D23: L 32

Sheet VARIABLES
B2: VARIABLES POR FACTOR · el catálogo del modelo de Cliente
B3: Una fila por variable. Es la política escrita del modelo: qué cuenta como riesgo alto, medio o bajo en cada factor. Va en el Manual (Art. 23 Bis).
B4: REGLA DEL CATÁLOGO · Un factor, un atributo. Cada variable de un factor mide lo mismo que las demás de ese factor, y nada de lo que mide otro factor. Si un atributo aparece en dos factores, se cuenta dos veces con peso. Todos los niveles son 1, 3 o 5.
B6: CATÁLOGO DE VARIABLES
B7: Clave | C7: Familia | D7: Factor | E7: Variable | F7: Nivel | G7: Fuente del dato | H7: Llave
B8: F01 | C8: Inherente | D8: Tipo de persona | E8: Persona física | F8: 1 | G8: Anexo aplicable: 3 física · 4 moral · 8 fideicomiso | H8: =VARIABLES!$B8&"|"&VARIABLES!$E8
B9: F01 | C9: Inherente | D9: Tipo de persona | E9: Persona moral con fines de lucro (sociedad mercantil) | F9: 3 | G9: Anexo aplicable: 3 física · 4 moral · 8 fideicomiso | H9: =VARIABLES!$B9&"|"&VARIABLES!$E9
B10: F01 | C10: Inherente | D10: Tipo de persona | E10: Persona moral sin fines de lucro (asociación o sociedad civil) | F10: 3 | G10: Anexo aplicable: 3 física · 4 moral · 8 fideicomiso | H10: =VARIABLES!$B10&"|"&VARIABLES!$E10
B11: F01 | C11: Inherente | D11: Tipo de persona | E11: Fideicomiso | F11: 5 | G11: Anexo aplicable: 3 física · 4 moral · 8 fideicomiso | H11: =VARIABLES!$B11&"|"&VARIABLES!$E11
B12: F01 | C12: Inherente | D12: Tipo de persona | E12: Otra figura o vehículo sin personalidad jurídica propia | F12: 5 | G12: Anexo aplicable: 3 física · 4 moral · 8 fideicomiso | H12: =VARIABLES!$B12&"|"&VARIABLES!$E12
B13: F01 | C13: Inherente | D13: Tipo de persona | E13: No determinado | F13: 5 | G13: Anexo aplicable: 3 física · 4 moral · 8 fideicomiso | H13: =VARIABLES!$B13&"|"&VARIABLES!$E13
B14: F02 | C14: Inherente | D14: Fecha de nacimiento o de constitución | E14: Persona física de 23 a 59 años | F14: 1 | G14: A3 a) ii) · A4 a) ii) | H14: =VARIABLES!$B14&"|"&VARIABLES!$E14
B15: F02 | C15: Inherente | D15: Fecha de nacimiento o de constitución | E15: Persona física mayor de 60 años | F15: 1 | G15: A3 a) ii) · A4 a) ii) | H15: =VARIABLES!$B15&"|"&VARIABLES!$E15
B16: F02 | C16: Inherente | D16: Fecha de nacimiento o de constitución | E16: Persona física menor de 23 años | F16: 3 | G16: A3 a) ii) · A4 a) ii) | H16: =VARIABLES!$B16&"|"&VARIABLES!$E16
B17: F02 | C17: Inherente | D17: Fecha de nacimiento o de constitución | E17: Persona moral constituida hace más de 5 años | F17: 1 | G17: A3 a) ii) · A4 a) ii) | H17: =VARIABLES!$B17&"|"&VARIABLES!$E17
B18: F02 | C18: Inherente | D18: Fecha de nacimiento o de constitución | E18: Persona moral constituida hace 2 a 5 años | F18: 3 | G18: A3 a) ii) · A4 a) ii) | H18: =VARIABLES!$B18&"|"&VARIABLES!$E18
B19: F02 | C19: Inherente | D19: Fecha de nacimiento o de constitución | E19: Persona moral constituida hace menos de 2 años | F19: 5 | G19: A3 a) ii) · A4 a) ii) | H19: =VARIABLES!$B19&"|"&VARIABLES!$E19
... B107: F22 | C107: Transaccional | D107: Congruencia entre domicilio y lugar de operación | E107: Distinta entidad federativa sin explicación | F107: 5 | G107: Derivado: A3 a) vi) / A4 a) v) contra el registro | H107: =VARIABLES!$B107&"|"&VARIABLES!$E107

Sheet B CLIENTE
B2: B · GRADO DE RIESGO DEL CLIENTE O USUARIA
B3: Modelo de clasificación por Grado de Riesgo individual (Art. 23 Bis). Los factores se agrupan en características inherentes y transaccionales, como los nombra el Art. 23 Bis 2.
B4: Elige la variable de cada factor en el desplegable. El nivel lo trae solo de la hoja VARIABLES; el del producto, de la hoja PRODUCTOS.
B6: IDENTIFICACIÓN DEL CLIENTE
B7: Nombre o identificador del Cliente: | E7: Comercializadora Ejemplo del Norte, S.A. de C.V.
B8: Anexo de identificación aplicable: | E8: Anexo 4 · persona moral mexicana
B9: Fecha de la clasificación: | E9: 2026-07-01
B10: ¿Reside en territorio mexicano?: | E10: Sí
B11: ¿Vínculo o efectos con jurisdicción de régimen fiscal preferente o deficiente en PLD?: | E11: No
B12: Amarillo = tú capturas. También los pesos: los de la columna «Peso» y los de familia (45 % / 55 %) los defines tú «en función de su importancia» (Art. 10 Septies 1, fr. II) y los justificas por escrito. Dentro de cada familia deben sumar 100 %.
B13: FACTORES DE RIESGO · elige la variable; el nivel se calcula solo
B14: Clave | C14: Familia | D14: Factor | E14: Variable seleccionada | F14: Nivel | G14: Peso | H14: Aporte | I14: Fuente del dato
B15: F01 | C15: Inherente | D15: Tipo de persona | E15: Persona moral con fines de lucro (sociedad mercantil) | F15: =IFERROR(INDEX(VARIABLES!$F:$F,MATCH($B15&"|"&$E15,VARIABLES!$H:$H,0)),0) | G15: 0.13 | H15: =F15*G15 | I15: Anexo aplicable: 3 física · 4 moral · 8 fideicomiso
B16: F02 | C16: Inherente | D16: Fecha de nacimiento o de constitución | E16: Persona moral constituida hace menos de 2 años | F16: =IFERROR(INDEX(VARIABLES!$F:$F,MATCH($B16&"|"&$E16,VARIABLES!$H:$H,0)),0) | G16: 0.07 | H16: =F16*G16 | I16: A3 a) ii) · A4 a) ii)
B17: F03 | C17: Inherente | D17: Actividad, ocupación, profesión o giro | E17: Servicios profesionales | F17: =IFERROR(INDEX(VARIABLES!$F:$F,MATCH($B17&"|"&$E17,VARIABLES!$H:$H,0)),0) | G17: 0.15 | H17: =F17*G17 | I17: A3 a) v) · A4 a) iv)
B18: F04 | C18: Inherente | D18: País de nacionalidad | E18: Mexicana | F18: =IFERROR(INDEX(VARIABLES!$F:$F,MATCH($B18&"|"&$E18,VARIABLES!$H:$H,0)),0) | G18: 0.06 | H18: =F18*G18 | I18: A3 a) iv) · A4 a) iii)
B19: F05 | C19: Inherente | D19: Domicilio: país y estado de residencia | E19: Residente en México, entidad federativa señalada en la ENR | F19: =IFERROR(INDEX(VARIABLES!$F:$F,MATCH($B19&"|"&$E19,VARIABLES!$H:$H,0)),0) | G19: 0.09 | H19: =F19*G19 | I19: A3 a) vi) · A4 a) v)
B20: F06 | C20: Inherente | D20: Condición de Persona Políticamente Expuesta | E20: No es Persona Políticamente Expuesta | F20: =IFERROR(INDEX(VARIABLES!$F:$F,MATCH($B20&"|"&$E20,VARIABLES!$H:$H,0)),0) | G20: 0.13 | H20: =F20*G20 | I20: Declaración del Cliente y consulta en Consulta PEP 2.0 · RCG 23 Quáter 1 · RCG 23 Bis 3 y 23 Bis 4
B21: F07 | C21: Inherente | D21: Coincidencia en listas de personas bloqueadas | E21: Sin coincidencia, búsqueda documentada en la operación | F21: =IFERROR(INDEX(VARIABLES!$F:$F,MATCH($B21&"|"&$E21,VARIABLES!$H:$H,0)),0) | G21: 0.1 | H21: =F21*G21 | I21: RCG 38 · RCG 41 fr. V
B22: F08 | C22: Inherente | D22: Beneficiario Controlador | E22: Beneficiario Controlador identificado, cadena de dos o más niveles | F22: =IFERROR(INDEX(VARIABLES!$F:$F,MATCH($B22&"|"&$E22,VARIABLES!$H:$H,0)),0) | G22: 0.17 | H22: =F22*G22 | I22: A3 b) iv) · A4 b) v) · A8 b) iv)
B23: F09 | C23: Inherente | D23: Fuente de los ingresos | E23: Ingresos acreditados parcialmente | F23: =IFERROR(INDEX(VARIABLES!$F:$F,MATCH($B23&"|"&$E23,VARIABLES!$H:$H,0)),0) | G23: 0.06 | H23: =F23*G23 | I23: A3 a) v) · declarada por el Cliente
B24: F10 | C24: Inherente | D24: Naturaleza y propósito de la relación | E24: Cliente ocasional, un solo acto u operación | F24: =IFERROR(INDEX(VARIABLES!$F:$F,MATCH($B24&"|"&$E24,VARIABLES!$H:$H,0)),0) | G24: 0.04 | H24: =F24*G24 | I24: Perfil transaccional · RCG 23 Ter 1
B25: F11 | C25: Transaccional | D25: Producto o servicio contratado | E25: Compraventa de local comercial | F25: =IFERROR(INDEX(PRODUCTOS!$J:$J,MATCH($E25,PRODUCTOS!$C:$C,0)),0) | G25: 0.157 | H25: =F25*G25 | I25: Hoja PRODUCTOS · registro de la operación
B26: F12 | C26: Transaccional | D26: Monto frente al Perfil transaccional y umbrales | E26: Igual o superior al umbral de aviso | F26: =IFERROR(INDEX(VARIABLES!$F:$F,MATCH($B26&"|"&$E26,VARIABLES!$H:$H,0)),0) | G26: 0.126 | H26: =F26*G26 | I26: RCG 23 Ter 1 · L 17
B27: F13 | C27: Transaccional | D27: Número y frecuencia de las operaciones | E27: De dos a cuatro operaciones al año | F27: =IFERROR(INDEX(VARIABLES!$F:$F,MATCH($B27&"|"&$E27,VARIABLES!$H:$H,0)),0) | G27: 0.116 | H27: =F27*G27 | I27: Mecanismo automatizado · criterio propio: el 23 Bis 2 fr. II es lista abierta
B28: F14 | C28: Transaccional | D28: Número de contrapartes | E28: De dos a tres contrapartes | F28: =IFERROR(INDEX(VARIABLES!$F:$F,MATCH($B28&"|"&$E28,VARIABLES!$H:$H,0)),0) | G28: 0.063 | H28: =F28*G28 | I28: Registro de operaciones
B29: F15 | C29: Transaccional | D29: Instrumento monetario | E29: Pago mixto con componente en efectivo | F29: =IFERROR(INDEX(VARIABLES!$F:$F,MATCH($B29&"|"&$E29,VARIABLES!$H:$H,0)),0) | G29: 0.147 | H29: =F29*G29 | I29: Registro de la operación · Aviso
B30: F16 | C30: Transaccional | D30: Tipo de moneda | E30: Peso mexicano | F30: =IFERROR(INDEX(VARIABLES!$F:$F,MATCH($B30&"|"&$E30,VARIABLES!$H:$H,0)),0) | G30: 0.032 | H30: =F30*G30 | I30: Registro de la operación · Aviso
B31: F17 | C31: Transaccional | D31: Origen de los recursos | E31: Origen declarado con soporte parcial | F31: =IFERROR(INDEX(VARIABLES!$F:$F,MATCH($B31&"|"&$E31,VARIABLES!$H:$H,0)),0) | G31: 0.137 | H31: =F31*G31 | I31: RCG 23 Ter 3 · declarado por el Cliente
B32: F18 | C32: Transaccional | D32: Destino de los recursos | E32: Destino es el propio bien u operación, registrado | F32: =IFERROR(INDEX(VARIABLES!$F:$F,MATCH($B32&"|"&$E32,VARIABLES!$H:$H,0)),0) | G32: 0.063 | H32: =F32*G32 | I32: RCG 23 Ter 3 · declarado por el Cliente
B33: F19 | C33: Transaccional | D33: Canal: certeza de identificación | E33: Comparecencia directa del Cliente, o identificación remota con biometría y prueba de vida | F33: =IFERROR(INDEX(VARIABLES!$F:$F,MATCH($B33&"|"&$E33,VARIABLES!$H:$H,0)),0) | G33: 0.053 | H33: =F33*G33 | I33: Registro de la operación · cómo se identificó al Cliente
B34: F20 | C34: Transaccional | D34: País o jurisdicción de la operación | E34: México | F34: =IFERROR(INDEX(VARIABLES!$F:$F,MATCH($B34&"|"&$E34,VARIABLES!$H:$H,0)),0) | G34: 0.042 | H34: =F34*G34 | I34: Registro de la operación
B35: F21 | C35: Transaccional | D35: Área geográfica nacional de la operación | E35: Entidad federativa con señalamiento en la ENR | F35: =IFERROR(INDEX(VARIABLES!$F:$F,MATCH($B35&"|"&$E35,VARIABLES!$H:$H,0)),0) | G35: 0.032 | H35: =F35*G35 | I35: Registro de la operación
B36: F22 | C36: Transaccional | D36: Congruencia entre domicilio y lugar de operación | E36: Distinta entidad federativa, con explicación documentada | F36: =IFERROR(INDEX(VARIABLES!$F:$F,MATCH($B36&"|"&$E36,VARIABLES!$H:$H,0)),0) | G36: 0.032 | H36: =F36*G36 | I36: Derivado: A3 a) vi) / A4 a) v) contra el registro
B37: F11 es el único factor cuyo nivel no sale de VARIABLES sino de la hoja PRODUCTOS: el riesgo del producto se calcula ahí con sus seis indicadores. Excel puede marcar esa celda como «fórmula inconsistente»; es correcta.
B38: RESULTADO POR FAMILIA · Art. 23 Bis 2 fracciones I y II
C39: Familia de factores | D39: Calif. | E39: Peso | F39: Aporte | G39: Nivel
B40: I | C40: Características inherentes | D40: =IFERROR(SUM(H15:H24)/SUM(G15:G24),0) | E40: 0.45 | F40: =D40*E40 | G40: =IF(D40>=3.67,"ALTO",IF(D40>=2.34,"MEDIO","BAJO"))
B41: II | C41: Características transaccionales | D41: =IFERROR(SUM(H25:H36)/SUM(G25:G36),0) | E41: 0.55 | F41: =D41*E41 | G41: =IF(D41>=3.67,"ALTO",IF(D41>=2.34,"MEDIO","BAJO"))
C42: Suma de los pesos de familia (debe ser 100 %) | E42: =SUM(E40:E41) | G42: =IF(ABS(SUM(E40:E41)-1)<=0.001,"OK","Corregir")
C43: Factores todavía sin elegir: | E43: =COUNTIF($F$15:$F$36,0) | G43: =IF($E$43=0,"Completo: los 22 factores resueltos","Mientras haya factores sin elegir no se emite grado")
B45: GRADO DE RIESGO DEL CLIENTE
B46: Calificación ponderada del Cliente (escala 1 a 5): | E46: =IFERROR(SUMPRODUCT(D40:D41,E40:E41)/SUM(E40:E41),0)
B47: Grado base: | E47: =IF(COUNTIF($F$15:$F$36,0)>0,"— faltan factores por elegir —",IF($E$46=0,"",IF($E$46>=3.67,"ALTO",IF($E$46>=2.34,"MEDIO","BAJO"))))
B48: Regla obligatoria de riesgo alto (Art. 23 Bis 4): | E48: =IF(OR($E$20="PEP extranjera",AND($E$10="No",$E$11="Sí")),"Aplica: PEP extranjera o no residente vinculado a jurisdicción de régimen fiscal preferente o deficiente","No aplica")
B50: GRADO DE RIESGO FINAL | E50: =IF(COUNTIF($F$15:$F$36,0)>0,"SIN CLASIFICAR",IF(OR($E$20="PEP extranjera",AND($E$10="No",$E$11="Sí")),"ALTO",E47)) | G50: =IF(E50="ALTO","Debida diligencia reforzada: Arts. 23 Ter 3, 23 Ter 4 y 23 Ter 5","Régimen ordinario, sin perjuicio del expediente que corresponda")
B53: CÓMO SE LEE · Alto = 5 · Medio = 3 · Bajo = 1, la misma escala de calificación de la hoja A1
C54: BAJO | D54: 1.00 a 2.33 | E54: Expediente conforme al Art. 12. Medidas simplificadas sólo si se cumplen LAS DOS condiciones: Cliente de bajo Riesgo (Art. 17 de las Reglas) y entidad de bajo riesgo (Art. 15 del Reglamento).
C55: MEDIO | D55: 2.34 a 3.66 | E55: Expediente completo del Art. 12 de las Reglas (Art. 17 Bis).
C56: ALTO | D56: 3.67 a 5.00 | E56: Expediente reforzado: Arts. 23 Ter 3, 23 Ter 4 y, si además es PEP, 23 Ter 5.
B58: SI EL GRADO ES ALTO — Debida Diligencia Reforzada
B59: • Art. 23 Ter 3 — Requerir mayor información sobre la actividad preponderante y aplicar revisión y monitoreo más estricto del comportamiento transaccional.
B60: • Art. 23 Ter 3 — Aplicar cuestionario de identificación sobre origen y destino de los recursos. Puede ser remoto, con Firma Electrónica de quien lo suscribe.
B61: • Art. 23 Ter 4 fr. I — Persona física: medidas reforzadas sobre origen y destino, y datos del cónyuge, dependientes económicos y vínculos patrimoniales.
B62: • Art. 23 Ter 4 fr. II — Persona moral: mayor información de accionistas o socios, verificando los datos en los registros electrónicos de la Secretaría de Economía.
B63: • Art. 23 Ter 5 — PEP con grado alto: aprobación previa de un directivo o equivalente. Si quien realiza la Actividad Vulnerable es persona física, se subsana con constancia motivada.
B64: • Art. 23 Bis 1 — Reevaluar el grado al menos cada seis meses, con mayor frecuencia mientras mayor sea el grado.
B66: RÉGIMEN DE EXPEDIENTE · dos ejes distintos y ambos deben cumplirse: Art. 17 de las Reglas para el Cliente, Art. 15 del Reglamento para la entidad
B67: Grado de riesgo final del CLIENTE: | E67: =$E$50
B68: Riesgo residual de la ENTIDAD (hoja A5): | E68: ='A5 RESIDUAL'!$G$13
B69: Expediente que debe integrarse: | E69: =IF(OR($E$67="",$E$67="SIN CLASIFICAR",$E$68="SIN EVALUAR"),"— falta completar la clasificación del Cliente o la evaluación de la entidad —",IF($E$67="ALTO","Expediente reforzado: expediente completo, más cuestionario de identificación reforzada con Firma Electrónica; si además es PEP, aprobación de un directivo (Arts. 23 Ter 3, 4 y 5).",IF($E$67="MEDIO","Expediente completo del Art. 12 de las Reglas (Art. 17 Bis).",IF($E$68="BAJO",("Medidas simplificadas: bastan los datos de los anexos (Art. 17 de las Reglas). Proceden porque se cumplen las DOS condiciones: el Cliente es de bajo Riesgo conforme al Capítulo III Bis (Art. 17) y tu entidad es de bajo riesgo residual (Art. 15 del Re"&"glamento)."),"Expediente completo del Art. 12: aunque el Cliente es de bajo Riesgo, tu entidad no lo es, y el Art. 15 del Reglamento condiciona las medidas simplificadas a que quien realiza la Actividad Vulnerable sea de bajo riesgo. Falta una de las dos condiciones."))))
B72: Coherencia con la metodología (Art. 23 Bis): este modelo usa la misma escala de calificación de la hoja A1 —Alto 5 · Medio 3 · Bajo 1— y el mismo criterio de ponderación del Art. 10 Septies 1 fr. II, pero se agrupa como lo nombra el Art. 23 Bis 2: características inherentes y transaccionales. Los cuatro elementos del Art. 10 Septies 1 fr. I son de la evaluación de la ENTIDAD, no del Cliente. Lo que no aplica al Cliente es la concentración, porque un Cliente no se reparte en porcentajes de operación: por eso el resultado corre de 1 a 5 y no de 1 a 25. · MEDIDAS SIMPLIFICADAS, CRITERIO DE LAS PERSONAS AUTORAS. Son dos condiciones en dos ordenamientos distintos y ninguno repite la del otro: el Art. 15 del Reglamento pide que la ENTIDAD sea de bajo riesgo, y el Art. 17 de las Reglas pide que el CLIENTE esté clasificado de bajo Riesgo conforme al Capítulo III Bis. Se leen como acumulativas por jerarquía: una regla de carácter general no puede dispensar una condición del Reglamento, y el propio Art. 15 la manda desarrollar, no sustituir. Consecuencia en los dos sentidos: una entidad de bajo riesgo no puede simplificar con un Cliente de Riesgo alto, y un Cliente de bajo Riesgo no accede al expediente simplificado si la entidad no es de bajo riesgo. · QUÉ RIESGO DE LA ENTIDAD. Este modelo usa el RESIDUAL de la hoja A5. Es criterio: ni el Art. 15 del Reglamento ni los Arts. 44 y 45 dicen si el riesgo es inherente o residual, y en las Reglas la palabra residual no aparece ni una vez. Se toma el residual porque el Art. 10 Septies 1 fr. III obliga a establecer el efecto de los Mitigantes sobre los elementos de Riesgo, y el Art. 10 Septies 2 a mantenerlos en un nivel de tolerancia aceptable. · Y un dato para el aula: la condición del bajo riesgo de la entidad NO es nueva. Está en el Art. 15 del Reglamento desde su publicación en el DOF del 16 de agosto de 2013. Lo que la reforma del 27 de marzo de 2026 agregó fue el anclaje a la evaluación del Art. 18 fr. VII de la Ley, fracción adicionada el 16 de julio de 2025. La reforma no creó la condición: la hizo operativa.
B76: EVENTOS QUE OBLIGAN A REVISAR EL GRADO · no suman puntos: disparan revisión
B77: Estos hechos NO entran al promedio ponderado. Si entraran, una desviación grave movería la calificación unas décimas y el Cliente se quedaría igual. Operan como el supuesto obligatorio del Art. 23 Bis 4: se saltan el puntaje. Al marcar cualquiera en «Sí», procede revisar el Grado y, en su caso, modificarlo (Art. 23 Ter frs. IV y V) y actualizar el expediente. El sistema de alertas del Art. 23 Ter 2 es el que debe detectarlos.
B78: Evento | E78: ¿Ocurrió? | F78: Fecha | G78: Fundamento
B79: Alerta de desviación respecto del Perfil transaccional declarado | E79: No | G79: RCG 23 Ter 1 y 23 Ter 2
B80: Cambio en el Beneficiario Controlador o en la cadena de control | E80: No | G80: RCG 22 · Anexos 3, 4 y 8
B81: Coincidencia nueva en listas de personas bloqueadas o de sanciones | E81: No | G81: RCG 38 · RCG 41 fr. V
B82: Cambio en la condición de Persona Políticamente Expuesta | E82: No | G82: RCG 23 Quáter · 23 Quáter 1 (Consulta PEP 2.0)
B83: Cambio significativo en la actividad, el giro o la fuente de los ingresos | E83: No | G83: RCG 23 Ter fr. IV
B84: Operación que se aparta del patrón habitual del Cliente | E84: No | G84: RCG 23 Ter 2
B85: ¿Procede revisar el Grado de Riesgo? | E85: =IF(COUNTIF($E$79:$E$84,"Sí")>0,"SÍ · REVISAR EL GRADO Y DEJAR CONSTANCIA DEL RESULTADO","Sin eventos registrados en el periodo")

Sheet PARAMETROS
B2: PARÁMETROS Y ESCALAS DE LA METODOLOGÍA
B3: Base técnica reglas / CNBV / GAFILAT. Solo edita el valor de la UMA y el Nivel de Tolerancia.
B4: Paso 0 de 10 · Se configura una vez · Sigue: INICIO
B5: ESCALA DE CALIFICACIÓN (qué tan riesgoso) | F5: ESCALA DE CONCENTRACIÓN (qué tan expuesto)
B6: 1 | C6: Muy bajo | D6: Perfil de bajo riesgo | F6: 1 | G6: Mínima | H6: Casi nada del negocio expuesto
B7: 2 | C7: Bajo | D7: Riesgo limitado | F7: 2 | G7: Baja | H7: Parte menor expuesta
B8: 3 | C8: Medio | D8: Riesgo moderado | F8: 3 | G8: Media | H8: Parte relevante expuesta
B9: 4 | C9: Alto | D9: Riesgo elevado | F9: 4 | G9: Alta | H9: Buena parte expuesta
B10: 5 | C10: Muy alto | D10: Riesgo crítico | F10: 5 | G10: Muy alta | H10: La mayoría del negocio expuesto
B11: Esta escala de cinco es para el riesgo de la ENTIDAD (hojas A1 a A9). Con tres niveles el resultado queda muy compacto y casi todo sale «medio».
B13: NIVELES DE RIESGO (Calificación × Concentración) | H13: ESCALA DE EVALUACIÓN DE OBLIGACIONES (Art. 48 de las Reglas)
B14: Límite inf. | C14: De | D14: A | E14: Nivel | F14: Color | H14: Resultado | I14: Equivale a | J14: Cuándo se usa (Art. 48)
B15: 0 | C15: 1 | D15: 5 | E15: BAJO | H15: Cumple | I15: 1 | J15: La eficacia del cumplimiento se demuestra y el auditor no recomienda mejoras.
B16: 5.01 | C16: 6 | D16: 9 | E16: MEDIO BAJO | H16: Cumple mayoritariamente | I16: 0.75 | J16: La eficacia no se demuestra por completo; hay al menos una recomendación de mejora.
B17: 9.01 | C17: 10 | D17: 12 | E17: MEDIO | H17: Cumple parcialmente | I17: 0.4 | J17: La eficacia no se demuestra por no contar con evidencia objetiva; hay al menos un hallazgo.
B18: 12.01 | C18: 13 | D18: 16 | E18: MEDIO ALTO | H18: No cumple | I18: 0 | J18: No cubre los elementos necesarios o actualiza una sanción. No mitiga: computa 0%.
B19: 16.01 | C19: 17 | D19: 25 | E19: ALTO | H19: No aplica | I19: — | J19: La obligación no es exigible (Art. 37 Bis 2). Sale del numerador y del denominador.
B20: OJO · Estos cinco niveles son de la ENTIDAD. El GRADO DE RIESGO DEL CLIENTE (hoja B CLIENTE) va en TRES: bajo, medio y alto — es el mínimo del Art. 23 Bis. No se mezclan.
H21: Editable (celdas amarillas): es el porcentaje que reconoces a cada resultado del Art. 48. «No cumple» vale 0% porque puede actualizar una sanción: no puede mitigar. «No aplica» no tiene porcentaje: la obligación sale del numerador y del denominador conforme al Art. 37 Bis 2.
B22: VALOR DIARIO DE LA UMA (MXN) — actualízalo cada año: | C22: 117.31 | D22: Vigente desde 1-feb-2026 (INEGI). Recalcula los umbrales MXN del catálogo.
B24: NIVEL DE TOLERANCIA AL RIESGO (editable)
B25: Riesgo máximo aceptable: | C25: MEDIO
B28: MITIGACIÓN: TOPE MÁXIMO DE REDUCCIÓN (editable)
B29: La efectividad promedio de tus mitigantes no se traslada íntegra al resultado: se multiplica por este tope. Con 50%, aunque todos tus controles fueran Óptimos, el riesgo inherente se reduce a la mitad y nunca a cero. El control mitiga, no elimina.
B30: Tope de reducción: | C30: 0.5
B31: Reducción aplicada = Efectividad del catálogo de controles mínimos (hoja A4 CONTROLES MINIMOS) × Tope de reducción.
B32: Riesgo residual = Riesgo inherente × (1 − Reducción aplicada). La misma reducción se aplica al indicador, al elemento y a la entidad.
B33: Si subes el tope, súbelo con criterio escrito: en Actividades Vulnerables el nivel de riesgo tiene consecuencias automáticas (régimen de auditoría del Cap. XIV y medidas simplificadas del Art. 15 del Reglamento). Un tope generoso no es un ahorro: es una exposición.
B38: CRITERIOS DE CALIBRACIÓN DOCUMENTADOS (por qué el número es el que es)
B39: Regla | D39: Fórmula | E39: Criterio y por qué
B40: Calificación | D40: 5×%Alto + 3×%Medio + 1×%Bajo, redondeado | E40: Escala de 1 a 5 ponderada por la proporción real del negocio en cada perfil. No es un promedio de opiniones: es la mezcla declarada en A1.
B41: Concentración | D41: 1 + 4×(%Alto + %Medio), redondeado | E41: Criterio conservador y deliberado: el perfil MEDIO se cuenta como plenamente expuesto, y solo la porción clasificada en BAJO reduce la concentración. Si tu metodología prefiere ponderar el medio al 50%, cámbialo aquí y documenta el cambio: lo defendible es que el criterio esté escrito.
B42: Riesgo inherente | D42: Calificación × Concentración | E42: Rango de 1 a 25. Los cortes entre BAJO, MEDIO BAJO, MEDIO, MEDIO ALTO y ALTO son los de la tabla de niveles de esta misma hoja y pueden editarse.
B43: Riesgo residual | D43: Riesgo inherente × (1 − Reducción aplicada) | E43: La reducción es un porcentaje, no una división: Reducción = Efectividad × Tope. La efectividad se mide contra un denominador fijo: las 14 obligaciones del catálogo de contenidos mínimos del Manual (Art. 37 Bis), menos las excluidas por «No aplica» conforme al Art. 37 Bis 2. Una obligación no registrada no se excluye: computa 0%. Los mitigantes se miden una sola vez, a nivel de la entidad, y esa misma reducción se aplica al indicador, al elemento y a la entidad.
B44: Peso de los indicadores | D44: Relativo dentro de cada elemento (A1, columna Peso) | E44: El cálculo es un promedio ponderado, así que los pesos se normalizan solos: no tienen que sumar 1. Lo que importa es la proporción entre ellos.
B45: Peso de los elementos | D45: Debe sumar 100% (A1, celdas D35:D38) | E45: Se captura y se justifica por escrito en la propia hoja A1 (Art. 10 Septies 1, fr. II: el valor se asigna en función de la importancia del elemento). Un reparto plano de 25/25/25/25 sin justificación se lee como que no se ponderó.
B47: Estos criterios forman parte de la metodología que debe describirse en el Manual (Art. 10 Septies, segundo párrafo). Si cambias un criterio, cámbialo también ahí.

Sheet CATALOGO
B2: CATÁLOGO DE ACTIVIDADES VULNERABLES (Art. 17 LFPIORPI)
B3: La actividad elegida en INICIO precarga umbrales, características y evento típico.
B4: Referencia: no se edita. La actividad se elige en INICIO.
B5: # | C5: Fracción | D5: Actividad Vulnerable | E5: Actividad (elegir en INICIO) | F5: Umbral identificación (UMA) | G5: Umbral aviso (UMA) | H5: Umbral identificación (MXN) | I5: Umbral aviso (MXN) | J5: Características ALTO | K5: Características MEDIO | L5: Características BAJO | M5: Evento típico | N5: Causa | O5: Consecuencia
B6: 1 | C6: I | D6: Juegos con apuesta | E6: I - Juegos con apuesta | F6: 325 | G6: 645 | H6: =IF(ISNUMBER($F6),$F6*PARAMETROS!$C$22,$F6) | I6: =IF(ISNUMBER($G6),$G6*PARAMETROS!$C$22,$G6) | J6: Apuestas en efectivo de alto monto, clientes no frecuentes o extranjeros, apuestas en línea sin trazabilidad clara. | K6: Apuestas mixtas (efectivo y transferencia), montos moderados, clientes recurrentes. | L6: Apuestas con tarjeta bancaria o monederos electrónicos, montos bajos y clientes identificables. | M6: Introducción de efectivo ilícito en casinos o plataformas. | N6: Uso intensivo de efectivo, dispersión de apuestas. | O6: Integración de dinero ilícito, sanciones a la entidad, pérdida de licencia.
B7: 2 | C7: II | D7: Tarjetas de crédito o servicios | E7: II - Tarjetas de crédito o servicios | F7: 805 | G7: 1285 | H7: =IF(ISNUMBER($F7),$F7*PARAMETROS!$C$22,$F7) | I7: =IF(ISNUMBER($G7),$G7*PARAMETROS!$C$22,$G7) | J7: Uso de tarjetas emitidas en el extranjero o con líneas de crédito inusualmente altas. | K7: Tarjetas nacionales con uso mixto (efectivo/transferencias) y movimientos atípicos. | L7: Tarjetas nacionales de clientes con historial crediticio claro y montos habituales. | M7: Uso de tarjetas para dispersar fondos ilícitos o triangular pagos. | N7: Montos elevados sin justificación económica. | O7: Detección por UIF, congelamiento de cuentas, sanciones.
B8: 3 | C8: II | D8: Tarjetas prepagadas y monederos electrónicos | E8: II - Tarjetas prepagadas y monederos electrónicos | F8: 645 | G8: 645 | H8: =IF(ISNUMBER($F8),$F8*PARAMETROS!$C$22,$F8) | I8: =IF(ISNUMBER($G8),$G8*PARAMETROS!$C$22,$G8) | J8: Tarjetas recargables en efectivo de alto monto, adquiridas de forma masiva. | K8: Tarjetas con recargas mixtas (efectivo y transferencia), uso en varios comercios. | L8: Tarjetas con recarga en cuenta bancaria, límites bajos y trazables. | M8: Uso de monederos para dispersión y anonimato en transacciones. | N8: Bajo nivel de identificación en productos masivos. | O8: Riesgo de operaciones estructuradas y financiamiento ilícito.
B9: 4 | C9: III | D9: Cheques de viajero | E9: III - Cheques de viajero | F9: Siempre | G9: 645 | H9: =IF(ISNUMBER($F9),$F9*PARAMETROS!$C$22,$F9) | I9: =IF(ISNUMBER($G9),$G9*PARAMETROS!$C$22,$G9) | J9: Emisión o adquisición en efectivo, altos montos, operaciones internacionales. | K9: Cheques adquiridos con mezcla de efectivo y transferencias, uso ocasional. | L9: Cheques adquiridos con transferencias desde cuentas bancarias de clientes identificados. | M9: Introducción de recursos ilícitos vía instrumentos internacionales. | N9: Facilidad de portabilidad y canje en múltiples países. | O9: Riesgo transfronterizo, sanciones regulatorias, congelamiento de fondos.
B10: 5 | C10: IV | D10: Préstamos o créditos | E10: IV - Préstamos o créditos | F10: Siempre | G10: 1605 | H10: =IF(ISNUMBER($F10),$F10*PARAMETROS!$C$22,$F10) | I10: =IF(ISNUMBER($G10),$G10*PARAMETROS!$C$22,$G10) | J10: Créditos en efectivo, sin garantía real, de monto elevado o a corto plazo, susceptibles de ser liquidados anticipadamente. | K10: Créditos personales o comerciales de mediano plazo, con garantía parcial o con pagos mixtos (efectivo y transferencia). | L10: Créditos hipotecarios, automotrices o empresariales con garantías reales, pagos periódicos y trazables vía sistema financiero. | M10: Uso del crédito para inyectar recursos ilícitos y justificar flujos financieros. | N10: Flexibilidad de los productos de crédito, posibilidad de pagos en efectivo. | O10: Riesgo de introducir fondos ilícitos disfrazados de financiamiento.
B11: 6 | C11: V | D11: Construcción/comercialización inmuebles | E11: V - Construcción/comercialización inmuebles | F11: Siempre | G11: 8025 | H11: =IF(ISNUMBER($F11),$F11*PARAMETROS!$C$22,$F11) | I11: =IF(ISNUMBER($G11),$G11*PARAMETROS!$C$22,$G11) | J11: Venta de inmuebles de lujo o múltiples operaciones en preventa con pagos en efectivo. | K11: Venta de inmuebles de valor medio con esquema de pagos mixtos (efectivo + transferencias). | L11: Venta de inmuebles de interés social o vivienda regulada con créditos hipotecarios bancarios. | M11: Uso de operaciones inmobiliarias para introducir o estratificar fondos ilícitos. | N11: Altos montos y posibilidad de pagos fragmentados. | O11: Riesgo de sobrevaluación, lavado de activos y sanciones.
B12: 7 | C12: V Bis | D12: Recepción recursos desarrollo inmobiliario | E12: V Bis - Recepción recursos desarrollo inmobiliario | F12: Siempre | G12: 8025 | H12: =IF(ISNUMBER($F12),$F12*PARAMETROS!$C$22,$F12) | I12: =IF(ISNUMBER($G12),$G12*PARAMETROS!$C$22,$G12) | J12: Recepción de aportaciones en efectivo o de múltiples inversionistas no identificados. | K12: Recursos mixtos (transferencias + efectivo) en proyectos medianos. | L12: Recursos canalizados vía instituciones financieras con trazabilidad plena y contratos formalizados. | M12: Canalización de recursos ilícitos a proyectos inmobiliarios. | N12: Participación de múltiples inversionistas, dificultad en verificar origen de fondos. | O12: Riesgo de cooptación de proyectos para blanqueo de capitales.
B13: 8 | C13: VI | D13: Piedras y metales preciosos, joyas | E13: VI - Piedras y metales preciosos, joyas | F13: 805 | G13: 1605 | H13: =IF(ISNUMBER($F13),$F13*PARAMETROS!$C$22,$F13) | I13: =IF(ISNUMBER($G13),$G13*PARAMETROS!$C$22,$G13) | J13: Operaciones en efectivo, piezas de alto valor unitario, transacciones frecuentes en mercados informales. | K13: Operaciones con combinación de pagos (efectivo + transferencia), piezas de valor medio, ventas a consignación. | L13: Ventas con factura a través de establecimientos formales, pagos vía sistema bancario. | M13: Uso de joyas, metales y piedras para mover y ocultar valor ilícito. | N13: Portabilidad, alta liquidez y difícil trazabilidad de estos bienes. | O13: Riesgo de blanqueo transfronterizo y sanciones.
B14: 9 | C14: VII | D14: Subasta/comercialización obras de arte | E14: VII - Subasta/comercialización obras de arte | F14: 2410 | G14: 4815 | H14: =IF(ISNUMBER($F14),$F14*PARAMETROS!$C$22,$F14) | I14: =IF(ISNUMBER($G14),$G14*PARAMETROS!$C$22,$G14) | J14: Obras de alto valor, subastas internacionales, piezas sin trazabilidad de propiedad. | K14: Obras de valor intermedio, galerías locales, pagos mixtos. | L14: Venta de arte contemporáneo o decorativo de bajo valor con facturación completa. | M14: Uso del arte para justificar incrementos patrimoniales o transferencias internacionales. | N14: Valor subjetivo y dificultad en tasación de obras. | O14: Riesgo de sobrevaluación, subdeclaración y financiamiento ilícito.
B15: 10 | C15: VIII | D15: Distribución/comercialización vehículos | E15: VIII - Distribución/comercialización vehículos | F15: 3210 | G15: 6420 | H15: =IF(ISNUMBER($F15),$F15*PARAMETROS!$C$22,$F15) | I15: =IF(ISNUMBER($G15),$G15*PARAMETROS!$C$22,$G15) | J15: Venta de vehículos de lujo o coleccionables, pagos en efectivo, operaciones múltiples en corto plazo. | K15: Venta de vehículos de gama media con esquemas de financiamiento parcial. | L15: Venta de vehículos económicos a través de agencias con pagos bancarios y crédito formal. | M15: Adquisición de vehículos para ocultar origen ilícito de fondos. | N15: Alto valor de los bienes y posibilidad de liquidación en efectivo. | O15: Riesgo de acumulación patrimonial ilícita y decomiso.
B16: 11 | C16: IX | D16: Servicios de blindaje | E16: IX - Servicios de blindaje | F16: 2410 | G16: 4815 | H16: =IF(ISNUMBER($F16),$F16*PARAMETROS!$C$22,$F16) | I16: =IF(ISNUMBER($G16),$G16*PARAMETROS!$C$22,$G16) | J16: Blindaje de vehículos de lujo y bienes inmuebles con pagos en efectivo. | K16: Blindaje de vehículos medianos con pagos mixtos. | L16: Blindaje contratado por empresas reguladas con pagos vía sistema financiero. | M16: Blindaje usado para protección de recursos ilícitos. | N16: Alta demanda de efectivo y bienes de alto valor. | O16: Riesgo de vínculo con delincuencia organizada.
B17: 12 | C17: X | D17: Transporte y custodia de valores | E17: X - Transporte y custodia de valores | F17: Siempre | G17: 3210 | H17: =IF(ISNUMBER($F17),$F17*PARAMETROS!$C$22,$F17) | I17: =IF(ISNUMBER($G17),$G17*PARAMETROS!$C$22,$G17) | J17: Custodia o traslado de valores en efectivo de alto volumen o bienes de alto valor | K17: Custodia de valores mixtos (efectivo y documentos) | L17: Custodia de valores financieros documentados (títulos, cheques, transferencias) | M17: Movilización de efectivo ilícito. | N17: Dificultad de control en traslado físico. | O17: Riesgo de decomiso y sanciones.
B18: 13 | C18: XI | D18: Servicios Profesionales | E18: XI - Servicios Profesionales | F18: Siempre | G18: Siempre | H18: =IF(ISNUMBER($F18),$F18*PARAMETROS!$C$22,$F18) | I18: =IF(ISNUMBER($G18),$G18*PARAMETROS!$C$22,$G18) | J18: Servicios que implican estructuración patrimonial o fiscal compleja | K18: Servicios especializados de valor intermedio (contratos mercantiles, trámites específicos) | L18: Servicios rutinarios o administrativos (contabilidad básica, asesoría legal común) | M18: Profesionales usados para dar apariencia de legalidad. | N18: Posibilidad de diseñar esquemas opacos. | O18: Corresponsabilidad legal.
B19: 14 | C19: XII | D19: NOTARIOS: Transmisión de inmuebles | E19: XII - NOTARIOS: Transmisión de inmuebles | F19: Siempre | G19: 8000 | H19: =IF(ISNUMBER($F19),$F19*PARAMETROS!$C$22,$F19) | I19: =IF(ISNUMBER($G19),$G19*PARAMETROS!$C$22,$G19) | J19: Transmisión de inmuebles de alto valor | K19: Transmisiones de inmuebles de valor intermedio | L19: Transmisiones de inmuebles de bajo valor o vivienda social | M19: Uso de escrituras para legitimar recursos ilícitos. | N19: Alto valor de operaciones notariales. | O19: Riesgo de nulidad de actos y sanciones.
B20: 15 | C20: XII | D20: NOTARIOS: Poderes irrevocables | E20: XII - NOTARIOS: Poderes irrevocables | F20: Siempre | G20: Siempre | H20: =IF(ISNUMBER($F20),$F20*PARAMETROS!$C$22,$F20) | I20: =IF(ISNUMBER($G20),$G20*PARAMETROS!$C$22,$G20) | J20: Poderes generales con facultades amplias y sin limitación temporal | K20: Poderes especiales de gestión con vigencia determinada | L20: Poderes notariales limitados a actos concretos y de valor reducido | M20: Uso de poderes para ocultar beneficiario final. | N20: Amplio acceso a actos jurídicos sin límite económico. | O20: Riesgo de facilitar control ilícito de activos.
B21: 16 | C21: XII | D21: NOTARIOS: Const. o modif. patrimonial | E21: XII - NOTARIOS: Const. o modif. patrimonial | F21: Siempre | G21: 8025 | H21: =IF(ISNUMBER($F21),$F21*PARAMETROS!$C$22,$F21) | I21: =IF(ISNUMBER($G21),$G21*PARAMETROS!$C$22,$G21) | J21: Constitución de sociedades patrimoniales con aportaciones significativas | K21: Modificación parcial de sociedades con capital intermedio | L21: Ajustes patrimoniales menores y documentados | M21: Uso de sociedades para canalizar fondos ilícitos. | N21: Flexibilidad de estructuras societarias. | O21: Riesgo de sobrevaluación y evasión.
B22: 17 | C22: XII | D22: NOTARIOS: Const. o modif. fideicomisos | E22: XII - NOTARIOS: Const. o modif. fideicomisos | F22: Siempre | G22: 4000 | H22: =IF(ISNUMBER($F22),$F22*PARAMETROS!$C$22,$F22) | I22: =IF(ISNUMBER($G22),$G22*PARAMETROS!$C$22,$G22) | J22: Fideicomisos de inversión de gran valor | K22: Fideicomisos de inversión o administración con montos intermedios | L22: Fideicomisos patrimoniales familiares con montos bajos | M22: Uso de fideicomisos para ocultar recursos ilícitos. | N22: Complejidad de instrumentos fiduciarios. | O22: Riesgo de ocultar beneficiarios finales.
B23: 18 | C23: XII | D23: NOTARIOS: Mutuo con no financiero | E23: XII - NOTARIOS: Mutuo con no financiero | F23: Siempre | G23: Siempre | H23: =IF(ISNUMBER($F23),$F23*PARAMETROS!$C$22,$F23) | I23: =IF(ISNUMBER($G23),$G23*PARAMETROS!$C$22,$G23) | J23: Mutuos de gran monto entre particulares | K23: Mutuos de valor intermedio | L23: Mutuos de bajo monto, formalizados y documentados | M23: Préstamos usados para circular recursos ilícitos. | N23: Flexibilidad del contrato civil. | O23: Riesgo de simulación de operaciones.
B24: 19 | C24: XII | D24: CORREDORES: Avalúos | E24: XII - CORREDORES: Avalúos | F24: 8025 | G24: 8025 | H24: =IF(ISNUMBER($F24),$F24*PARAMETROS!$C$22,$F24) | I24: =IF(ISNUMBER($G24),$G24*PARAMETROS!$C$22,$G24) | J24: Avalúos de bienes de alto valor | K24: Avalúos de bienes de valor intermedio | L24: Avalúos de bienes de bajo valor o de vivienda social | M24: Uso de avalúos para inflar patrimonio. | N24: Valoración subjetiva de bienes. | O24: Riesgo de justificación ilícita de activos.
B25: 20 | C25: XII | D25: CORREDORES: Const. o modif. patrimonial | E25: XII - CORREDORES: Const. o modif. patrimonial | F25: Siempre | G25: Siempre | H25: =IF(ISNUMBER($F25),$F25*PARAMETROS!$C$22,$F25) | I25: =IF(ISNUMBER($G25),$G25*PARAMETROS!$C$22,$G25) | J25: Constitución de sociedades patrimoniales de alto valor | K25: Modificaciones societarias de valor intermedio | L25: Ajustes menores en sociedades pequeñas | M25: Uso de sociedades mercantiles para blanquear recursos. | N25: Flexibilidad del marco mercantil. | O25: Riesgo de opacidad en beneficiarios.
B26: 21 | C26: XII | D26: CORREDORES: Modif. o cesión fideicomiso | E26: XII - CORREDORES: Modif. o cesión fideicomiso | F26: Siempre | G26: Siempre | H26: =IF(ISNUMBER($F26),$F26*PARAMETROS!$C$22,$F26) | I26: =IF(ISNUMBER($G26),$G26*PARAMETROS!$C$22,$G26) | J26: Cesión de derechos fiduciarios de alto valor | K26: Cesiones parciales de derechos de valor intermedio | L26: Cesiones de bajo valor o entre familiares | M26: Cesión usada para ocultar transferencia ilícita. | N26: Complejidad fiduciaria. | O26: Riesgo de lavado mediante cesiones.
B27: 22 | C27: XII | D27: CORREDORES: Mutuo mercantil | E27: XII - CORREDORES: Mutuo mercantil | F27: Siempre | G27: Siempre | H27: =IF(ISNUMBER($F27),$F27*PARAMETROS!$C$22,$F27) | I27: =IF(ISNUMBER($G27),$G27*PARAMETROS!$C$22,$G27) | J27: Mutuos mercantiles de alto valor | K27: Mutuos mercantiles de valor intermedio | L27: Mutuos mercantiles de bajo valor, documentados | M27: Simulación de préstamos para circular fondos ilícitos. | N27: Flexibilidad contractual. | O27: Riesgo de simulación patrimonial.
B28: 23 | C28: XII | D28: FACILITADORES: Solución de controversias | E28: XII - FACILITADORES: Solución de controversias | F28: Siempre | G28: 8025 | H28: =IF(ISNUMBER($F28),$F28*PARAMETROS!$C$22,$F28) | I28: =IF(ISNUMBER($G28),$G28*PARAMETROS!$C$22,$G28) | J28: Soluciones de controversias internacionales de alto valor económico | K28: Controversias nacionales de valor intermedio | L28: Controversias de bajo valor económico | M28: Uso de servicios legales para legitimar flujos. | N28: Pago de honorarios difícil de trazar. | O28: Riesgo de corresponsabilidad.
B29: 24 | C29: XIII | D29: Recepción de donativos | E29: XIII - Recepción de donativos | F29: 1605 | G29: 3210 | H29: =IF(ISNUMBER($F29),$F29*PARAMETROS!$C$22,$F29) | I29: =IF(ISNUMBER($G29),$G29*PARAMETROS!$C$22,$G29) | J29: Donativos de gran valor económico | K29: Donativos de valor intermedio | L29: Donativos de bajo valor, frecuentes en asociaciones pequeñas | M29: Uso de asociaciones para canalizar fondos ilícitos. | N29: Flexibilidad en recepción de recursos. | O29: Riesgo de infiltración criminal.
B30: 25 | C30: XIV | D30: CEXT: Joyas, metales, piedras preciosas | E30: XIV - CEXT: Joyas, metales, piedras preciosas | F30: 485 | G30: 485 | H30: =IF(ISNUMBER($F30),$F30*PARAMETROS!$C$22,$F30) | I30: =IF(ISNUMBER($G30),$G30*PARAMETROS!$C$22,$G30) | J30: Transacciones internacionales de alto valor | K30: Operaciones nacionales de valor intermedio | L30: Operaciones nacionales de bajo valor con documentación | M30: Uso de comercio exterior para mover valor ilícito. | N30: Portabilidad y liquidez. | O30: Riesgo de contrabando y sanciones.
B31: 26 | C31: XIV | D31: CEXT: Obras de arte | E31: XIV - CEXT: Obras de arte | F31: 4815 | G31: 4815 | H31: =IF(ISNUMBER($F31),$F31*PARAMETROS!$C$22,$F31) | I31: =IF(ISNUMBER($G31),$G31*PARAMETROS!$C$22,$G31) | J31: Subastas internacionales de alto valor | K31: Ventas nacionales de valor intermedio | L31: Obras de bajo valor con factura | M31: Uso de arte en comercio exterior para justificar flujos ilícitos. | N31: Valor subjetivo y mercado opaco. | O31: Riesgo de sobre/subvaluación.
B32: 27 | C32: XIV | D32: CEXT: Vehículos, máquinas, blindaje, etc. | E32: XIV - CEXT: Vehículos, máquinas, blindaje, etc. | F32: Siempre | G32: Siempre | H32: =IF(ISNUMBER($F32),$F32*PARAMETROS!$C$22,$F32) | I32: =IF(ISNUMBER($G32),$G32*PARAMETROS!$C$22,$G32) | J32: Importación/exportación de bienes de lujo | K32: Comercialización de bienes de valor intermedio | L32: Bienes de uso común con documentación completa | M32: Comercio exterior usado para estratificación. | N32: Alto valor de mercancías. | O32: Riesgo de contrabando.
B33: 28 | C33: XV | D33: Arrendamiento de bienes inmuebles (uso o goce) | E33: XV - Arrendamiento de bienes inmuebles (uso o goce) | F33: 1605 | G33: 3210 | H33: =IF(ISNUMBER($F33),$F33*PARAMETROS!$C$22,$F33) | I33: =IF(ISNUMBER($G33),$G33*PARAMETROS!$C$22,$G33) | J33: Arrendamiento de inmuebles de alto valor mensual, pagos en efectivo, arrendatarios de dificil identificacion o giro sensible. | K33: Arrendamiento de valor intermedio con pagos mixtos (efectivo y transferencia). | L33: Arrendamiento de bajo valor mensual, contrato formal y pagos trazables. | M33: Uso del arrendamiento como fachada o para introducir recursos ilicitos. | N33: Falta de verificacion del giro real del arrendatario y del origen de los pagos. | O33: Riesgo legal y reputacional; local usado para actividades ilicitas.
B34: 29 | C34: XVI | D34: Activos virtuales (PSAV): operación de intercambio/transferencia | E34: XVI - Activos virtuales (PSAV): operación de intercambio/transferencia | F34: Siempre | G34: 210 | H34: =IF(ISNUMBER($F34),$F34*PARAMETROS!$C$22,$F34) | I34: =IF(ISNUMBER($G34),$G34*PARAMETROS!$C$22,$G34) | J34: Intercambio/transferencia de activos virtuales con clientes no identificados, operaciones transfronterizas, montos elevados o anonimato on-chain. | K34: Operaciones con identificacion parcial y montos moderados. | L34: Operaciones con KYC completo, trazabilidad on-chain y montos bajos en MXN. | M34: Uso de activos virtuales para estratificar u ocultar el origen de recursos. | N34: Anonimato y dificultad de trazabilidad; operacion transfronteriza. | O34: Riesgo de LD/FT, sanciones y bloqueo de cuentas; deteccion por UIF.
B35: 30 | C35: XVI | D35: Activos virtuales (PSAV): cobro de contraprestación (comisión) por el servicio | E35: XVI - Activos virtuales (PSAV): cobro de contraprestación (comisión) por el servicio | F35: Siempre | G35: 4 | H35: =IF(ISNUMBER($F35),$F35*PARAMETROS!$C$22,$F35) | I35: =IF(ISNUMBER($G35),$G35*PARAMETROS!$C$22,$G35) | J35: Cobro de comisiones a clientes de alto riesgo o en efectivo, sin trazabilidad del pago. | K35: Comisiones con pagos mixtos e identificacion parcial. | L35: Comisiones cobradas por medios trazables con cliente identificado. | M35: Uso del cobro de comisiones para justificar flujos o fragmentar operaciones. | N35: Falta de trazabilidad en el cobro y bajo umbral de deteccion (4 UMA). | O35: Riesgo de simulacion y de omitir operaciones sujetas a aviso.

Sheet BASE
B2: BASE · 30 actividades × 25 indicadores = 750 perfiles
B3: Referencia: 30 Actividades Vulnerables × 25 indicadores. No se edita.
A5: Clave | B5: Actividad | C5: Núm. | D5: Indicador | E5: Perfil ALTO | F5: Perfil MEDIO | G5: Perfil BAJO | H5: De dónde sale
A6: =B6&"-"&C6 | B6: I - Juegos con apuesta | C6: 1 | D6: Valor unitario de la operación | E6: La ficha o el saldo de juego tiene un valor unitario muy por encima del ticket promedio de tu operación de doce meses. | F6: La ficha o el saldo de juego tiene un valor unitario dentro del rango habitual de tu operación. | G6: La ficha o el saldo de juego tiene un valor unitario por debajo de tu ticket promedio. | H6: calculado
A7: =B7&"-"&C7 | B7: I - Juegos con apuesta | C7: 2 | D7: Liquidez: facilidad de convertir en dinero | E7: La ficha o el saldo de juego puede revenderse o cederse de inmediato y prácticamente a su valor íntegro. | F7: La ficha o el saldo de juego puede revenderse, pero con trámite, plazo o pérdida de valor apreciable. | G7: La ficha o el saldo de juego es difícil de revender: exige formalidades o registro, o pierde valor de forma significativa. | H7: bandera
A8: =B8&"-"&C8 | B8: I - Juegos con apuesta | C8: 3 | D8: Anonimato: si el beneficiario queda a la vista | E8: La compra o el cobro de fichas admite que quien aparece no sea quien recibe el beneficio, sin que quede registro de quién es el beneficiario final. | F8: Se identifica a el jugador, pero el beneficiario final se declara sin documento que lo respalde. | G8: El jugador y el beneficiario final coinciden, y ambos constan en el expediente. | H8: bandera
A9: =B9&"-"&C9 | B9: I - Juegos con apuesta | C9: 4 | D9: Ocultamiento de valor en el precio | E9: La compra o el cobro de fichas admite sobrevaluar, subvaluar o fraccionar el precio sin que la contabilidad lo refleje. | F9: El precio se aparta del valor de referencia, pero existe explicación documentada de la diferencia. | G9: El precio corresponde al valor de referencia y queda registrado en la contabilidad. | H9: bandera
A10: =B10&"-"&C10 | B10: I - Juegos con apuesta | C10: 5 | D10: Exposición a personas señaladas por terrorismo | E10: El jugador, su beneficiario o su contraparte aparece en listas de sanciones o de organizaciones terroristas. | F10: Existe un vínculo indirecto —contraparte, domicilio o ruta de los fondos— con una jurisdicción en conflicto o de acción requerida. | G10: Sin coincidencias ni vínculos con esas listas ni con jurisdicciones en conflicto, con búsqueda documentada. | H10: campo
A11: =B11&"-"&C11 | B11: I - Juegos con apuesta | C11: 6 | D11: Tipo de persona | E11: El jugador es un fideicomiso u otro vehículo sin personalidad jurídica propia. No hay un titular único: la figura permite que quien apuesta y quien cobra el premio sean personas distintas y que ninguna aparezca en el contrato. | F11: El jugador es persona moral. La voluntad se forma en órganos y la propiedad está en socios, así que hay que llegar al Beneficiario Controlador para saber quién está realmente detrás. | G11: El jugador es persona física. Coincide quien apuesta y quien cobra el premio, y la identificación es directa contra un solo expediente. | H11: campo
A12: =B12&"-"&C12 | B12: I - Juegos con apuesta | C12: 7 | D12: Antigüedad del Cliente | E12: Persona moral constituida hace menos de dos años, o persona física menor de veintitrés años. | F12: Persona moral constituida hace entre dos y cinco años. | G12: Persona moral con más de cinco años de constituida, o persona física de veintitrés años en adelante. | H12: campo
A13: =B13&"-"&C13 | B13: I - Juegos con apuesta | C13: 8 | D13: Giro o actividad declarada | E13: El giro que declara el jugador es a su vez una Actividad Vulnerable del artículo 17, o no se acredita con documento alguno. | F13: El giro se declara y se acredita sólo de forma parcial. | G13: El giro se acredita con documento: constancia de situación fiscal, acta constitutiva o comprobante de empleo. | H13: campo
A14: =B14&"-"&C14 | B14: I - Juegos con apuesta | C14: 9 | D14: Nacionalidad | E14: Nacionalidad de país o jurisdicción señalada por la UIF, o no determinada. | F14: Nacionalidad extranjera de país sin señalamiento. | G14: Nacionalidad mexicana. | H14: campo
A15: =B15&"-"&C15 | B15: I - Juegos con apuesta | C15: 10 | D15: País y entidad de residencia | E15: Residencia en jurisdicción de régimen fiscal preferente o señalada por deficiencias, o domicilio no verificable. | F15: Residencia en el extranjero sin señalamiento, o en entidad federativa señalada en la ENR. | G15: Residencia en México, en entidad federativa sin señalamiento en la ENR. | H15: campo
A16: =B16&"-"&C16 | B16: I - Juegos con apuesta | C16: 11 | D16: Condición de Persona Políticamente Expuesta | E16: Persona Políticamente Expuesta extranjera, o nacional cuyo comportamiento transaccional no corresponde con sus ingresos y funciones. | F16: Persona Políticamente Expuesta nacional con comportamiento congruente, o familiar o allegado de una. | G16: Sin condición de Persona Políticamente Expuesta, con búsqueda documentada. | H16: campo
A17: =B17&"-"&C17 | B17: I - Juegos con apuesta | C17: 12 | D17: Resultado de la búsqueda en listas | E17: Coincidencia positiva en listas de personas bloqueadas o de sanciones, o búsqueda no realizada o sin constancia. | F17: Coincidencia descartada por homonimia acreditada, con constancia. | G17: Sin coincidencia, con constancia de la búsqueda y su fecha. | H17: campo
... A755: =B755&"-"&C755 | B755: XVI - Activos virtuales (PSAV): cobro de contraprestación (comisión) por el servicio | C755: 25 | D755: Combinación de canal e instrumento idónea para el financiamiento al terrorismo | E755: El cobro de la contraprestación combina contratación a distancia sin verificación reforzada con pagos en efectivo o instrumentos al portador. | F755: Concurre uno solo de los dos: o la contratación remota sin verificación reforzada, o el pago en instrumento no bancarizado. | G755: Ni la forma de contratar ni la de pagar permiten mover valor de forma anónima. | H755: bandera
